Workbook
Name CPDK: DVDK!$C$4:$D$399
Name ECVAN: Data!$B$29:$B$30
Name HERIO: Data!$B$5
Name LAC.HONG: Data!$B$27:$B$28
Name LIMO: Data!$B$13
Name MANHOM: Data!$J$2:$J$13
Name MANHOM1: Data!$J$2:$J$13
Name MANHOMDOIXE: Data!$AH$14:$AH$15
Name MANHOMKV: Data!$AH$2:$AH$8
Name MINIO: Data!$B$2
Name NAM: Data!#REF!
Name NERIO: Data!$B$8
Name TAY: Data!#REF!
Name TONGHOP: '[1]1.DT'!$A$2:$CA$202
Name TRUNG: Data!#REF!
Name VF.3: Data!$B$3:$B$4
Name VF.5: Data!$B$6:$B$7
Name VF.6: Data!$B$9:$B$12
Name VF.7: Data!$B$14:$B$18
Name VF.8: Data!$B$19:$B$21
Name VF.9: Data!$B$22:$B$26

Sheet All Info
A1: GIÁ XE | B1: LÃI SUẤT | C1: SỐ TIỀN HẰNG THÁNG
C2: 0.1 | F2: 0.15 | I2: 0.2
C3: 7Y | D3: 6Y | E3: 5Y | F3: 7Y | G3: 6Y | H3: 5Y | I3: 7Y | J3: 6Y | K3: 5Y
C4: TPBank
A5: 1155000000 | B5: 0.12 | C5: =#REF!+#REF! -> #REF! | D5: =#REF!+#REF! -> #REF! | E5: =#REF!+#REF! -> #REF! | F5: =#REF!+#REF! -> #REF! | G5: =#REF!+#REF! -> #REF! | H5: =#REF!+#REF! -> #REF! | I5: =#REF! -> #REF! | J5: =#REF! -> #REF! | K5: =#REF! -> #REF!
C6: 15% | G6: 20%
C7: 4Y | D7: 5Y | E7: 6Y | F7: 7Y | G7: 4Y | H7: 5Y | I7: 6Y | J7: 7Y | K7: 8Y
C8: Other Bank
B9: 0.12 | C9: =#REF! -> #REF! | D9: =#REF! -> #REF! | E9: =#REF! -> #REF! | F9: =#REF! -> #REF! | G9: =#REF! -> #REF! | H9: =#REF! -> #REF! | I9: =#REF! -> #REF! | J9: =#REF! -> #REF! | K9: =#REF! -> #REF!

Sheet BG New
A2: =VLOOKUP(L13,Data!A35:B45,2,0) -> #VALUE! | E2: THÔNG SỐ CƠ BẢN | F2: #VALUE! | G2: =UPPER(Z25) -> QUÃNG ĐƯỜNG DI CHUYỂN DỰ KIẾN 496KM | K2: Khung thuế HCM | L2: =V16 -> 0 | N2: TRA CỨU ĐỊA CHỈ ĐĂNG KÝ XE | Q2: KHÔNG XE | R2: CP ỨNG | S2: LƯU Ý THUẾ ĐĂNG KÝ XE
K3: Lệch | L3: =G26-L2 -> 0 | Q3: Không xe | R3: 1500000
F4: #VALUE! | G4: =UPPER(Z20) -> THỜI GIAN NẠP PIN (10 - 70%) < 28 PHÚT | K4: Disble ! | Q4: Xe | R4: 1500000
F6: #VALUE! | G6: =UPPER(Z22) -> CÔNG SUẤT TỐI ĐA 150 KW/201 HP | K6: Disble !
K7: Disble !
F8: #VALUE! | G8: =UPPER(Z23) -> LAZANG 20 INCH
N9: Hưng
A10: =UPPER(L14) -> VINFAST VF7 PLUS (TC) - THÉP | F10: #VALUE! | G10: =UPPER(Z24) -> TRANG BỊ 08 TÚI KHÍ | Q10: Không xe | R10: 1000000
K11: =V13 -> 949000000 | Q11: Không xe | R11: 1500000 | V11: 0
A12: =UPPER("các chương trình khuyến mãi & giá lăn bánh") -> CÁC CHƯƠNG TRÌNH KHUYẾN MÃI & GIÁ LĂN BÁNH | K12: VIP | Q12: 6000000 | R12: 1500000 | T12: 1500000
C13: GIÁ NIÊM YẾT (ĐÃ BAO GỒM PIN) | G13: GIÁ KHUYẾN MÃI | K13: Dòng xe | L13: VF.7 | N13: Khu vực | O13: Tiền gốc | P13: Tình trạng | Q13: 6000000 | R13: 1500000 | T13: 2000000 | V13: =VLOOKUP(L14,Data!B2:C29,2,0) -> 949000000 | X13: Thu cũ đổi mới | Z13: Lương | AA13: Vinclub
K14: Loại xe : | L14: Vinfast VF7 Plus (TC) - Thép | N14: =DVDK!J4 -> [Hà Tĩnh] Hưng Khê | O14: =DVDK!K4 -> 10000000 | P14: =DVDK!L4 -> 0 | Q14: Xe | T14: 2500000 | V14: =VLOOKUP(L14,Data!F2:G29,2,0) -> 0 | X14: =VLOOKUP(L14,Data!AB2:AC30,2,0) -> 50000000 | Z14: =VLOOKUP(L14,Data!T2:U30,2,0) -> 20000000 | AA14: =VLOOKUP(L14,Data!Z2:AA30,2,0) -> 35000000
C15: =TEXT(V13, "#.##0")& " VNĐ" -> 949.000.000 VNĐ | G15: =V13 -> 949000000 | I15: VNĐ | K15: Trả trước VPBank : | L15: 0.1 | N15: =DVDK!J5 | O15: =DVDK!K5 -> #N/A | P15: =DVDK!L5 -> #N/A | Q15: 7000000 | T15: 3000000 | U15: 531000 | V15: =VLOOKUP(L14,Data!N2:O29,2,0) -> 949000000 | W15: =VLOOKUP(L14,Data!AM2:AN29,2,0) -> 911040000 | Z15: Thưởng | AA15: Biên
N16: =DVDK!J6 | O16: =DVDK!K6 -> #N/A | P16: =DVDK!L6 -> #N/A | Q16: 6000000 | R16: 3300000 | T16: 4000000 | U16: 847000 | V16: =VLOOKUP(L14,Data!AE2:AF29,2,0) -> 0 | Z16: =VLOOKUP(L14,Data!V2:W30,2,0) -> 10000000 | AA16: =VLOOKUP(L14,Data!X2:Y30,2,0) -> 15000000
K17: Trả trước Shinhan : | N17: =DVDK!J7 | O17: =DVDK!K7 -> #N/A | P17: =DVDK!L7 -> #N/A | T17: 4500000 | U17: 944000
C18: CÁC CHƯƠNG TRÌNH KHUYẾN MÃI | L18: 0.2 | N18: =DVDK!J8 | O18: =DVDK!K8 -> #N/A | P18: =DVDK!L8 -> #N/A | T18: 5000000 | U18: 1205000
N19: =DVDK!J9 | T19: 5500000 | U19: 1429000
C20: ● Ưu đãi giảm giá xe 4% | G20: =G15-H20 -> 911040000 | H20: =L31 -> 37960000 | I20: VNĐ | N20: =DVDK!J10 | T20: 6000000 | U20: 3240000 | Z20: =VLOOKUP(L14,Data!BC2:BD30,2,0) -> Thời gian nạp pin (10 - 70%) < 28 phút
C21: ● Ưu đãi 3% dành cho Công An & Quân Đội (nếu có) | G21: =G20-H21 -> 911040000 | I21: =IF(H21="","-","VNĐ") -> -
C22: ● Thu cũ đổi mới (nếu có) | G22: =G21-H22 -> 911040000 | I22: =IF(H22="","-","VNĐ") -> - | T22: 6500000 | V22: =V13-V15 -> 0 | W22: =V13-W15 -> 37960000 | Z22: =VLOOKUP(L14,Data!BE2:BF30,2,0) -> Công suất tối đa 150 kW/201 hp
C23: ● Khách hàng thân thiết (nếu có) | G23: =G22-H23 -> 911040000 | I23: =IF(H23="","-","VNĐ") -> - | K23: VinClub | L23: =AA14 -> 35000000 | V23: =VLOOKUP(L14,Data!AP2:AQ29,2,0) -> Miễn phí sạc 02 năm tại VGreen | Z23: =VLOOKUP(L14,Data!BG2:BH30,2,0) -> Lazang 20 Inch
C24: ● Quy đổi bảo hiểm (áp dụng cho VF3 & VF5) | I24: =IF(H24="","-","VNĐ") -> - | K24: Thưởng | M24: =Z16 -> 10000000 | N24: Tips : Xác định nhu cầu khách hàn | Z24: =VLOOKUP(L14,Data!BI2:BJ30,2,0) -> Trang bị 08 túi khí
C25: ● Ưu đãi khác | G25: =G23-H25 -> 846040000 | H25: 65000000 | I25: =IF(H25="","-","VNĐ") -> VNĐ | K25: Lương | L25: =Z14 -> 20000000 | N25: 1. Anh/ chị có dự định nhận xe trong tháng không hay mình tham khảo trước để em tư vấn anh/ chị luôn ạ ! | Q25: Xe | R25: 5000000 | V25: =VLOOKUP(L14,Data!AR2:AS29,2,0) -> Miễn phí bãi đổ xe và ưu tiên hệ sinh thái VINGROUP | Z25: =VLOOKUP(L14,Data!BK2:BL30,2,0) -> Quãng đường di chuyển dự kiến 496Km
C26: GIÁ CUỐI CÙNG | H26: =$G$25 -> 846040000 | I26: =IF(H26="","-","VNĐ") -> VNĐ | K26: BẢO HIỂM VC XE | L26: 0 | N26: 2. Dạ vậy để tiện cho anh trải nghiệm thực tế trước khi quyết định em đem xe cho Anh/ chị lái thử để cảm nhận luôn nha ! | Q26: 10000000 | R26: 7500000 | T26: 10000000 | V26: =VLOOKUP(L14,Data!AT2:AU29,2,0) -> 0
N27: 3. Trong tuần này Anh/chị có rãnh không ạ, sắp xếp ghé qua Showroom em, sẵn tiện xem xe và em tư vấn kỹ hơn về xe và ngân hàng luôn | Q27: 10000000 | R27: 7000000 | T27: 15000000 | V27: =VLOOKUP(L14,Data!AV2:AW29,2,0) -> 0
K28: Thuế HN tăng thêm : | L28: =U71-G26 -> 0 | N28: Tin nhắn nhanh | R28: 5000000 | T28: 20000000 | V28: =VLOOKUP(L14,Data!AX2:AY29,2,0) -> 0 | W28: =VLOOKUP(L14,Data!AX2:AY29,2,0) -> 0
C29: CHI PHÍ LĂN BÁNH | K29: Thu cũ đổi mới | L29: =X14 -> 50000000 | N29: Dạ mình đã chọn được phiên bản nào chưa ạ, nếu chưa để e tư vấn cho mình thêm để dễ so sánh các bản | R29: 5000000 | T29: 25000000 | U29: 20000000 | V29: =VLOOKUP(L14,Data!#REF!,2,0) -> #REF!
K30: Giá gốc : | L30: =V13 -> 949000000 | N30: Dạ mình tham kháo giá và chương trình khuyến mãi để cân nhắc lấy xe đúng không ạ | Q30: Không xe | R30: 5000000 | T30: 30000000 | U30: 14000000 | V30: =VLOOKUP(L14,Data!AZ2:BA29,2,0) -> 0
C31: 1. Thuế bạ | H31: Miễn phí | K31: Giảm giá : | L31: =IF(L33>L34,L33,L34) -> 37960000 | N31: Mình tham khảo lấy xe lăn bánh biển số về đâu ạ, để e tính cho mình bảng giá chi tiết tham khảo cho dễ | Q31: Xe | R31: 5000000 | T31: 35000000 | U31: 1000000
C32: 2. Lệ phí đăng kí biển số (thu theo biên lai nhà nước) | H32: 20000000 | I32: =IF(H32="","-","VNĐ") -> VNĐ | K32: Điều chỉnh giá : | N32: Mình dự định mua tiền may luôn hay là chọn hình thức trả góp ạ, bên e có hỗ trợ trả góp tối đa lên tới 85% luôn ạ | R32: 5000000 | T32: 40000000 | U32: 200000 | V32: Trắng | W32: - 5L Nguyên liệu
C33: 3. Phí đường bộ (thu theo biên lai nhà nước) | H33: 1560000 | I33: =IF(H33="","-","VNĐ") -> VNĐ | K33: Chương Trình 2024 : | L33: =V22 -> 0 | M33: =L33-L34 -> -37960000 | N33: Lãi Vay các bank : - TRả trước: 20 % trở lên - Lãi suất : + VPBank (Không cần CM thu nhập) : 6.9%/ 2 năm / Thả nổi cỡ 12% (Cần mua BH khoản vay ~ 1.5% giá trị vay) + Lotte (Có CM Thu nhập) : 6.9%/ 2 năm / Thả nổi cỡ 12% (Không cần mua BH khoản vay) + Sacombank : 6.5%/ 2 năm / Thả nổi cỡ 12% (Không cần mua BH khoản vay) + TPBank : 6.5%/ 2 năm / Thả nổi cỡ 12% (cần mua BH khoản vay) Bank nước ngoài như Shinhan : 4.8% / cố định 3 năm Thả nổi cỡ : 10.25% Cần CM thu nhập (NH Nước ngoài không ưu tiên hồ sơ nhỏ nên có thể sẽ cần mua bảo hiêm) | T33: 45000000 | W33: - Bộ lên kiếng tự động
C34: 4. Lệ phí cấp sổ đăng kiểm (thu theo biên lai nhà nước) | H34: 94680 | I34: =IF(H34="","-","VNĐ") -> VNĐ | K34: Chương Trình 2025 : | L34: =W22 -> 37960000 | Q34: Không xe | R34: 5000000 | T34: 50000000 | U34: 0 | V34: Bạc | W34: - Dán phim cách nhiệt Bh 10 Năm
C35: 5. Bảo hiểm trách nhiệm dân sự + người ngồi trên xe | H35: 531000 | I35: =IF(H35="","-","VNĐ") -> VNĐ | K35: Biên nhà máy | L35: =AA16 -> 15000000 | Q35: Không xe | R35: 5000000 | T35: 60000000 | U35: 0.01 | V35: Đỏ | W35: - Lót sàn cách âm , chống cháy
C36: 6. Bảo hiểm vật chất xe/năm | H36: =L26*H26 -> 0 | I36: =IF(H36="","-","VNĐ") -> VNĐ | Q36: Không xe | R36: 5000000 | U36: 0.011 | V36: Đen | W36: - Lót sàn 5D
C37: 7. Dịch vụ đăng ký xe | H37: 3000000 | I37: =IF(H37="","-","VNĐ") -> VNĐ | Q37: Không xe | R37: 5000000 | U37: 0.012 | V37: Vàng cát | W37: - Camera hành trình
C38: TỔNG CỘNG | H38: =SUM($H$32:$H$37) -> 25185680 | I38: =IF(H38="","-","VNĐ") -> VNĐ | K38: TRUE | L38: =IF(OR(L13="VF.9", L13="LIMO"), 1, 0) -> 0 | Q38: 6000000 | R38: 5000000 | U38: 0.013 | V38: Vàng be | W38: - Thẻ nhớ hành trình
C39: TỔNG CỘNG | D39: (GIÁ XE SAU KHUYẾN MÃI + CHI PHÍ ĐĂNG KÝ) | H39: =$H$26+$H$38-$H$24 -> 871225680 | I39: VNĐ | K39: FALSE | Q39: Xe | R39: 5000000 | U39: 0.014 | V39: Xanh | W39: - Tẩu sạc USB
K40: Ngân hàng cho vay : | L40: 375000000 | Q40: 7000000 | R40: 5000000 | U40: 0.015 | V40: Cam | W40: - Phủ gầm
K41: Chênh lệch | L41: =L40-G40 -> 375000000 | Q41: 7000000 | R41: 6000000 | U41: 0.016 | V41: Xanh chuối | W41: - Phủ Ceramic
Q42: 7000000 | R42: 5000000 | U42: 0.017 | W42: - Viền che mưa
A43: ƯU ĐÃI HẬU MÃI | B43: =UPPER(("Bảo hành 07 năm hoặc 160.000 Km và 10 năm hoặc 200.000 Km đối với VF7, VF9")) -> BẢO HÀNH 07 NĂM HOẶC 160.000 KM VÀ 10 NĂM HOẶC 200.000 KM ĐỐI VỚI VF7, VF9 | Q43: 7000000 | R43: 5000000 | U43: 0.018 | W43: - Bệ bước chân cao cấp
N44: Mình có dự định lấy xe trong tháng luôn chưa ạ hay dự định quá tháng mới lấy xe ạ
B45: =UPPER(("PIN bảo hành 08 năm và không giới hạn Km")) -> PIN BẢO HÀNH 08 NĂM VÀ KHÔNG GIỚI HẠN KM
N46: Bước 1 : Đặt cọc tối thiểu 10tr để lên HĐ mua bán chính thức Bước 2 : Bên Em sẽ tiến hành đem HĐ bản chính qua cho mình Bước 3 : Trong thời gian đó bên e sẽ có BP hỗ trợ ngân hàng làm việc với bên mình + TH 1 : Làm NH không được bên e sẽ back lại 100% tiền cọc + TH 2 : Làm NH okay 2 bên sẽ tiến hành bước tiếp theo của HĐ Bước 4 : Sau khi Ngân hàng ra thư cho vay bên Mua sẽ tiến hành thanh toán tiền đối ứng cho bên A (bên bán) Bước 5 : Bên Bán sẽ tiến hành làm thủ tục ra biển số (Dự kiến 3- 5 ngày) Bước 6 : Bên Bán sẽ báo bên Mua về thủ tục bấm số ra biển => Sau khi hoàn thành bên Bán sẽ gửi toàn bộ giấy tờ về Ngân hàng Bước 7 : Ngân hàng gọi bên Mua lên ký giấy tờ giải ngân => Tiền giải ngân vào tài khoản Hyundai => Bên Mua nhận xe và hoàn tất HĐ | Q46: 7000000 | R46: 5000000 | U46: 0.019 | W46: - Hộp đen kinh doanh
B47: =UPPER("Tặng "&TEXT(L23,"#.##0")&" Point VINCLUB (Áp dụng Khách hàng ở TP.HCM & Hà Nội) - Chỉ áp dụng gói vay thông thường") -> TẶNG 35.000.000 POINT VINCLUB (ÁP DỤNG KHÁCH HÀNG Ở TP.HCM & HÀ NỘI) - CHỈ ÁP DỤNG GÓI VAY THÔNG THƯỜNG | Q47: 8000000 | R47: 1500000 | U47: 0.02 | W47: - Gói bảo hành nâng cấp 05 năm
Q48: 7000000 | R48: 5000000 | U48: 0.023 | W48: - Thảm taplo
B49: =UPPER("Miễn phí gửi xe và đỗ xe ưu tiên tại các điểm thuộc hệ sinh thái VINGROUP") -> MIỄN PHÍ GỬI XE VÀ ĐỖ XE ƯU TIÊN TẠI CÁC ĐIỂM THUỘC HỆ SINH THÁI VINGROUP | Q49: 7000000 | R49: 5000000 | U49: 0.025
Q50: 7000000 | R50: 5000000 | U50: 0.028
B51: =UPPER("Miễn phí sạc 02 năm tại các trạm V-Green tới tháng 07/2027") -> MIỄN PHÍ SẠC 02 NĂM TẠI CÁC TRẠM V-GREEN TỚI THÁNG 07/2027 | Q51: 7000000 | R51: 5000000 | U51: 0.03
R52: 5000000
A53: DỰ TÍNH NGÂN HÀNG | B53: #VALUE! | D53: THANH TOÁN | G53: #VALUE! | H53: THANH TOÁN | Q53: Không xe | R53: 6500000
D54: =$H$26*$L$15+$H$38-$H$24 -> 109789680 | F54: VNĐ | H54: =$H$26*$L$18+$H$38-$H$24 -> 194393680 | I54: VNĐ
B55: =" CÒN LẠI "&TEXT($H$26*(100%-$L$15), "#.##0") & " GÓP HẰNG THÁNG" -> CÒN LẠI 761.436.000 GÓP HẰNG THÁNG | G55: =" CÒN LẠI "&TEXT($H$26*(100%-$L$18), "#.##0") & " GÓP HẰNG THÁNG" -> CÒN LẠI 676.832.000 GÓP HẰNG THÁNG
Q56: Không xe | R56: 5000000
C57: 03 NĂM | D57: =BG03Y!F11 -> 25675199 | F57: VNĐ | G57: 03 NĂM | H57: ='Bank 2'!F11 -> 21598461 | I57: VNĐ | R57: 6500000
C58: 04 NĂM | D58: =BG04Y!F11 -> 20387449 | F58: VNĐ | G58: =C58 -> 04 NĂM | H58: ='Bank 2'!M11 -> 16898239 | I58: VNĐ
C59: 05 NĂM | D59: =BG05Y!F11 -> 17214799 | F59: VNĐ | G59: =C59 -> 05 NĂM | H59: ='Bank 2'!T11 -> 14078106 | I59: VNĐ
C60: 06 NĂM | D60: =BG06Y!F11 -> 15099699 | F60: VNĐ | G60: =C60 -> 06 NĂM | H60: ='Bank 2'!AA11 -> 12198017 | I60: VNĐ
C61: 07 NĂM | D61: =BG07Y!F11 -> 13588913 | F61: VNĐ | G61: =C61 -> 07 NĂM | H61: ='Bank 2'!AH11 -> 10855096 | I61: VNĐ | Q61: Không xe | R61: 8000000
C62: 08 NĂM | D62: =BG08Y!F11 -> 12455824 | F62: VNĐ | G62: =C62 -> 08 NĂM | H62: ='Bank 2'!AO11 -> 9847905.6 | I62: VNĐ | Q62: Không xe | R62: 5000000
C63: Số tiền dự tính hằng tháng trên là tạm tính, số tiền trả hằng tháng sẽ giảm dần theo dư nợ (tháng sau ít hơn tháng trước) | Q63: Không xe | R63: 5000000 | U63: 1560000 | V63: 10 Ngày
Q64: Không xe | R64: 5000000 | U64: 2160000 | V64: 10-15 Ngày
Q65: Không xe | R65: 6500000 | U65: 3389000 | V65: 15-25 Ngày
H66: =H26*L15 -> 84604000 | Q66: Không xe | R66: 6500000 | V66: 20-30 Ngày
Q67: Không xe | R67: 6500000 | V67: 30 - 45 Ngày
Q68: Không xe | R68: 6500000 | V68: 45 - 60 Ngày
Q69: Không xe | R69: 6500000 | V69: 60 - 75 Ngày
H70: =$H$26*(100%-$L$18) -> 676832000 | Q70: Không xe | R70: 6500000 | V70: 75 - 90 Ngày
Q71: Không xe | R71: 12000000
Q72: Không xe | R72: 6500000
T86: 23

Sheet Config

Sheet Báo giá
E1: =NOW() -> 45958.743 | F1: Khung thuế HCM | G1: =Q10 -> 0 | I1: TRA CỨU ĐỊA CHỈ ĐĂNG KÝ XE | L1: KHÔNG XE | M1: CP ỨNG | N1: LƯU Ý THUẾ ĐĂNG KÝ XE
D2: Code quà tặng giảm giá : | E2: =RAND()*99999999999 -> 7.9617732e+10 | F2: Lệch | G2: =D19-G1 -> 0 | L2: Không xe | M2: 1500000
G3: ss | L3: Xe | M3: 1500000
A4: BẢNG GIÁ TẠM TÍNH | G4: ss | L4: Không xe | M4: 1000000
A5: - Bảng báo giá chỉ có hiệu lực 24h từ lúc phát hành - Bảng tạm tính các chi phí có liên quan sẽ hoàn lại nếu dư sau khi có hóa đơn - Các mã quà tặng và khuyến mãi sẽ tùy thời điểm nhận xe - Thời gian hiệu lực của mã quà tặng sẽ có hiệu lục 48h sau khi kích hoạt - Lưu ý : phần thanh toán ngân hàng là tạm tính theo mức lãi cao nhất hiện tại, quý khách có đủ điều kiện vay ngân hàng tốt hơn lãi sẽ tốt hơn | F5: =Q7 -> 299000000 | L5: Không xe | M5: 1500000 | Q5: 0
A6: Kính gửi : | B6: =F6 -> VIP | F6: VIP | L6: 6000000 | M6: 1500000 | O6: 1500000
A7: Loại xe : | B7: =G8&" (GIÁ ĐÃ BAO GỒM PIN)" -> Vinfast VF3 (GIÁ ĐÃ BAO GỒM PIN) | F7: Dòng xe | G7: VF.3 | I7: Khu vực | J7: Tiền gốc | K7: Tình trạng | L7: 6000000 | M7: 1500000 | O7: 2000000 | Q7: =VLOOKUP(G8,Data!B2:C29,2,0) -> 299000000 | S7: Thu cũ đổi mới | U7: Lương | V7: Vinclub
A8: GIÁ NIÊM YẾT | C8: =Q7 -> 299000000 | E8: VND | F8: Loại xe : | G8: Vinfast VF3 | I8: =DVDK!J4 -> [Hà Tĩnh] Hưng Khê | J8: =DVDK!K4 -> 10000000 | K8: =DVDK!L4 -> 0 | L8: Xe | O8: 2500000 | Q8: =VLOOKUP(G8,Data!F2:G29,2,0) -> 0 | S8: =VLOOKUP(G8,Data!AB2:AC30,2,0) -> 5000000 | U8: =VLOOKUP(G8,Data!T2:U30,2,0) -> 6000000 | V8: =VLOOKUP(G8,Data!Z2:AA30,2,0) -> 6000000
A9: CÁC CHƯƠNG TRÌNH KHUYẾN MÃI | F9: Trả trước : | G9: 0.15 | I9: =DVDK!J5 | J9: =DVDK!K5 -> #N/A | K9: =DVDK!L5 -> #N/A | L9: 7000000 | O9: 3000000 | P9: 531000 | Q9: =VLOOKUP(G8,Data!N2:O29,2,0) -> 299000000 | R9: =VLOOKUP(G8,Data!AM2:AN29,2,0) -> 287040000 | U9: Thưởng | V9: Biên
A10: =" 1. "&"ƯU ĐÃI GIẢM 4%/ GIÁ XE" -> 1. ƯU ĐÃI GIẢM 4%/ GIÁ XE | D10: =G24-G25 -> 11960000 | E10: =$C$8-D10 -> 287040000 | F10: Tổng tiền đưa trước | G10: =D36 -> 64821200 | I10: =DVDK!J6 | J10: =DVDK!K6 -> #N/A | K10: =DVDK!L6 -> #N/A | L10: 6000000 | M10: 3300000 | O10: 4000000 | P10: 847000 | Q10: =VLOOKUP(G8,Data!AE2:AF29,2,0) -> 0 | U10: =VLOOKUP(G8,Data!V2:W30,2,0) -> 4000000 | V10: =VLOOKUP(G8,Data!X2:Y30,2,0) -> 6000000
A11: =" 2."&" XE VIN 24 (NẾU CÓ)" -> 2. XE VIN 24 (NẾU CÓ) | E11: =E10-D11 -> 287040000 | I11: =DVDK!J7 | J11: =DVDK!K7 -> #N/A | K11: =DVDK!L7 -> #N/A | O11: 4500000 | P11: 944000
A12: =" 2. "&" CHƯƠNG TRÌNH THU CŨ ĐỔI MỚI" -> 2. CHƯƠNG TRÌNH THU CŨ ĐỔI MỚI | E12: =E11-D12 -> 287040000 | I12: =DVDK!J8 | J12: =DVDK!K8 -> #N/A | K12: =DVDK!L8 -> #N/A | O12: 5000000 | P12: 1205000
A13: =" 3. "&" KHÁCH HÀNG THÂN THIẾT" -> 3. KHÁCH HÀNG THÂN THIẾT | E13: =E12-D13 -> 287040000 | I13: =DVDK!J9 | J13: =DVDK!K9 -> #N/A | K13: =DVDK!L9 -> #N/A | O13: 5500000 | P13: 1429000
A14: =" 4."&" CHƯƠNG TRÌNH QUY ĐỔI BẢO HIỂM" -> 4. CHƯƠNG TRÌNH QUY ĐỔI BẢO HIỂM | D14: 6500000 | I14: =DVDK!J10 | J14: =DVDK!K10 -> #N/A | K14: =DVDK!L10 -> #N/A | O14: 6000000 | P14: 3240000
A15: 5. ƯU ĐÃI ĐẶC BIỆT | D15: 4000000 | E15: =E13-D15 -> 283040000 | I15: =DVDK!J11 | J15: =DVDK!K11 -> #N/A | K15: =DVDK!L11 -> #N/A | O15: 6500000 | Q15: =Q7-Q9 -> 0 | R15: =Q7-R9 -> 11960000
A16: GIÁ XE SAU KHUYẾN MÃI | D16: =E15 -> 283040000 | E16: VND | F16: VinClub | G16: =V8 -> 6000000 | Q16: =VLOOKUP(G8,Data!AP2:AQ29,2,0) -> Miễn phí sạc 02 năm tại VGreen
F17: Thưởng | H17: =U10 -> 4000000
A18: STT | B18: CÁC KHOẢN LỆ PHÍ (Hoàn trả lại nếu dư) | D18: THÀNH TIỀN | F18: Lương | G18: =U8 -> 6000000 | L18: Xe | M18: 5000000 | Q18: =VLOOKUP(G8,Data!AR2:AS29,2,0) -> Miễn phí bãi đổ xe và ưu tiên hệ sinh thái VINGROUP
A19: 1 | B19: Thuế trước bạ tam tính (miễn phí) | D19: =(Q8-E19) -> 0 | L19: 10000000 | M19: 7500000 | O19: 10000000 | Q19: =VLOOKUP(G8,Data!AT2:AU29,2,0) -> 0
A20: 2 | B20: Lệ phí đăng kí biển số (thu theo biên lai nhà nước) | D20: 20000000 | L20: 10000000 | M20: 7000000 | O20: 15000000 | Q20: =VLOOKUP(G8,Data!AV2:AW29,2,0) -> 0
A21: 3 | B21: Phí đường bộ (thu theo biên lai nhà nước) | D21: 1560000 | F21: Thuế HN tăng thêm : | G21: =P60-D19 -> 0 | M21: 5000000 | O21: 20000000 | Q21: =VLOOKUP(G8,Data!AX2:AY29,2,0) -> 0 | R21: =VLOOKUP(G8,Data!AX2:AY29,2,0) -> 0
A22: 4 | B22: Lệ phí cấp sổ đăng kiểm (thu theo biên lai nhà nước) | D22: 94680 | F22: Thu cũ đổi mới | G22: =S8 -> 5000000 | M22: 5000000 | O22: 25000000 | P22: 20000000 | Q22: =VLOOKUP(G8,Data!#REF!,2,0) -> #REF!
A23: 5 | B23: Bảo hiểm trách nhiệm dân sự + người ngồi trên xe | D23: =IF(F32=TRUE, P13, IF(F31=TRUE, IF(G31=0, P10, P12), IF(G31=0, P9, P11))) -> 531000 | F23: Giá gốc : | G23: =Q7 -> 299000000 | L23: Không xe | M23: 5000000 | O23: 30000000 | P23: 14000000 | Q23: =VLOOKUP(G8,Data!AZ2:BA29,2,0) -> 0
A24: 6 | B24: Bảo hiểm vật chất xe/năm | C24: 0.013 | D24: =D16*C24 -> 3679520 | F24: Giảm giá : | G24: =IF(G26>G27,G26,G27) -> 11960000 | L24: Xe | M24: 5000000 | O24: 35000000 | P24: 1000000
A25: 7 | B25: Dịch vụ đăng ký xe | D25: 3000000 | F25: Điều chỉnh giá : | M25: 5000000 | O25: 40000000 | P25: 200000 | Q25: Trắng | R25: - 5L Nguyên liệu
A26: 8 | B26: CHƯƠNG TRÌNH GIẢM GIÁ KHÁC | F26: Chương Trình 2024 : | G26: =Q15 -> 0 | H26: =G26-G27 -> -11960000 | O26: 45000000 | R26: - Bộ lên kiếng tự động
A27: Tổng cộng chi phí đăng ký | D27: =SUM(D19:D25) -> 28865200 | F27: Chương Trình 2025 : | G27: =R15 -> 11960000 | L27: Không xe | M27: 5000000 | O27: 50000000 | P27: 0 | Q27: Bạc | R27: - Dán phim cách nhiệt Bh 10 Năm
A28: PHƯƠNG THỨC TRẢ THẲNG | F28: Biên nhà máy | G28: =V10 -> 6000000 | L28: Không xe | M28: 5000000 | O28: 60000000 | P28: 0.01 | Q28: Đỏ | R28: - Lót sàn cách âm , chống cháy
B29: Tiền xe: | D29: =D16 -> 283040000 | L29: Không xe | M29: 5000000 | P29: 0.011 | Q29: Đen | R29: - Lót sàn 5D
B30: Chi phí đăng ký: | D30: =D27 -> 28865200 | L30: Không xe | M30: 5000000 | P30: 0.012 | Q30: Vàng cát | R30: - Camera hành trình
B31: Tổng cộng: | D31: =D29+D30-D14-D26 -> 305405200 | E31: VND | F31: FALSE | G31: =IF(OR(G7="VF.9", G7="LIMO"), 1, 0) -> 0 | L31: 6000000 | M31: 5000000 | P31: 0.013 | Q31: Vàng be | R31: - Thẻ nhớ hành trình
A32: PHƯƠNG THỨC TRẢ QUA NGÂN HÀNG | F32: FALSE | L32: Xe | M32: 5000000 | P32: 0.014 | Q32: Xanh | R32: - Tẩu sạc USB
B33: Vay ngân hàng: | C33: =100%-C34 -> 0.85 | D33: =C33*D16-E33 -> 240584000 | F33: Ngân hàng cho vay : | G33: 375000000 | L33: 7000000 | M33: 5000000 | P33: 0.015 | Q33: Cam | R33: - Phủ gầm
B34: Trả trước: | C34: =G9 -> 0.15 | D34: =D16*G9 -> 42456000 | E34: (1) | F34: Chênh lệch | G34: =G33-D33 -> 134416000 | L34: 7000000 | M34: 6000000 | P34: 0.016 | Q34: Xanh chuối | R34: - Phủ Ceramic
B35: Chi phí đăng ký: | D35: =D27 -> 28865200 | E35: (2) | L35: 7000000 | M35: 5000000 | P35: 0.017 | R35: - Viền che mưa
B36: Tổng cộng (1) + (2) | D36: =D35+D34-D14-D26 -> 64821200 | E36: VND | F36: Tips : Xác định nhu cầu khách hàng | L36: 7000000 | M36: 5000000 | P36: 0.018 | R36: - Bệ bước chân cao cấp
F37: 1. Anh/ chị có dự định nhận xe trong tháng không hay mình tham khảo trước để em tư vấn anh/ chị luôn ạ ! | L37: 7000000 | M37: 5000000 | P37: 0.019 | R37: - Hộp đen kinh doanh
A38: BẢO HÀNH | B38: - Bảo hành 10 năm hoặc 200.000 Km tùy điều kiện nào đến trước | C38: THANH TOÁN NGÂN HÀNG | E38: Số tiền /tháng | L38: 8000000 | M38: 1500000 | P38: 0.02 | R38: - Gói bảo hành nâng cấp 05 năm
C39: - Trả góp 03 năm (dư nợ giảm dần) | E39: =BG03Y!F11 -> 25675199 | F39: 2. Dạ vậy để tiện cho anh trải nghiệm thực tế trước khi quyết định em đem xe cho Anh/ chị lái thử để cảm nhận luôn nha ! | L39: 7000000 | M39: 5000000 | P39: 0.023 | R39: - Thảm taplo
B40: - Bảo hành Pin : 8 Năm | C40: - Trả góp 04 năm (dư nợ giảm dần) | E40: =BG04Y!F11 -> 20387449 | L40: 7000000 | M40: 5000000 | P40: 0.025
A41: QUYỀN LỢI | B41: ="Tặng "&TEXT(G16, "#.##0")&" Point VINCLUB (HCM)" -> Tặng 6.000.000 Point VINCLUB (HCM) | C41: - Trả góp 05 năm (dư nợ giảm dần) | E41: =BG05Y!F11 -> 17214799 | L41: 7000000 | M41: 5000000 | P41: 0.028
B42: =Q18 -> Miễn phí bãi đổ xe và ưu tiên hệ sinh thái VINGROUP | C42: - Trả góp 06 năm (dư nợ giảm dần) | E42: =BG06Y!F11 -> 15099699 | F42: 3. Trong tuần này Anh/chị có rãnh không ạ, sắp xếp ghé qua Showroom em, sẵn tiện xem xe và em tư vấn kỹ hơn về xe và ngân hàng luôn | L42: 7000000 | M42: 5000000 | P42: 0.03
C43: - Trả góp 07 năm (dư nợ giảm dần) | E43: =BG07Y!F11 -> 13588913 | M43: 5000000
B44: =Q16 -> Miễn phí sạc 02 năm tại VGreen | C44: - Trả góp 08 năm (dư nợ giảm dần) | E44: =BG08Y!F11 -> 12455824 | L44: Không xe | M44: 6500000
B45: =Q19 -> 0 | C45: Số tiền dự tính hằng tháng trên là tạm tính, số tiền trả hằng tháng sẽ giảm dần theo dư nợ (tháng sau ít hơn tháng trước) | F45: Tin nhắn nhanh | L45: Không xe | M45: 5000000
B46: =Q20 -> 0 | F46: Dạ mình đã chọn được phiên bản nào chưa ạ, nếu chưa để e tư vấn cho mình thêm để dễ so sánh các bản | M46: 6500000
B47: =Q21 -> 0
C48: TẤT TOÁN TRƯỚC HẠN THAM KHẢO | F48: Dạ mình tham kháo giá và chương trình khuyến mãi để cân nhắc lấy xe đúng không ạ
C49: Năm thứ 1 : 4% Năm thứ 3 : 2% Năm thứ 5 : Free Năm thứ 2 : 3% Năm thứ 4 : 1%
F50: Mình tham khảo lấy xe lăn bánh biển số về đâu ạ, để e tính cho mình bảng giá chi tiết tham khảo cho dễ | L50: Không xe | M50: 8000000
L51: Không xe | M51: 5000000
F52: Mình dự định mua tiền may luôn hay là chọn hình thức trả góp ạ, bên e có hỗ trợ trả góp tối đa lên tới 85% luôn ạ | L52: Không xe | M52: 5000000 | P52: 1560000 | Q52: 10 Ngày
L53: Không xe | M53: 5000000 | P53: 2160000 | Q53: 10-15 Ngày
F54: Trả góp thì bên e hiện có 2 hình thức : - Ngân hàng nước ngoài : + Hỗ trợ tối đa : 80% giá trị xe + 7 Năm + Ưu điểm : Lãi tốt và Chăm sóc khách hàng tốt, dịch vụ hậu mãi tốt + Nhược điểm : Hồ sơ khó duyệt, phải chứng minh được thu nhập và giấy tờ đầy đủ - Ngân hàng trong nước : + Hỗ trợ tối đa : 85% + 8 Năm + Ưu điểm : Hồ sơ vay dễ và nhanh + Nhược điểm : Lãi cao hơn ngân hàng nước ngoài và các chính sach hậu mãi sẽ không bằng ngân hàng nước ngoài | L54: Không xe | M54: 6500000 | P54: 3389000 | Q54: 15-25 Ngày
L55: Không xe | M55: 6500000 | Q55: 20-30 Ngày
L56: Không xe | M56: 6500000 | Q56: 30 - 45 Ngày
L57: Không xe | M57: 6500000 | Q57: 45 - 60 Ngày
L58: Không xe | M58: 6500000 | Q58: 60 - 75 Ngày
L59: Không xe | M59: 6500000 | Q59: 75 - 90 Ngày
L60: Không xe | M60: 12000000
L61: Không xe | M61: 6500000
F62: Mình có dự định lấy xe trong tháng luôn chưa ạ hay dự định quá tháng mới lấy xe ạ
F64: Bước 1 : Đặt cọc tối thiểu 10tr để lên HĐ mua bán chính thức Bước 2 : Bên Em sẽ tiến hành đem HĐ bản chính qua cho mình Bước 3 : Trong thời gian đó bên e sẽ có BP hỗ trợ ngân hàng làm việc với bên mình + TH 1 : Làm NH không được bên e sẽ back lại 100% tiền cọc + TH 2 : Làm NH okay 2 bên sẽ tiến hành bước tiếp theo của HĐ Bước 4 : Sau khi Ngân hàng ra thư cho vay bên Mua sẽ tiến hành thanh toán tiền đối ứng cho bên A (bên bán) Bước 5 : Bên Bán sẽ tiến hành làm thủ tục ra biển số (Dự kiến 3- 5 ngày) Bước 6 : Bên Bán sẽ báo bên Mua về thủ tục bấm số ra biển => Sau khi hoàn thành bên Bán sẽ gửi toàn bộ giấy tờ về Ngân hàng Bước 7 : Ngân hàng gọi bên Mua lên ký giấy tờ giải ngân => Tiền giải ngân vào tài khoản Hyundai => Bên Mua nhận xe và hoàn tất HĐ
O75: 23

Sheet Thuế chấp
A1: LỊCH TRẢ NỢ DỰ KIẾN
A2: KHÁCH HÀNG VAY
A3: Giá xe | D3: ='BG New'!H26 -> 846040000
A4: Tổng số tiền vay (VND) | D4: =D3-'BG New'!H66 -> 761436000 | E4: Thời gian ưu đãi (tháng) | G4: 24
A5: Thời gian vay (tháng) | D5: 96 | E5: Lãi tạm tính sau ưu đãi (%/năm) | G5: 0.0925 | L5: 12
A6: Lãi suất ưu đãi (%/năm) | D6: 0.069 | E6: Ngày vay dự kiến | G6: =TODAY() -> 45958 | L6: 24
A7: Số tiền trả trước | D7: =D3-D4+'BG New'!H38 -> 109789680 | E7: =TODAY() -> 45958 | L7: 36
A8: =D5 -> 96 | G8: Tháng | L8: 48
A9: Ngày đóng | B9: Kỳ hạn | C9: Số ngày | D9: Trả gốc | E9: Trả lãi | F9: Total | G9: Dư nợ còn lại | L9: 60
A10: =$G$6 -> 45958 | B10: 0 | G10: =$D4-D10 -> 761436000 | L10: 72
A11: =IF(B10<$D$5,DATE(YEAR(A10),MONTH(A10)+1,DAY(A10)),IF(B10=$D$5,"Tổng","")) -> 45989 | B11: =IF(B10<$D$5,B10+1,"") -> 1 | C11: =IF(B11<>"",A11-A10,"") -> 31 | D11: =IF($B10<$D$5,IF(B10<$G$7,0,$D$4/($D$5-$G$7)),IF($B10=$D$5,$D$4,"")) -> 7931625 | E11: =IF(AND($B11<>"",$B11<=$G$4),$G10*C11*$D$6/360,IF(B11<>"",$G10*C11*$G$5/360,IF(AND(B10<>"",B10=$D$5),SUM($E$10:E10),""))) -> 4524198.9 | F11: =IF(D11<>"",D11+E11,"") -> 12455824 | G11: =IF($B11<>"",G10-D11,"") -> 753504375 | L11: 84
A12: =IF(B11<$D$5,DATE(YEAR(A11),MONTH(A11)+1,DAY(A11)),IF(B11=$D$5,"Tổng","")) -> 46019 | B12: =IF(B11<$D$5,B11+1,"") -> 2 | C12: =IF(B12<>"",A12-A11,"") -> 30 | D12: =IF($B11<$D$5,IF(B11<$G$7,0,$D$4/($D$5-$G$7)),IF($B11=$D$5,$D$4,"")) -> 7931625 | E12: =IF(AND($B12<>"",$B12<=$G$4),$G11*C12*$D$6/360,IF(B12<>"",$G11*C12*$G$5/360,IF(AND(B11<>"",B11=$D$5),SUM($E$10:E11),""))) -> 4332650.2 | F12: =IF(D12<>"",D12+E12,"") -> 12264275 | G12: =IF($B12<>"",G11-D12,"") -> 745572750 | L12: 96
A13: =IF(B12<$D$5,DATE(YEAR(A12),MONTH(A12)+1,DAY(A12)),IF(B12=$D$5,"Tổng","")) -> 46050 | B13: =IF(B12<$D$5,B12+1,"") -> 3 | C13: =IF(B13<>"",A13-A12,"") -> 31 | D13: =IF($B12<$D$5,IF(B12<$G$7,0,$D$4/($D$5-$G$7)),IF($B12=$D$5,$D$4,"")) -> 7931625 | E13: =IF(AND($B13<>"",$B13<=$G$4),$G12*C13*$D$6/360,IF(B13<>"",$G12*C13*$G$5/360,IF(AND(B12<>"",B12=$D$5),SUM($E$10:E12),""))) -> 4429944.8 | F13: =IF(D13<>"",D13+E13,"") -> 12361570 | G13: =IF($B13<>"",G12-D13,"") -> 737641125
A14: =IF(B13<$D$5,DATE(YEAR(A13),MONTH(A13)+1,DAY(A13)),IF(B13=$D$5,"Tổng","")) -> 46081 | B14: =IF(B13<$D$5,B13+1,"") -> 4 | C14: =IF(B14<>"",A14-A13,"") -> 31 | D14: =IF($B13<$D$5,IF(B13<$G$7,0,$D$4/($D$5-$G$7)),IF($B13=$D$5,$D$4,"")) -> 7931625 | E14: =IF(AND($B14<>"",$B14<=$G$4),$G13*C14*$D$6/360,IF(B14<>"",$G13*C14*$G$5/360,IF(AND(B13<>"",B13=$D$5),SUM($E$10:E13),""))) -> 4382817.7 | F14: =IF(D14<>"",D14+E14,"") -> 12314443 | G14: =IF($B14<>"",G13-D14,"") -> 729709500
A15: =IF(B14<$D$5,DATE(YEAR(A14),MONTH(A14)+1,DAY(A14)),IF(B14=$D$5,"Tổng","")) -> 46109 | B15: =IF(B14<$D$5,B14+1,"") -> 5 | C15: =IF(B15<>"",A15-A14,"") -> 28 | D15: =IF($B14<$D$5,IF(B14<$G$7,0,$D$4/($D$5-$G$7)),IF($B14=$D$5,$D$4,"")) -> 7931625 | E15: =IF(AND($B15<>"",$B15<=$G$4),$G14*C15*$D$6/360,IF(B15<>"",$G14*C15*$G$5/360,IF(AND(B14<>"",B14=$D$5),SUM($E$10:E14),""))) -> 3916107.6 | F15: =IF(D15<>"",D15+E15,"") -> 11847733 | G15: =IF($B15<>"",G14-D15,"") -> 721777875
A16: =IF(B15<$D$5,DATE(YEAR(A15),MONTH(A15)+1,DAY(A15)),IF(B15=$D$5,"Tổng","")) -> 46140 | B16: =IF(B15<$D$5,B15+1,"") -> 6 | C16: =IF(B16<>"",A16-A15,"") -> 31 | D16: =IF($B15<$D$5,IF(B15<$G$7,0,$D$4/($D$5-$G$7)),IF($B15=$D$5,$D$4,"")) -> 7931625 | E16: =IF(AND($B16<>"",$B16<=$G$4),$G15*C16*$D$6/360,IF(B16<>"",$G15*C16*$G$5/360,IF(AND(B15<>"",B15=$D$5),SUM($E$10:E15),""))) -> 4288563.5 | F16: =IF(D16<>"",D16+E16,"") -> 12220189 | G16: =IF($B16<>"",G15-D16,"") -> 713846250
A17: =IF(B16<$D$5,DATE(YEAR(A16),MONTH(A16)+1,DAY(A16)),IF(B16=$D$5,"Tổng","")) -> 46170 | B17: =IF(B16<$D$5,B16+1,"") -> 7 | C17: =IF(B17<>"",A17-A16,"") -> 30 | D17: =IF($B16<$D$5,IF(B16<$G$7,0,$D$4/($D$5-$G$7)),IF($B16=$D$5,$D$4,"")) -> 7931625 | E17: =IF(AND($B17<>"",$B17<=$G$4),$G16*C17*$D$6/360,IF(B17<>"",$G16*C17*$G$5/360,IF(AND(B16<>"",B16=$D$5),SUM($E$10:E16),""))) -> 4104615.9 | F17: =IF(D17<>"",D17+E17,"") -> 12036241 | G17: =IF($B17<>"",G16-D17,"") -> 705914625
A18: =IF(B17<$D$5,DATE(YEAR(A17),MONTH(A17)+1,DAY(A17)),IF(B17=$D$5,"Tổng","")) -> 46201 | B18: =IF(B17<$D$5,B17+1,"") -> 8 | C18: =IF(B18<>"",A18-A17,"") -> 31 | D18: =IF($B17<$D$5,IF(B17<$G$7,0,$D$4/($D$5-$G$7)),IF($B17=$D$5,$D$4,"")) -> 7931625 | E18: =IF(AND($B18<>"",$B18<=$G$4),$G17*C18*$D$6/360,IF(B18<>"",$G17*C18*$G$5/360,IF(AND(B17<>"",B17=$D$5),SUM($E$10:E17),""))) -> 4194309.4 | F18: =IF(D18<>"",D18+E18,"") -> 12125934 | G18: =IF($B18<>"",G17-D18,"") -> 697983000
A19: =IF(B18<$D$5,DATE(YEAR(A18),MONTH(A18)+1,DAY(A18)),IF(B18=$D$5,"Tổng","")) -> 46231 | B19: =IF(B18<$D$5,B18+1,"") -> 9 | C19: =IF(B19<>"",A19-A18,"") -> 30 | D19: =IF($B18<$D$5,IF(B18<$G$7,0,$D$4/($D$5-$G$7)),IF($B18=$D$5,$D$4,"")) -> 7931625 | E19: =IF(AND($B19<>"",$B19<=$G$4),$G18*C19*$D$6/360,IF(B19<>"",$G18*C19*$G$5/360,IF(AND(B18<>"",B18=$D$5),SUM($E$10:E18),""))) -> 4013402.3 | F19: =IF(D19<>"",D19+E19,"") -> 11945027 | G19: =IF($B19<>"",G18-D19,"") -> 690051375
A20: =IF(B19<$D$5,DATE(YEAR(A19),MONTH(A19)+1,DAY(A19)),IF(B19=$D$5,"Tổng","")) -> 46262 | B20: =IF(B19<$D$5,B19+1,"") -> 10 | C20: =IF(B20<>"",A20-A19,"") -> 31 | D20: =IF($B19<$D$5,IF(B19<$G$7,0,$D$4/($D$5-$G$7)),IF($B19=$D$5,$D$4,"")) -> 7931625 | E20: =IF(AND($B20<>"",$B20<=$G$4),$G19*C20*$D$6/360,IF(B20<>"",$G19*C20*$G$5/360,IF(AND(B19<>"",B19=$D$5),SUM($E$10:E19),""))) -> 4100055.3 | F20: =IF(D20<>"",D20+E20,"") -> 12031680 | G20: =IF($B20<>"",G19-D20,"") -> 682119750
A21: =IF(B20<$D$5,DATE(YEAR(A20),MONTH(A20)+1,DAY(A20)),IF(B20=$D$5,"Tổng","")) -> 46293 | B21: =IF(B20<$D$5,B20+1,"") -> 11 | C21: =IF(B21<>"",A21-A20,"") -> 31 | D21: =IF($B20<$D$5,IF(B20<$G$7,0,$D$4/($D$5-$G$7)),IF($B20=$D$5,$D$4,"")) -> 7931625 | E21: =IF(AND($B21<>"",$B21<=$G$4),$G20*C21*$D$6/360,IF(B21<>"",$G20*C21*$G$5/360,IF(AND(B20<>"",B20=$D$5),SUM($E$10:E20),""))) -> 4052928.2 | F21: =IF(D21<>"",D21+E21,"") -> 11984553 | G21: =IF($B21<>"",G20-D21,"") -> 674188125
A22: =IF(B21<$D$5,DATE(YEAR(A21),MONTH(A21)+1,DAY(A21)),IF(B21=$D$5,"Tổng","")) -> 46323 | B22: =IF(B21<$D$5,B21+1,"") -> 12 | C22: =IF(B22<>"",A22-A21,"") -> 30 | D22: =IF($B21<$D$5,IF(B21<$G$7,0,$D$4/($D$5-$G$7)),IF($B21=$D$5,$D$4,"")) -> 7931625 | E22: =IF(AND($B22<>"",$B22<=$G$4),$G21*C22*$D$6/360,IF(B22<>"",$G21*C22*$G$5/360,IF(AND(B21<>"",B21=$D$5),SUM($E$10:E21),""))) -> 3876581.7 | F22: =IF(D22<>"",D22+E22,"") -> 11808207 | G22: =IF($B22<>"",G21-D22,"") -> 666256500
A23: =IF(B22<$D$5,DATE(YEAR(A22),MONTH(A22)+1,DAY(A22)),IF(B22=$D$5,"Tổng","")) -> 46354 | B23: =IF(B22<$D$5,B22+1,"") -> 13 | C23: =IF(B23<>"",A23-A22,"") -> 31 | D23: =IF($B22<$D$5,IF(B22<$G$7,0,$D$4/($D$5-$G$7)),IF($B22=$D$5,$D$4,"")) -> 7931625 | E23: =IF(AND($B23<>"",$B23<=$G$4),$G22*C23*$D$6/360,IF(B23<>"",$G22*C23*$G$5/360,IF(AND(B22<>"",B22=$D$5),SUM($E$10:E22),""))) -> 3958674 | F23: =IF(D23<>"",D23+E23,"") -> 11890299 | G23: =IF($B23<>"",G22-D23,"") -> 658324875
A24: =IF(B23<$D$5,DATE(YEAR(A23),MONTH(A23)+1,DAY(A23)),IF(B23=$D$5,"Tổng","")) -> 46384 | B24: =IF(B23<$D$5,B23+1,"") -> 14 | C24: =IF(B24<>"",A24-A23,"") -> 30 | D24: =IF($B23<$D$5,IF(B23<$G$7,0,$D$4/($D$5-$G$7)),IF($B23=$D$5,$D$4,"")) -> 7931625 | E24: =IF(AND($B24<>"",$B24<=$G$4),$G23*C24*$D$6/360,IF(B24<>"",$G23*C24*$G$5/360,IF(AND(B23<>"",B23=$D$5),SUM($E$10:E23),""))) -> 3785368 | F24: =IF(D24<>"",D24+E24,"") -> 11716993 | G24: =IF($B24<>"",G23-D24,"") -> 650393250
... A195: =IF(B194<$D$5,DATE(YEAR(A194),MONTH(A194)+1,DAY(A194)),IF(B194=$D$5,"Tổng","")) | B195: =IF(B194<$D$5,B194+1,"") | C195: =IF(B195<>"",A195-A194,"") | D195: =IF($B194<$D$5,IF(B194<$G$7,0,$D$4/($D$5-$G$7)),IF($B194=$D$5,$D$4,"")) | E195: =IF(AND($B195<>"",$B195<=$G$4),$G194*C195*$D$6/360,IF(B195<>"",$G194*C195*$G$5/360,IF(AND(B194<>"",B194=$D$5),SUM($E$10:E194),""))) | F195: =IF(D195<>"",D195+E195,"") | G195: =IF($B195<>"",G194-D195,"")
A196: =IF(B195<$D$5,DATE(YEAR(A195),MONTH(A195)+1,DAY(A195)),IF(B195=$D$5,"Tổng","")) | B196: =IF(B195<$D$5,B195+1,"") | C196: =IF(B196<>"",A196-A195,"") | D196: =IF($B195<$D$5,$D$4/$D$5,IF($B195=$D$5,$D$4,"")) | E196: =IF(AND($B196<>"",$B196<=$G$4),$G195*C196*$D$6/360,IF(B196<>"",$G195*C196*$G$5/360,IF(AND(B195<>"",B195=$D$5),SUM($E$10:E195),""))) | F196: =IF(D196<>"",D196+E196,"") | G196: =IF($B196<>"",G195-D196,"")
A197: =IF(B196<$D$5,DATE(YEAR(A196),MONTH(A196)+1,DAY(A196)),IF(B196=$D$5,"Tổng","")) | B197: =IF(B196<$D$5,B196+1,"") | C197: =IF(B197<>"",A197-A196,"") | D197: =IF($B196<$D$5,$D$4/$D$5,IF($B196=$D$5,$D$4,"")) | E197: =IF(AND($B197<>"",$B197<=$G$4),$G196*C197*$D$6/360,IF(B197<>"",$G196*C197*$G$5/360,IF(AND(B196<>"",B196=$D$5),SUM($E$10:E196),""))) | F197: =IF(D197<>"",D197+E197,"") | G197: =IF($B197<>"",G196-D197,"")
A198: =IF(B197<$D$5,DATE(YEAR(A197),MONTH(A197)+1,DAY(A197)),IF(B197=$D$5,"Tổng","")) | B198: =IF(B197<$D$5,B197+1,"") | C198: =IF(B198<>"",A198-A197,"") | D198: =IF($B197<$D$5,$D$4/$D$5,IF($B197=$D$5,$D$4,"")) | E198: =IF(AND($B198<>"",$B198<=$G$4),$G197*C198*$D$6/360,IF(B198<>"",$G197*C198*$G$5/360,IF(AND(B197<>"",B197=$D$5),SUM($E$10:E197),""))) | F198: =IF(D198<>"",D198+E198,"") | G198: =IF($B198<>"",G197-D198,"")
A199: =IF(B198<$D$5,DATE(YEAR(A198),MONTH(A198)+1,DAY(A198)),IF(B198=$D$5,"Tổng","")) | B199: =IF(B198<$D$5,B198+1,"") | C199: =IF(B199<>"",A199-A198,"") | D199: =IF($B198<$D$5,$D$4/$D$5,IF($B198=$D$5,$D$4,"")) | E199: =IF(AND($B199<>"",$B199<=$G$4),$G198*C199*$D$6/360,IF(B199<>"",$G198*C199*$G$5/360,IF(AND(B198<>"",B198=$D$5),SUM($E$10:E198),""))) | F199: =IF(D199<>"",D199+E199,"") | G199: =IF($B199<>"",G198-D199,"")
A200: =IF(B199<$D$5,DATE(YEAR(A199),MONTH(A199)+1,DAY(A199)),IF(B199=$D$5,"Tổng","")) | B200: =IF(B199<$D$5,B199+1,"") | C200: =IF(B200<>"",A200-A199,"") | D200: =IF($B199<$D$5,$D$4/$D$5,IF($B199=$D$5,$D$4,"")) | E200: =IF(AND($B200<>"",$B200<=$G$4),$G199*C200*$D$6/360,IF(B200<>"",$G199*C200*$G$5/360,IF(AND(B199<>"",B199=$D$5),SUM($E$10:E199),""))) | F200: =IF(D200<>"",D200+E200,"") | G200: =IF($B200<>"",G199-D200,"")
A201: =IF(B200<$D$5,DATE(YEAR(A200),MONTH(A200)+1,DAY(A200)),IF(B200=$D$5,"Tổng","")) | B201: =IF(B200<$D$5,B200+1,"") | C201: =IF(B201<>"",A201-A200,"") | D201: =IF($B200<$D$5,$D$4/$D$5,IF($B200=$D$5,$D$4,"")) | E201: =IF(AND($B201<>"",$B201<=$G$4),$G200*C201*$D$6/360,IF(B201<>"",$G200*C201*$G$5/360,IF(AND(B200<>"",B200=$D$5),SUM($E$10:E200),""))) | F201: =IF(D201<>"",D201+E201,"") | G201: =IF($B201<>"",G200-D201,"")
A202: =IF(B201<$D$5,DATE(YEAR(A201),MONTH(A201)+1,DAY(A201)),IF(B201=$D$5,"Tổng","")) | B202: =IF(B201<$D$5,B201+1,"") | C202: =IF(B202<>"",A202-A201,"") | D202: =IF($B201<$D$5,$D$4/$D$5,IF($B201=$D$5,$D$4,"")) | E202: =IF(AND($B202<>"",$B202<=$G$4),$G201*C202*$D$6/360,IF(B202<>"",$G201*C202*$G$5/360,IF(AND(B201<>"",B201=$D$5),SUM($E$10:E201),""))) | F202: =IF(D202<>"",D202+E202,"") | G202: =IF($B202<>"",G201-D202,"")
A203: =IF(B202<$D$5,DATE(YEAR(A202),MONTH(A202)+1,DAY(A202)),IF(B202=$D$5,"Tổng","")) | B203: =IF(B202<$D$5,B202+1,"") | C203: =IF(B203<>"",A203-A202,"") | D203: =IF($B202<$D$5,$D$4/$D$5,IF($B202=$D$5,$D$4,"")) | E203: =IF(AND($B203<>"",$B203<=$G$4),$G202*C203*$D$6/360,IF(B203<>"",$G202*C203*$G$5/360,IF(AND(B202<>"",B202=$D$5),SUM($E$10:E202),""))) | F203: =IF(D203<>"",D203+E203,"") | G203: =IF($B203<>"",G202-D203,"")
A204: =IF(B203<$D$5,DATE(YEAR(A203),MONTH(A203)+1,DAY(A203)),IF(B203=$D$5,"Tổng","")) | B204: =IF(B203<$D$5,B203+1,"") | C204: =IF(B204<>"",A204-A203,"") | D204: =IF($B203<$D$5,$D$4/$D$5,IF($B203=$D$5,$D$4,"")) | E204: =IF(AND($B204<>"",$B204<=$G$4),$G203*C204*$D$6/360,IF(B204<>"",$G203*C204*$G$5/360,IF(AND(B203<>"",B203=$D$5),SUM($E$10:E203),""))) | F204: =IF(D204<>"",D204+E204,"") | G204: =IF($B204<>"",G203-D204,"")
A205: =IF(B204<$D$5,DATE(YEAR(A204),MONTH(A204)+1,DAY(A204)),IF(B204=$D$5,"Tổng","")) | B205: =IF(B204<$D$5,B204+1,"") | C205: =IF(B205<>"",A205-A204,"") | D205: =IF($B204<$D$5,$D$4/$D$5,IF($B204=$D$5,$D$4,"")) | E205: =IF(AND($B205<>"",$B205<=$G$4),$G204*C205*$D$6/360,IF(B205<>"",$G204*C205*$G$5/360,IF(AND(B204<>"",B204=$D$5),SUM($E$10:E204),""))) | F205: =IF(D205<>"",D205+E205,"") | G205: =IF($B205<>"",G204-D205,"")
A206: =IF(B205<$D$5,DATE(YEAR(A205),MONTH(A205)+1,DAY(A205)),IF(B205=$D$5,"Tổng","")) | B206: =IF(B205<$D$5,B205+1,"") | C206: =IF(B206<>"",A206-A205,"") | D206: =IF($B205<$D$5,$D$4/$D$5,IF($B205=$D$5,$D$4,"")) | E206: =IF(AND($B206<>"",$B206<=$G$4),$G205*C206*$D$6/360,IF(B206<>"",$G205*C206*$G$5/360,IF(AND(B205<>"",B205=$D$5),SUM($E$10:E205),""))) | F206: =IF(D206<>"",D206+E206,"") | G206: =IF($B206<>"",G205-D206,"")
A207: =IF(B206<$D$5,DATE(YEAR(A206),MONTH(A206)+1,DAY(A206)),IF(B206=$D$5,"Tổng","")) | B207: =IF(B206<$D$5,B206+1,"") | C207: =IF(B207<>"",A207-A206,"") | D207: =IF($B206<$D$5,$D$4/$D$5,IF($B206=$D$5,$D$4,"")) | E207: =IF(AND($B207<>"",$B207<=$G$4),$G206*C207*$D$6/360,IF(B207<>"",$G206*C207*$G$5/360,IF(AND(B206<>"",B206=$D$5),SUM($E$10:E206),""))) | F207: =IF(D207<>"",D207+E207,"") | G207: =IF($B207<>"",G206-D207,"")
... A251: =IF(B250<$D$5,DATE(YEAR(A250),MONTH(A250)+1,DAY(A250)),IF(B250=$D$5,"Tổng","")) | B251: =IF(B250<$D$5,B250+1,"") | C251: =IF(B251<>"",A251-A250,"") | D251: =IF($B250<$D$5,$D$4/$D$5,IF($B250=$D$5,$D$4,"")) | E251: =IF(AND($B251<>"",$B251<=$G$4),$G250*C251*$D$6/360,IF(B251<>"",$G250*C251*$G$5/360,IF(AND(B250<>"",B250=$D$5),SUM($E$10:E250),""))) | F251: =IF(D251<>"",D251+E251,"") | G251: =IF($B251<>"",G250-D251,"")
A252: =IF(B251<$D$5,DATE(YEAR(A251),MONTH(A251)+1,DAY(A251)),IF(B251=$D$5,"Tổng","")) | B252: =IF(B251<$D$5,B251+1,"") | C252: =IF(B252<>"",A252-A251,"") | D252: =IF($B251<$D$5,$D$4/$D$5,IF($B251=$D$5,$D$4,"")) | E252: =IF(AND($B252<>"",$B252<=$G$4),$G251*C252*$D$6/360,IF(B252<>"",$G251*C252*$G$5/360,IF(AND(B252<>"",B251=$D$5),SUM($E$10:E251),""))) | F252: =IF(D252<>"",D252+E252,"") | G252: =IF($B252<>"",G251-D252,"")
A253: =IF(B252<$D$5,DATE(YEAR(A252),MONTH(A252)+1,DAY(A252)),IF(B252=$D$5,"Tổng","")) | B253: =IF(B252<$D$5,B252+1,"") | C253: =IF(B253<>"",A253-A252,"") | D253: =IF($B252<$D$5,$D$4/$D$5,IF($B252=$D$5,$D$4,"")) | E253: =IF(AND($B253<>"",$B253<=$G$4),$G252*C253*$D$6/360,IF(B253<>"",$G252*C253*$G$5/360,IF(AND(B253<>"",B252=$D$5),SUM($E$10:E252),""))) | F253: =IF(D253<>"",D253+E253,"") | G253: =IF($B253<>"",G252-D253,"")
A254: =IF(B253<$D$5,DATE(YEAR(A253),MONTH(A253)+1,DAY(A253)),IF(B253=$D$5,"Tổng","")) | B254: =IF(B253<$D$5,B253+1,"") | C254: =IF(B254<>"",A254-A253,"") | D254: =IF($B253<$D$5,$D$4/$D$5,IF($B253=$D$5,$D$4,"")) | E254: =IF(AND($B254<>"",$B254<=$G$4),$G253*C254*$D$6/360,IF(B254<>"",$G253*C254*$G$5/360,IF(AND(B254<>"",B253=$D$5),SUM($E$10:E253),""))) | F254: =IF(D254<>"",D254+E254,"") | G254: =IF($B254<>"",G253-D254,"")
A255: =IF(B254<$D$5,DATE(YEAR(A254),MONTH(A254)+1,DAY(A254)),IF(B254=$D$5,"Tổng","")) | B255: =IF(B254<$D$5,B254+1,"") | C255: =IF(B255<>"",A255-A254,"") | D255: =IF($B254<$D$5,$D$4/$D$5,IF($B254=$D$5,$D$4,"")) | E255: =IF(AND($B255<>"",$B255<=$G$4),$G254*C255*$D$6/360,IF(B255<>"",$G254*C255*$G$5/360,IF(AND(B255<>"",B254=$D$5),SUM($E$10:E254),""))) | F255: =IF(D255<>"",D255+E255,"") | G255: =IF($B255<>"",G254-D255,"")
A256: =IF(B255<$D$5,DATE(YEAR(A255),MONTH(A255)+1,DAY(A255)),IF(B255=$D$5,"Tổng","")) | B256: =IF(B255<$D$5,B255+1,"") | C256: =IF(B256<>"",A256-A255,"") | D256: =IF($B255<$D$5,$D$4/$D$5,IF($B255=$D$5,$D$4,"")) | E256: =IF(AND($B256<>"",$B256<=$G$4),$G255*C256*$D$6/360,IF(B256<>"",$G255*C256*$G$5/360,IF(AND(B256<>"",B255=$D$5),SUM($E$10:E255),""))) | F256: =IF(D256<>"",D256+E256,"") | G256: =IF($B256<>"",G255-D256,"")
A257: =IF(B256<$D$5,DATE(YEAR(A256),MONTH(A256)+1,DAY(A256)),IF(B256=$D$5,"Tổng","")) | B257: =IF(B256<$D$5,B256+1,"") | C257: =IF(B257<>"",A257-A256,"") | D257: =IF($B256<$D$5,$D$4/$D$5,IF($B256=$D$5,$D$4,"")) | E257: =IF(AND($B257<>"",$B257<=$G$4),$G256*C257*$D$6/360,IF(B257<>"",$G256*C257*$G$5/360,IF(AND(B257<>"",B256=$D$5),SUM($E$10:E256),""))) | F257: =IF(D257<>"",D257+E257,"") | G257: =IF($B257<>"",G256-D257,"")
A258: =IF(B257<$D$5,DATE(YEAR(A257),MONTH(A257)+1,DAY(A257)),IF(B257=$D$5,"Tổng","")) | B258: =IF(B257<$D$5,B257+1,"") | C258: =IF(B258<>"",A258-A257,"") | D258: =IF($B257<$D$5,$D$4/$D$5,IF($B257=$D$5,$D$4,"")) | E258: =IF(AND($B258<>"",$B258<=$G$4),$G257*C258*$D$6/360,IF(B258<>"",$G257*C258*$G$5/360,IF(AND(B258<>"",B257=$D$5),SUM($E$10:E257),""))) | F258: =IF(D258<>"",D258+E258,"") | G258: =IF($B258<>"",G257-D258,"")
A259: =IF(B258<$D$5,DATE(YEAR(A258),MONTH(A258)+1,DAY(A258)),IF(B258=$D$5,"Tổng","")) | B259: =IF(B258<$D$5,B258+1,"") | C259: =IF(B259<>"",A259-A258,"") | D259: =IF($B258<$D$5,$D$4/$D$5,IF($B258=$D$5,$D$4,"")) | E259: =IF(AND($B259<>"",$B259<=$G$4),$G258*C259*$D$6/360,IF(B259<>"",$G258*C259*$G$5/360,IF(AND(B259<>"",B258=$D$5),SUM($E$10:E258),""))) | F259: =IF(D259<>"",D259+E259,"") | G259: =IF($B259<>"",G258-D259,"")
A260: =IF(B259<$D$5,DATE(YEAR(A259),MONTH(A259)+1,DAY(A259)),IF(B259=$D$5,"Tổng","")) | B260: =IF(B259<$D$5,B259+1,"") | C260: =IF(B260<>"",A260-A259,"") | D260: =IF($B259<$D$5,$D$4/$D$5,IF($B259=$D$5,$D$4,"")) | E260: =IF(AND($B260<>"",$B260<=$G$4),$G259*C260*$D$6/360,IF(B260<>"",$G259*C260*$G$5/360,IF(AND(B260<>"",B259=$D$5),SUM($E$10:E259),""))) | F260: =IF(D260<>"",D260+E260,"") | G260: =IF($B260<>"",G259-D260,"")
A261: =IF(B260<$D$5,DATE(YEAR(A260),MONTH(A260)+1,DAY(A260)),IF(B260=$D$5,"Tổng","")) | B261: =IF(B260<$D$5,B260+1,"") | C261: =IF(B261<>"",A261-A260,"") | D261: =IF($B260<$D$5,$D$4/$D$5,IF($B260=$D$5,$D$4,"")) | E261: =IF(AND($B261<>"",$B261<=$G$4),$G260*C261*$D$6/360,IF(B261<>"",$G260*C261*$G$5/360,IF(AND(B261<>"",B260=$D$5),SUM($E$10:E260),""))) | F261: =IF(D261<>"",D261+E261,"") | G261: =IF($B261<>"",G260-D261,"")
A262: =IF(B261<$D$5,DATE(YEAR(A261),MONTH(A261)+1,DAY(A261)),IF(B261=$D$5,"Tổng","")) | B262: =IF(B261<$D$5,B261+1,"") | C262: =IF(B262<>"",A262-A261,"") | D262: =IF($B261<$D$5,$D$4/$D$5,IF($B261=$D$5,$D$4,"")) | E262: =IF(AND($B262<>"",$B262<=$G$4),$G261*C262*$D$6/360,IF(B262<>"",$G261*C262*$G$5/360,IF(AND(B262<>"",B261=$D$5),SUM($E$10:E261),""))) | F262: =IF(D262<>"",D262+E262,"") | G262: =IF($B262<>"",G261-D262,"")
A263: =IF(B262<$D$5,DATE(YEAR(A262),MONTH(A262)+1,DAY(A262)),IF(B262=$D$5,"Tổng","")) | B263: =IF(B262<$D$5,B262+1,"") | C263: =IF(B263<>"",A263-A262,"") | D263: =IF($B262<$D$5,$D$4/$D$5,IF($B262=$D$5,$D$4,"")) | E263: =IF(AND($B263<>"",$B263<=$G$4),$G262*C263*$D$6/360,IF(B263<>"",$G262*C263*$G$5/360,IF(AND(B263<>"",B262=$D$5),SUM($E$10:E262),""))) | F263: =IF(B263<>"",D263+E263,"") | G263: =IF($B263<>"",G262-D263,"")
A264: =IF(B263<$D$5,DATE(YEAR(A263),MONTH(A263)+1,DAY(A263)),IF(B263=$D$5,"Tổng","")) | B264: =IF(B263<$D$5,B263+1,"") | C264: =IF(B264<>"",A264-A263,"") | D264: =IF($B263<$D$5,$D$4/$D$5,IF($B263=$D$5,$D$4,"")) | E264: =IF(AND($B264<>"",$B264<=$G$4),$G263*C264*$D$6/360,IF(B264<>"",$G263*C264*$G$5/360,IF(AND(B264<>"",B263=$D$5),SUM($E$10:E263),""))) | F264: =IF(B264<>"",D264+E264,"") | G264: =IF($B264<>"",G263-D264,"")
A265: =IF(B264<$D$5,DATE(YEAR(A264),MONTH(A264)+1,DAY(A264)),IF(B264=$D$5,"Tổng","")) | B265: =IF(B264<$D$5,B264+1,"") | C265: =IF(B265<>"",A265-A264,"") | D265: =IF($B264<$D$5,$D$4/$D$5,IF($B264=$D$5,$D$4,"")) | E265: =IF(AND($B265<>"",$B265<=$G$4),$G264*C265*$D$6/360,IF(B265<>"",$G264*C265*$G$5/360,IF(AND(B265<>"",B264=$D$5),SUM($E$10:E264),""))) | F265: =IF(B265<>"",D265+E265,"") | G265: =IF($B265<>"",G264-D265,"")
A266: =IF(B265<$D$5,DATE(YEAR(A265),MONTH(A265)+1,DAY(A265)),IF(B265=$D$5,"Tổng","")) | B266: =IF(B265<$D$5,B265+1,"") | C266: =IF(B266<>"",A266-A265,"") | D266: =IF($B265<$D$5,$D$4/$D$5,IF($B265=$D$5,$D$4,"")) | E266: =IF(AND($B266<>"",$B266<=$G$4),$G265*C266*$D$6/360,IF(B266<>"",$G265*C266*$G$5/360,IF(AND(B266<>"",B265=$D$5),SUM($E$10:E265),""))) | F266: =IF(B266<>"",D266+E266,"") | G266: =IF($B266<>"",G265-D266,"")
A267: =IF(B266<$D$5,DATE(YEAR(A266),MONTH(A266)+1,DAY(A266)),IF(B266=$D$5,"Tổng","")) | B267: =IF(B266<$D$5,B266+1,"") | C267: =IF(B267<>"",A267-A266,"") | D267: =IF($B266<$D$5,$D$4/$D$5,IF($B266=$D$5,$D$4,"")) | E267: =IF(AND($B267<>"",$B267<=$G$4),$G266*C267*$D$6/360,IF(B267<>"",$G266*C267*$G$5/360,IF(AND(B267<>"",B266=$D$5),SUM($E$10:E266),""))) | F267: =IF(B267<>"",D267+E267,"") | G267: =IF($B267<>"",G266-D267,"")
A268: =IF(B267<$D$5,DATE(YEAR(A267),MONTH(A267)+1,DAY(A267)),IF(B267=$D$5,"Tổng","")) | B268: =IF(B267<$D$5,B267+1,"") | C268: =IF(B268<>"",A268-A267,"") | D268: =IF($B267<$D$5,$D$4/$D$5,IF($B267=$D$5,$D$4,"")) | E268: =IF(AND($B268<>"",$B268<=$G$4),$G267*C268*$D$6/360,IF(B268<>"",$G267*C268*$G$5/360,IF(AND(B268<>"",B267=$D$5),SUM($E$10:E267),""))) | F268: =IF(B268<>"",D268+E268,"") | G268: =IF($B268<>"",G267-D268,"")
A269: =IF(B268<$D$5,DATE(YEAR(A268),MONTH(A268)+1,DAY(A268)),IF(B268=$D$5,"Tổng","")) | B269: =IF(B268<$D$5,B268+1,"") | C269: =IF(B269<>"",A269-A268,"") | D269: =IF($B268<$D$5,$D$4/$D$5,IF($B268=$D$5,$D$4,"")) | E269: =IF(AND($B269<>"",$B269<=$G$4),$G268*C269*$D$6/360,IF(B269<>"",$G268*C269*$G$5/360,IF(AND(B269<>"",B268=$D$5),SUM($E$10:E268),""))) | F269: =IF(B269<>"",D269+E269,"") | G269: =IF($B269<>"",G268-D269,"")
A270: =IF(B269<$D$5,DATE(YEAR(A269),MONTH(A269)+1,DAY(A269)),IF(B269=$D$5,"Tổng","")) | B270: =IF(B269<$D$5,B269+1,"") | C270: =IF(B270<>"",A270-A269,"") | D270: =IF($B269<$D$5,$D$4/$D$5,IF($B269=$D$5,$D$4,"")) | E270: =IF(AND($B270<>"",$B270<=$G$4),$G269*C270*$D$6/360,IF(B270<>"",$G269*C270*$G$5/360,IF(AND(B270<>"",B269=$D$5),SUM($E$10:E269),""))) | F270: =IF(B270<>"",D270+E270,"") | G270: =IF($B270<>"",G269-D270,"")
A271: =IF(B270<$D$5,DATE(YEAR(A270),MONTH(A270)+1,DAY(A270)),IF(B270=$D$5,"Tổng","")) | B271: =IF(B270<$D$5,B270+1,"") | C271: =IF(B271<>"",A271-A270,"") | D271: =IF($B270<$D$5,$D$4/$D$5,IF($B270=$D$5,$D$4,"")) | E271: =IF(AND($B271<>"",$B271<=$G$4),$G270*C271*$D$6/360,IF(B271<>"",$G270*C271*$G$5/360,IF(AND(B271<>"",B270=$D$5),SUM($E$10:E270),""))) | F271: =IF(B271<>"",D271+E271,"") | G271: =IF($B271<>"",G270-D271,"")
A272: =IF(B271<$D$5,DATE(YEAR(A271),MONTH(A271)+1,DAY(A271)),IF(B271=$D$5,"Tổng","")) | B272: =IF(B271<$D$5,B271+1,"") | C272: =IF(B272<>"",A272-A271,"") | D272: =IF($B271<$D$5,$D$4/$D$5,IF($B271=$D$5,$D$4,"")) | E272: =IF(AND($B272<>"",$B272<=$G$4),$G271*C272*$D$6/360,IF(B272<>"",$G271*C272*$G$5/360,IF(AND(B272<>"",B271=$D$5),SUM($E$10:E271),""))) | G272: =IF($B272<>"",G271-D272,"")
A273: =IF(B272<$D$5,DATE(YEAR(A272),MONTH(A272)+1,DAY(A272)),IF(B272=$D$5,"Tổng","")) | B273: =IF(B272<$D$5,B272+1,"") | C273: =IF(B273<>"",A273-A272,"") | D273: =IF($B272<$D$5,$D$4/$D$5,IF($B272=$D$5,$D$4,"")) | E273: =IF(AND($B273<>"",$B273<=$G$4),$G272*C273*$D$6/360,IF(B273<>"",$G272*C273*$G$5/360,IF(AND(B273<>"",B272=$D$5),SUM($E$10:E272),""))) | G273: =IF($B273<>"",G272-D273,"")
A274: =IF(B273<$D$5,DATE(YEAR(A273),MONTH(A273)+1,DAY(A273)),IF(B273=$D$5,"Tổng","")) | B274: =IF(B273<$D$5,B273+1,"") | C274: =IF(B274<>"",A274-A273,"") | D274: =IF($B273<$D$5,$D$4/$D$5,IF($B273=$D$5,$D$4,"")) | E274: =IF(AND($B274<>"",$B274<=$G$4),$G273*C274*$D$6/360,IF(B274<>"",$G273*C274*$G$5/360,IF(AND(B274<>"",B273=$D$5),SUM($E$10:E273),""))) | G274: =IF($B274<>"",G273-D274,"")
A275: =IF(B274<$D$5,DATE(YEAR(A274),MONTH(A274)+1,DAY(A274)),IF(B274=$D$5,"Tổng","")) | B275: =IF(B274<$D$5,B274+1,"") | C275: =IF(B275<>"",A275-A274,"") | D275: =IF($B274<$D$5,$D$4/$D$5,IF($B274=$D$5,$D$4,"")) | E275: =IF(AND($B275<>"",$B275<=$G$4),$G274*C275*$D$6/360,IF(B275<>"",$G274*C275*$G$5/360,IF(AND(B275<>"",B274=$D$5),SUM($E$10:E274),""))) | G275: =IF($B275<>"",G274-D275,"")
A276: =IF(B275<$D$5,DATE(YEAR(A275),MONTH(A275)+1,DAY(A275)),IF(B275=$D$5,"Tổng","")) | B276: =IF(B275<$D$5,B275+1,"") | C276: =IF(B276<>"",A276-A275,"") | D276: =IF($B275<$D$5,$D$4/$D$5,IF($B275=$D$5,$D$4,"")) | G276: =IF($B276<>"",G275-D276,"")
A277: =IF(B276<$D$5,DATE(YEAR(A276),MONTH(A276)+1,DAY(A276)),IF(B276=$D$5,"Tổng","")) | B277: =IF(B276<$D$5,B276+1,"") | C277: =IF(B277<>"",A277-A276,"") | D277: =IF($B276<$D$5,$D$4/$D$5,IF($B276=$D$5,$D$4,"")) | G277: =IF($B277<>"",G276-D277,"")
A278: =IF(B277<$D$5,DATE(YEAR(A277),MONTH(A277)+1,DAY(A277)),IF(B277=$D$5,"Tổng","")) | B278: =IF(B277<$D$5,B277+1,"") | C278: =IF(B278<>"",A278-A277,"") | D278: =IF($B277<$D$5,$D$4/$D$5,IF($B277=$D$5,$D$4,"")) | G278: =IF($B278<>"",G277-D278,"")
A279: =IF(B278<$D$5,DATE(YEAR(A278),MONTH(A278)+1,DAY(A278)),IF(B278=$D$5,"Tổng","")) | B279: =IF(B278<$D$5,B278+1,"") | C279: =IF(B279<>"",A279-A278,"") | D279: =IF($B278<$D$5,$D$4/$D$5,IF($B278=$D$5,$D$4,"")) | G279: =IF($B279<>"",G278-D279,"")
A280: =IF(B279<$D$5,DATE(YEAR(A279),MONTH(A279)+1,DAY(A279)),IF(B279=$D$5,"Tổng","")) | B280: =IF(B279<$D$5,B279+1,"") | C280: =IF(B280<>"",A280-A279,"") | D280: =IF($B279<$D$5,$D$4/$D$5,IF($B279=$D$5,$D$4,"")) | G280: =IF($B280<>"",G279-D280,"")
A281: =IF(B280<$D$5,DATE(YEAR(A280),MONTH(A280)+1,DAY(A280)),IF(B280=$D$5,"Tổng","")) | B281: =IF(B280<$D$5,B280+1,"") | C281: =IF(B281<>"",A281-A280,"") | D281: =IF($B280<$D$5,$D$4/$D$5,IF($B280=$D$5,$D$4,"")) | G281: =IF($B281<>"",G280-D281,"")
A282: =IF(B281<$D$5,DATE(YEAR(A281),MONTH(A281)+1,DAY(A281)),IF(B281=$D$5,"Tổng","")) | B282: =IF(B281<$D$5,B281+1,"") | C282: =IF(B282<>"",A282-A281,"") | D282: =IF($B281<$D$5,$D$4/$D$5,IF($B281=$D$5,$D$4,"")) | G282: =IF($B282<>"",G281-D282,"")
A283: =IF(B282<$D$5,DATE(YEAR(A282),MONTH(A282)+1,DAY(A282)),IF(B282=$D$5,"Tổng","")) | B283: =IF(B282<$D$5,B282+1,"") | C283: =IF(B283<>"",A283-A282,"") | D283: =IF($B282<$D$5,$D$4/$D$5,IF($B282=$D$5,$D$4,"")) | G283: =IF($B283<>"",G282-D283,"")
A284: =IF(B283<$D$5,DATE(YEAR(A283),MONTH(A283)+1,DAY(A283)),IF(B283=$D$5,"Tổng","")) | B284: =IF(B283<$D$5,B283+1,"") | C284: =IF(B284<>"",A284-A283,"") | D284: =IF($B283<$D$5,$D$4/$D$5,IF($B283=$D$5,$D$4,"")) | G284: =IF($B284<>"",G283-D284,"")
A285: =IF(B284<$D$5,DATE(YEAR(A284),MONTH(A284)+1,DAY(A284)),IF(B284=$D$5,"Tổng","")) | B285: =IF(B284<$D$5,B284+1,"") | C285: =IF(B285<>"",A285-A284,"") | D285: =IF($B284<$D$5,$D$4/$D$5,IF($B284=$D$5,$D$4,"")) | G285: =IF($B285<>"",G284-D285,"")
A286: =IF(B285<$D$5,DATE(YEAR(A285),MONTH(A285)+1,DAY(A285)),IF(B285=$D$5,"Tổng","")) | B286: =IF(B285<$D$5,B285+1,"") | C286: =IF(B286<>"",A286-A285,"") | D286: =IF($B285<$D$5,$D$4/$D$5,IF($B285=$D$5,$D$4,"")) | G286: =IF($B286<>"",G285-D286,"")
A287: =IF(B286<$D$5,DATE(YEAR(A286),MONTH(A286)+1,DAY(A286)),IF(B286=$D$5,"Tổng","")) | B287: =IF(B286<$D$5,B286+1,"") | C287: =IF(B287<>"",A287-A286,"") | D287: =IF($B286<$D$5,$D$4/$D$5,IF($B286=$D$5,$D$4,"")) | G287: =IF($B287<>"",G286-D287,"")
... A296: =IF(B295<$D$5,DATE(YEAR(A295),MONTH(A295)+1,DAY(A295)),IF(B295=$D$5,"Tổng","")) | B296: =IF(B295<$D$5,B295+1,"") | C296: =IF(B296<>"",A296-A295,"") | D296: =IF($B295<$D$5,$D$4/$D$5,IF($B295=$D$5,$D$4,"")) | G296: =IF($B296<>"",G295-D296,"")
A297: =IF(B296<$D$5,DATE(YEAR(A296),MONTH(A296)+1,DAY(A296)),IF(B296=$D$5,"Tổng","")) | B297: =IF(B296<$D$5,B296+1,"") | C297: =IF(B297<>"",A297-A296,"") | D297: =IF($B296<$D$5,$D$4/$D$5,IF($B296=$D$5,$D$4,""))
A298: =IF(B297<$D$5,DATE(YEAR(A297),MONTH(A297)+1,DAY(A297)),IF(B297=$D$5,"Tổng","")) | B298: =IF(B297<$D$5,B297+1,"") | C298: =IF(B298<>"",A298-A297,"") | D298: =IF($B297<$D$5,$D$4/$D$5,IF($B297=$D$5,$D$4,""))
A299: =IF(B298<$D$5,DATE(YEAR(A298),MONTH(A298)+1,DAY(A298)),IF(B298=$D$5,"Tổng","")) | B299: =IF(B298<$D$5,B298+1,"") | C299: =IF(B299<>"",A299-A298,"") | D299: =IF($B298<$D$5,$D$4/$D$5,IF($B298=$D$5,$D$4,""))
A300: =IF(B299<$D$5,DATE(YEAR(A299),MONTH(A299)+1,DAY(A299)),IF(B299=$D$5,"Tổng","")) | B300: =IF(B299<$D$5,B299+1,"") | C300: =IF(B300<>"",A300-A299,"") | D300: =IF($B299<$D$5,$D$4/$D$5,IF($B299=$D$5,$D$4,""))

Sheet Bank 2
A1: LỊCH TRẢ NỢ DỰ KIẾN | H1: LỊCH TRẢ NỢ DỰ KIẾN | O1: LỊCH TRẢ NỢ DỰ KIẾN | V1: LỊCH TRẢ NỢ DỰ KIẾN | AC1: LỊCH TRẢ NỢ DỰ KIẾN | AJ1: LỊCH TRẢ NỢ DỰ KIẾN
A2: KHÁCH HÀNG VAY | H2: KHÁCH HÀNG VAY | O2: KHÁCH HÀNG VAY | V2: KHÁCH HÀNG VAY | AC2: KHÁCH HÀNG VAY | AJ2: KHÁCH HÀNG VAY
A3: Giá xe | D3: ='Thuế chấp'!$D$3 -> 846040000 | H3: Giá xe | K3: ='Thuế chấp'!$D$3 -> 846040000 | O3: Giá xe | R3: ='Thuế chấp'!$D$3 -> 846040000 | V3: Giá xe | Y3: ='Thuế chấp'!$D$3 -> 846040000 | AC3: Giá xe | AF3: ='Thuế chấp'!$D$3 -> 846040000 | AJ3: Giá xe | AM3: ='Thuế chấp'!$D$3 -> 846040000
A4: Tổng số tiền vay (VND) | D4: ='BG New'!H70 -> 676832000 | E4: Thời gian ưu đãi (tháng) | G4: 36 | H4: Tổng số tiền vay (VND) | K4: =D4 -> 676832000 | L4: Thời gian ưu đãi (tháng) | N4: 36 | O4: Tổng số tiền vay (VND) | R4: =K4 -> 676832000 | S4: Thời gian ưu đãi (tháng) | U4: 36 | V4: Tổng số tiền vay (VND) | Y4: =R4 -> 676832000 | Z4: Thời gian ưu đãi (tháng) | AB4: 36 | AC4: Tổng số tiền vay (VND) | AF4: =Y4 -> 676832000 | AG4: Thời gian ưu đãi (tháng) | AI4: 36 | AJ4: Tổng số tiền vay (VND) | AM4: =AF4 -> 676832000 | AN4: Thời gian ưu đãi (tháng) | AP4: 36
A5: Thời gian vay (tháng) | D5: 36 | E5: Lãi tạm tính sau ưu đãi (%/năm) | G5: 0.1025 | H5: Thời gian vay (tháng) | K5: 48 | L5: Lãi tạm tính sau ưu đãi (%/năm) | N5: 0.1025 | O5: Thời gian vay (tháng) | R5: 60 | S5: Lãi tạm tính sau ưu đãi (%/năm) | U5: 0.1025 | V5: Thời gian vay (tháng) | Y5: 72 | Z5: Lãi tạm tính sau ưu đãi (%/năm) | AB5: 0.1025 | AC5: Thời gian vay (tháng) | AF5: 84 | AG5: Lãi tạm tính sau ưu đãi (%/năm) | AI5: 0.1025 | AJ5: Thời gian vay (tháng) | AM5: 96 | AN5: Lãi tạm tính sau ưu đãi (%/năm) | AP5: 0.1025
A6: Lãi suất ưu đãi (%/năm) | D6: 0.048 | E6: Ngày vay dự kiến | G6: =TODAY() -> 45958 | H6: Lãi suất ưu đãi (%/năm) | K6: 0.048 | L6: Ngày vay dự kiến | N6: =TODAY() -> 45958 | O6: Lãi suất ưu đãi (%/năm) | R6: 0.048 | S6: Ngày vay dự kiến | U6: =TODAY() -> 45958 | V6: Lãi suất ưu đãi (%/năm) | Y6: 0.048 | Z6: Ngày vay dự kiến | AB6: =TODAY() -> 45958 | AC6: Lãi suất ưu đãi (%/năm) | AF6: 0.048 | AG6: Ngày vay dự kiến | AI6: =TODAY() -> 45958 | AJ6: Lãi suất ưu đãi (%/năm) | AM6: 0.048 | AN6: Ngày vay dự kiến | AP6: =TODAY() -> 45958
A7: Số tiền trả trước | D7: ='Báo giá'!$D$36 -> 64821200 | E7: =TODAY() -> 45958 | H7: Số tiền trả trước | K7: ='Báo giá'!$D$36 -> 64821200 | L7: =TODAY() -> 45958 | O7: Số tiền trả trước | R7: ='Báo giá'!$D$36 -> 64821200 | S7: =TODAY() -> 45958 | V7: Số tiền trả trước | Y7: ='Báo giá'!$D$36 -> 64821200 | Z7: =TODAY() -> 45958 | AC7: Số tiền trả trước | AF7: ='Báo giá'!$D$36 -> 64821200 | AG7: =TODAY() -> 45958 | AJ7: Số tiền trả trước | AM7: ='Báo giá'!$D$36 -> 64821200 | AN7: =TODAY() -> 45958
A8: =D5 -> 36 | G8: Tháng | H8: =K5 -> 48 | N8: Tháng | O8: =R5 -> 60 | U8: Tháng | V8: =Y5 -> 72 | AB8: Tháng | AC8: =AF5 -> 84 | AI8: Tháng | AJ8: =AM5 -> 96 | AP8: Tháng
A9: Ngày đóng | B9: Kỳ hạn | C9: Số ngày | D9: Trả gốc | E9: Trả lãi | F9: Total | G9: Dư nợ còn lại | H9: Ngày đóng | I9: Kỳ hạn | J9: Số ngày | K9: Trả gốc | L9: Trả lãi | M9: Total | N9: Dư nợ còn lại | O9: Ngày đóng | P9: Kỳ hạn | Q9: Số ngày | R9: Trả gốc | S9: Trả lãi | T9: Total | U9: Dư nợ còn lại | V9: Ngày đóng | W9: Kỳ hạn | X9: Số ngày | Y9: Trả gốc | Z9: Trả lãi | AA9: Total | AB9: Dư nợ còn lại | AC9: Ngày đóng | AD9: Kỳ hạn | AE9: Số ngày | AF9: Trả gốc | AG9: Trả lãi | AH9: Total | AI9: Dư nợ còn lại | AJ9: Ngày đóng | AK9: Kỳ hạn | AL9: Số ngày | AM9: Trả gốc | AN9: Trả lãi | AO9: Total | AP9: Dư nợ còn lại
A10: =$G$6 -> 45958 | B10: 0 | G10: =D4-D10 -> 676832000 | H10: =$G$6 -> 45958 | I10: 1 | N10: =K4-K10 -> 676832000 | O10: =$G$6 -> 45958 | P10: 2 | U10: =R4-R10 -> 676832000 | V10: =$G$6 -> 45958 | W10: 3 | AB10: =Y4-Y10 -> 676832000 | AC10: =$G$6 -> 45958 | AD10: 4 | AI10: =AF4-AF10 -> 676832000 | AJ10: =$G$6 -> 45958 | AK10: 5 | AP10: =AM4-AM10 -> 676832000
A11: =IF(B10<$D$5,DATE(YEAR(A10),MONTH(A10)+1,DAY(A10)),IF(B10=$D$5,"Tổng","")) -> 45989 | B11: =IF($B$10<$D$5,$B$10+1,"") -> 1 | C11: =IF($B$11<>"",$A$11-$A$10,"") -> 31 | D11: =IF(B10<D5,IF(B10<G7,0,D4/(D5-G7)),IF(B10=D5,D4,"")) -> 18800889 | E11: =IF(AND(B11<>"",B11<=G4),G10*C11*D6/360,IF(B11<>"",G10*C11*G5/360,IF(AND(B10<>"",B10=D5),SUM(E10:E10),""))) -> 2797572.3 | F11: =IF(D11<>"",D11+E11,"") -> 21598461 | G11: =IF(B11<>"",G10-D11,"") -> 6.5803111e+08 | H11: =IF(I10<$D$5,DATE(YEAR(H10),MONTH(H10)+1,DAY(H10)),IF(I10=$D$5,"Tổng","")) -> 45989 | I11: =IF($B$10<$D$5,$B$10+1,"") -> 1 | J11: =IF($B$11<>"",$A$11-$A$10,"") -> 31 | K11: =IF(I10<K5,IF(I10<N7,0,K4/(K5-N7)),IF(I10=K5,K4,"")) -> 14100667 | L11: =IF(AND(I11<>"",I11<=N4),N10*J11*K6/360,IF(I11<>"",N10*J11*N5/360,IF(AND(I10<>"",I10=K5),SUM(L10:L10),""))) -> 2797572.3 | M11: =IF(K11<>"",K11+L11,"") -> 16898239 | N11: =IF(I11<>"",N10-K11,"") -> 6.6273133e+08 | O11: =IF(P10<$D$5,DATE(YEAR(O10),MONTH(O10)+1,DAY(O10)),IF(P10=$D$5,"Tổng","")) -> 45989 | P11: =IF($B$10<$D$5,$B$10+1,"") -> 1 | Q11: =IF($B$11<>"",$A$11-$A$10,"") -> 31 | R11: =IF(P10<R5,IF(P10<U7,0,R4/(R5-U7)),IF(P10=R5,R4,"")) -> 11280533 | S11: =IF(AND(P11<>"",P11<=U4),U10*Q11*R6/360,IF(P11<>"",U10*Q11*U5/360,IF(AND(P10<>"",P10=R5),SUM(S10:S10),""))) -> 2797572.3 | T11: =IF(R11<>"",R11+S11,"") -> 14078106 | U11: =IF(P11<>"",U10-R11,"") -> 6.6555147e+08 | V11: =IF(W10<$D$5,DATE(YEAR(V10),MONTH(V10)+1,DAY(V10)),IF(W10=$D$5,"Tổng","")) -> 45989 | W11: =IF($B$10<$D$5,$B$10+1,"") -> 1 | X11: =IF($B$11<>"",$A$11-$A$10,"") -> 31 | Y11: =IF(W10<Y5,IF(W10<AB7,0,Y4/(Y5-AB7)),IF(W10=Y5,Y4,"")) -> 9400444.4 | Z11: =IF(AND(W11<>"",W11<=AB4),AB10*X11*Y6/360,IF(W11<>"",AB10*X11*AB5/360,IF(AND(W10<>"",W10=Y5),SUM(Z10:Z10),""))) -> 2797572.3 | AA11: =IF(Y11<>"",Y11+Z11,"") -> 12198017 | AB11: =IF(W11<>"",AB10-Y11,"") -> 6.6743156e+08 | AC11: =IF(AD10<$D$5,DATE(YEAR(AC10),MONTH(AC10)+1,DAY(AC10)),IF(AD10=$D$5,"Tổng","")) -> 45989 | AD11: =IF($B$10<$D$5,$B$10+1,"") -> 1 | AE11: =IF($B$11<>"",$A$11-$A$10,"") -> 31 | AF11: =IF(AD10<AF5,IF(AD10<AI7,0,AF4/(AF5-AI7)),IF(AD10=AF5,AF4,"")) -> 8057523.8 | AG11: =IF(AND(AD11<>"",AD11<=AI4),AI10*AE11*AF6/360,IF(AD11<>"",AI10*AE11*AI5/360,IF(AND(AD10<>"",AD10=AF5),SUM(AG10:AG10),""))) -> 2797572.3 | AH11: =IF(AF11<>"",AF11+AG11,"") -> 10855096 | AI11: =IF(AD11<>"",AI10-AF11,"") -> 6.6877448e+08 | AJ11: =IF(AK10<$D$5,DATE(YEAR(AJ10),MONTH(AJ10)+1,DAY(AJ10)),IF(AK10=$D$5,"Tổng","")) -> 45989 | AK11: =IF($B$10<$D$5,$B$10+1,"") -> 1 | AL11: =IF($B$11<>"",$A$11-$A$10,"") -> 31 | AM11: =IF(AK10<AM5,IF(AK10<AP7,0,AM4/(AM5-AP7)),IF(AK10=AM5,AM4,"")) -> 7050333.3 | AN11: =IF(AND(AK11<>"",AK11<=AP4),AP10*AL11*AM6/360,IF(AK11<>"",AP10*AL11*AP5/360,IF(AND(AK10<>"",AK10=AM5),SUM(AN10:AN10),""))) -> 2797572.3 | AO11: =IF(AM11<>"",AM11+AN11,"") -> 9847905.6 | AP11: =IF(AK11<>"",AP10-AM11,"") -> 6.6978167e+08

Sheet LS_Custom
A1: LỊCH TRẢ NỢ DỰ KIẾN
A2: KHÁCH HÀNG VAY
A3: Giá xe | D3: -
A4: Tổng số tiền vay (VND) | D4: 35000000 | E4: Thời gian ưu đãi (tháng) | G4: 24
A5: Thời gian vay (tháng) | D5: 36 | E5: Lãi dự kiến sau ưu đãi (%/năm) | G5: 0.0925
A6: Lãi suất ưu đãi (%/năm) | D6: 0.32 | E6: Ngày vay dự kiến | G6: =TODAY() -> 45958 | J6: =1192174*24 -> 28612176
A7: Số tiền vay | C7: =D4 -> 35000000 | E7: Thời gian ân hạn gốc (tháng) | G7: 0 | J7: 12
A8: =D5 -> 36 | G8: Tháng | J8: =J7+12 -> 24
A9: Ngày đóng | B9: Kỳ hạn | C9: Số ngày | D9: Trả gốc | E9: Trả lãi | F9: Total | G9: Dư nợ còn lại
A10: =$G$6 -> 45958 | B10: 0 | G10: =$D4-D10 -> 35000000
A11: =IF(B10<$D$5,DATE(YEAR(A10),MONTH(A10)+1,DAY(A10)),IF(B10=$D$5,"Tổng","")) -> 45989 | B11: =IF(B10<$D$5,B10+1,"") -> 1 | C11: =IF(B11<>"",A11-A10,"") -> 31 | D11: =IF($B10<$D$5,IF(B10<$G$7,0,$D$4/($D$5-$G$7)),IF($B10=$D$5,$D$4,"")) -> 972222.22 | E11: =IF(AND($B11<>"",$B11<=$G$4),$G10*C11*$D$6/360,IF(B11<>"",$G10*C11*$G$5/360,IF(AND(B10<>"",B10=$D$5),SUM($E$10:E10),""))) -> 964444.44 | F11: =IF(D11<>"",D11+E11,"") -> 1936666.7 | G11: =IF($B11<>"",G10-D11,"") -> 34027778 | J11: =J10+12 -> 12
A12: =IF(B11<$D$5,DATE(YEAR(A11),MONTH(A11)+1,DAY(A11)),IF(B11=$D$5,"Tổng","")) -> 46019 | B12: =IF(B11<$D$5,B11+1,"") -> 2 | C12: =IF(B12<>"",A12-A11,"") -> 30 | D12: =IF($B11<$D$5,IF(B11<$G$7,0,$D$4/($D$5-$G$7)),IF($B11=$D$5,$D$4,"")) -> 972222.22 | E12: =IF(AND($B12<>"",$B12<=$G$4),$G11*C12*$D$6/360,IF(B12<>"",$G11*C12*$G$5/360,IF(AND(B11<>"",B11=$D$5),SUM($E$10:E11),""))) -> 907407.41 | F12: =IF(D12<>"",D12+E12,"") -> 1879629.6 | G12: =IF($B12<>"",G11-D12,"") -> 33055556 | J12: =J11+12 -> 24
A13: =IF(B12<$D$5,DATE(YEAR(A12),MONTH(A12)+1,DAY(A12)),IF(B12=$D$5,"Tổng","")) -> 46050 | B13: =IF(B12<$D$5,B12+1,"") -> 3 | C13: =IF(B13<>"",A13-A12,"") -> 31 | D13: =IF($B12<$D$5,IF(B12<$G$7,0,$D$4/($D$5-$G$7)),IF($B12=$D$5,$D$4,"")) -> 972222.22 | E13: =IF(AND($B13<>"",$B13<=$G$4),$G12*C13*$D$6/360,IF(B13<>"",$G12*C13*$G$5/360,IF(AND(B12<>"",B12=$D$5),SUM($E$10:E12),""))) -> 910864.2 | F13: =IF(D13<>"",D13+E13,"") -> 1883086.4 | G13: =IF($B13<>"",G12-D13,"") -> 32083333 | J13: =J12+12 -> 36
A14: =IF(B13<$D$5,DATE(YEAR(A13),MONTH(A13)+1,DAY(A13)),IF(B13=$D$5,"Tổng","")) -> 46081 | B14: =IF(B13<$D$5,B13+1,"") -> 4 | C14: =IF(B14<>"",A14-A13,"") -> 31 | D14: =IF($B13<$D$5,IF(B13<$G$7,0,$D$4/($D$5-$G$7)),IF($B13=$D$5,$D$4,"")) -> 972222.22 | E14: =IF(AND($B14<>"",$B14<=$G$4),$G13*C14*$D$6/360,IF(B14<>"",$G13*C14*$G$5/360,IF(AND(B13<>"",B13=$D$5),SUM($E$10:E13),""))) -> 884074.07 | F14: =IF(D14<>"",D14+E14,"") -> 1856296.3 | G14: =IF($B14<>"",G13-D14,"") -> 31111111 | J14: =J13+12 -> 48
A15: =IF(B14<$D$5,DATE(YEAR(A14),MONTH(A14)+1,DAY(A14)),IF(B14=$D$5,"Tổng","")) -> 46109 | B15: =IF(B14<$D$5,B14+1,"") -> 5 | C15: =IF(B15<>"",A15-A14,"") -> 28 | D15: =IF($B14<$D$5,IF(B14<$G$7,0,$D$4/($D$5-$G$7)),IF($B14=$D$5,$D$4,"")) -> 972222.22 | E15: =IF(AND($B15<>"",$B15<=$G$4),$G14*C15*$D$6/360,IF(B15<>"",$G14*C15*$G$5/360,IF(AND(B14<>"",B14=$D$5),SUM($E$10:E14),""))) -> 774320.99 | F15: =IF(D15<>"",D15+E15,"") -> 1746543.2 | G15: =IF($B15<>"",G14-D15,"") -> 30138889
A16: =IF(B15<$D$5,DATE(YEAR(A15),MONTH(A15)+1,DAY(A15)),IF(B15=$D$5,"Tổng","")) -> 46140 | B16: =IF(B15<$D$5,B15+1,"") -> 6 | C16: =IF(B16<>"",A16-A15,"") -> 31 | D16: =IF($B15<$D$5,IF(B15<$G$7,0,$D$4/($D$5-$G$7)),IF($B15=$D$5,$D$4,"")) -> 972222.22 | E16: =IF(AND($B16<>"",$B16<=$G$4),$G15*C16*$D$6/360,IF(B16<>"",$G15*C16*$G$5/360,IF(AND(B15<>"",B15=$D$5),SUM($E$10:E15),""))) -> 830493.83 | F16: =IF(D16<>"",D16+E16,"") -> 1802716 | G16: =IF($B16<>"",G15-D16,"") -> 29166667
A17: =IF(B16<$D$5,DATE(YEAR(A16),MONTH(A16)+1,DAY(A16)),IF(B16=$D$5,"Tổng","")) -> 46170 | B17: =IF(B16<$D$5,B16+1,"") -> 7 | C17: =IF(B17<>"",A17-A16,"") -> 30 | D17: =IF($B16<$D$5,IF(B16<$G$7,0,$D$4/($D$5-$G$7)),IF($B16=$D$5,$D$4,"")) -> 972222.22 | E17: =IF(AND($B17<>"",$B17<=$G$4),$G16*C17*$D$6/360,IF(B17<>"",$G16*C17*$G$5/360,IF(AND(B16<>"",B16=$D$5),SUM($E$10:E16),""))) -> 777777.78 | F17: =IF(D17<>"",D17+E17,"") -> 1750000 | G17: =IF($B17<>"",G16-D17,"") -> 28194444
A18: =IF(B17<$D$5,DATE(YEAR(A17),MONTH(A17)+1,DAY(A17)),IF(B17=$D$5,"Tổng","")) -> 46201 | B18: =IF(B17<$D$5,B17+1,"") -> 8 | C18: =IF(B18<>"",A18-A17,"") -> 31 | D18: =IF($B17<$D$5,IF(B17<$G$7,0,$D$4/($D$5-$G$7)),IF($B17=$D$5,$D$4,"")) -> 972222.22 | E18: =IF(AND($B18<>"",$B18<=$G$4),$G17*C18*$D$6/360,IF(B18<>"",$G17*C18*$G$5/360,IF(AND(B17<>"",B17=$D$5),SUM($E$10:E17),""))) -> 776913.58 | F18: =IF(D18<>"",D18+E18,"") -> 1749135.8 | G18: =IF($B18<>"",G17-D18,"") -> 27222222
A19: =IF(B18<$D$5,DATE(YEAR(A18),MONTH(A18)+1,DAY(A18)),IF(B18=$D$5,"Tổng","")) -> 46231 | B19: =IF(B18<$D$5,B18+1,"") -> 9 | C19: =IF(B19<>"",A19-A18,"") -> 30 | D19: =IF($B18<$D$5,IF(B18<$G$7,0,$D$4/($D$5-$G$7)),IF($B18=$D$5,$D$4,"")) -> 972222.22 | E19: =IF(AND($B19<>"",$B19<=$G$4),$G18*C19*$D$6/360,IF(B19<>"",$G18*C19*$G$5/360,IF(AND(B18<>"",B18=$D$5),SUM($E$10:E18),""))) -> 725925.93 | F19: =IF(D19<>"",D19+E19,"") -> 1698148.1 | G19: =IF($B19<>"",G18-D19,"") -> 26250000
A20: =IF(B19<$D$5,DATE(YEAR(A19),MONTH(A19)+1,DAY(A19)),IF(B19=$D$5,"Tổng","")) -> 46262 | B20: =IF(B19<$D$5,B19+1,"") -> 10 | C20: =IF(B20<>"",A20-A19,"") -> 31 | D20: =IF($B19<$D$5,IF(B19<$G$7,0,$D$4/($D$5-$G$7)),IF($B19=$D$5,$D$4,"")) -> 972222.22 | E20: =IF(AND($B20<>"",$B20<=$G$4),$G19*C20*$D$6/360,IF(B20<>"",$G19*C20*$G$5/360,IF(AND(B19<>"",B19=$D$5),SUM($E$10:E19),""))) -> 723333.33 | F20: =IF(D20<>"",D20+E20,"") -> 1695555.6 | G20: =IF($B20<>"",G19-D20,"") -> 25277778
A21: =IF(B20<$D$5,DATE(YEAR(A20),MONTH(A20)+1,DAY(A20)),IF(B20=$D$5,"Tổng","")) -> 46293 | B21: =IF(B20<$D$5,B20+1,"") -> 11 | C21: =IF(B21<>"",A21-A20,"") -> 31 | D21: =IF($B20<$D$5,IF(B20<$G$7,0,$D$4/($D$5-$G$7)),IF($B20=$D$5,$D$4,"")) -> 972222.22 | E21: =IF(AND($B21<>"",$B21<=$G$4),$G20*C21*$D$6/360,IF(B21<>"",$G20*C21*$G$5/360,IF(AND(B20<>"",B20=$D$5),SUM($E$10:E20),""))) -> 696543.21 | F21: =IF(D21<>"",D21+E21,"") -> 1668765.4 | G21: =IF($B21<>"",G20-D21,"") -> 24305556
A22: =IF(B21<$D$5,DATE(YEAR(A21),MONTH(A21)+1,DAY(A21)),IF(B21=$D$5,"Tổng","")) -> 46323 | B22: =IF(B21<$D$5,B21+1,"") -> 12 | C22: =IF(B22<>"",A22-A21,"") -> 30 | D22: =IF($B21<$D$5,IF(B21<$G$7,0,$D$4/($D$5-$G$7)),IF($B21=$D$5,$D$4,"")) -> 972222.22 | E22: =IF(AND($B22<>"",$B22<=$G$4),$G21*C22*$D$6/360,IF(B22<>"",$G21*C22*$G$5/360,IF(AND(B21<>"",B21=$D$5),SUM($E$10:E21),""))) -> 648148.15 | F22: =IF(D22<>"",D22+E22,"") -> 1620370.4 | G22: =IF($B22<>"",G21-D22,"") -> 23333333
A23: =IF(B22<$D$5,DATE(YEAR(A22),MONTH(A22)+1,DAY(A22)),IF(B22=$D$5,"Tổng","")) -> 46354 | B23: =IF(B22<$D$5,B22+1,"") -> 13 | C23: =IF(B23<>"",A23-A22,"") -> 31 | D23: =IF($B22<$D$5,IF(B22<$G$7,0,$D$4/($D$5-$G$7)),IF($B22=$D$5,$D$4,"")) -> 972222.22 | E23: =IF(AND($B23<>"",$B23<=$G$4),$G22*C23*$D$6/360,IF(B23<>"",$G22*C23*$G$5/360,IF(AND(B22<>"",B22=$D$5),SUM($E$10:E22),""))) -> 642962.96 | F23: =IF(D23<>"",D23+E23,"") -> 1615185.2 | G23: =IF($B23<>"",G22-D23,"") -> 22361111
A24: =IF(B23<$D$5,DATE(YEAR(A23),MONTH(A23)+1,DAY(A23)),IF(B23=$D$5,"Tổng","")) -> 46384 | B24: =IF(B23<$D$5,B23+1,"") -> 14 | C24: =IF(B24<>"",A24-A23,"") -> 30 | D24: =IF($B23<$D$5,IF(B23<$G$7,0,$D$4/($D$5-$G$7)),IF($B23=$D$5,$D$4,"")) -> 972222.22 | E24: =IF(AND($B24<>"",$B24<=$G$4),$G23*C24*$D$6/360,IF(B24<>"",$G23*C24*$G$5/360,IF(AND(B23<>"",B23=$D$5),SUM($E$10:E23),""))) -> 596296.3 | F24: =IF(D24<>"",D24+E24,"") -> 1568518.5 | G24: =IF($B24<>"",G23-D24,"") -> 21388889
A25: =IF(B24<$D$5,DATE(YEAR(A24),MONTH(A24)+1,DAY(A24)),IF(B24=$D$5,"Tổng","")) -> 46415 | B25: =IF(B24<$D$5,B24+1,"") -> 15 | C25: =IF(B25<>"",A25-A24,"") -> 31 | D25: =IF($B24<$D$5,IF(B24<$G$7,0,$D$4/($D$5-$G$7)),IF($B24=$D$5,$D$4,"")) -> 972222.22 | E25: =IF(AND($B25<>"",$B25<=$G$4),$G24*C25*$D$6/360,IF(B25<>"",$G24*C25*$G$5/360,IF(AND(B24<>"",B24=$D$5),SUM($E$10:E24),""))) -> 589382.72 | F25: =IF(D25<>"",D25+E25,"") -> 1561604.9 | G25: =IF($B25<>"",G24-D25,"") -> 20416667
A26: =IF(B25<$D$5,DATE(YEAR(A25),MONTH(A25)+1,DAY(A25)),IF(B25=$D$5,"Tổng","")) -> 46446 | B26: =IF(B25<$D$5,B25+1,"") -> 16 | C26: =IF(B26<>"",A26-A25,"") -> 31 | D26: =IF($B25<$D$5,IF(B25<$G$7,0,$D$4/($D$5-$G$7)),IF($B25=$D$5,$D$4,"")) -> 972222.22 | E26: =IF(AND($B26<>"",$B26<=$G$4),$G25*C26*$D$6/360,IF(B26<>"",$G25*C26*$G$5/360,IF(AND(B25<>"",B25=$D$5),SUM($E$10:E25),""))) -> 562592.59 | F26: =IF(D26<>"",D26+E26,"") -> 1534814.8 | G26: =IF($B26<>"",G25-D26,"") -> 19444444
... A195: =IF(B194<$D$5,DATE(YEAR(A194),MONTH(A194)+1,DAY(A194)),IF(B194=$D$5,"Tổng","")) | B195: =IF(B194<$D$5,B194+1,"") | C195: =IF(B195<>"",A195-A194,"") | D195: =IF($B194<$D$5,IF(B194<$G$7,0,$D$4/($D$5-$G$7)),IF($B194=$D$5,$D$4,"")) | E195: =IF(AND($B195<>"",$B195<=$G$4),$G194*C195*$D$6/360,IF(B195<>"",$G194*C195*$G$5/360,IF(AND(B194<>"",B194=$D$5),SUM($E$10:E194),""))) | F195: =IF(D195<>"",D195+E195,"") | G195: =IF($B195<>"",G194-D195,"")
A196: =IF(B195<$D$5,DATE(YEAR(A195),MONTH(A195)+1,DAY(A195)),IF(B195=$D$5,"Tổng","")) | B196: =IF(B195<$D$5,B195+1,"") | C196: =IF(B196<>"",A196-A195,"") | D196: =IF($B195<$D$5,$D$4/$D$5,IF($B195=$D$5,$D$4,"")) | E196: =IF(AND($B196<>"",$B196<=$G$4),$G195*C196*$D$6/360,IF(B196<>"",$G195*C196*$G$5/360,IF(AND(B195<>"",B195=$D$5),SUM($E$10:E195),""))) | F196: =IF(D196<>"",D196+E196,"") | G196: =IF($B196<>"",G195-D196,"")
A197: =IF(B196<$D$5,DATE(YEAR(A196),MONTH(A196)+1,DAY(A196)),IF(B196=$D$5,"Tổng","")) | B197: =IF(B196<$D$5,B196+1,"") | C197: =IF(B197<>"",A197-A196,"") | D197: =IF($B196<$D$5,$D$4/$D$5,IF($B196=$D$5,$D$4,"")) | E197: =IF(AND($B197<>"",$B197<=$G$4),$G196*C197*$D$6/360,IF(B197<>"",$G196*C197*$G$5/360,IF(AND(B196<>"",B196=$D$5),SUM($E$10:E196),""))) | F197: =IF(D197<>"",D197+E197,"") | G197: =IF($B197<>"",G196-D197,"")
A198: =IF(B197<$D$5,DATE(YEAR(A197),MONTH(A197)+1,DAY(A197)),IF(B197=$D$5,"Tổng","")) | B198: =IF(B197<$D$5,B197+1,"") | C198: =IF(B198<>"",A198-A197,"") | D198: =IF($B197<$D$5,$D$4/$D$5,IF($B197=$D$5,$D$4,"")) | E198: =IF(AND($B198<>"",$B198<=$G$4),$G197*C198*$D$6/360,IF(B198<>"",$G197*C198*$G$5/360,IF(AND(B197<>"",B197=$D$5),SUM($E$10:E197),""))) | F198: =IF(D198<>"",D198+E198,"") | G198: =IF($B198<>"",G197-D198,"")
A199: =IF(B198<$D$5,DATE(YEAR(A198),MONTH(A198)+1,DAY(A198)),IF(B198=$D$5,"Tổng","")) | B199: =IF(B198<$D$5,B198+1,"") | C199: =IF(B199<>"",A199-A198,"") | D199: =IF($B198<$D$5,$D$4/$D$5,IF($B198=$D$5,$D$4,"")) | E199: =IF(AND($B199<>"",$B199<=$G$4),$G198*C199*$D$6/360,IF(B199<>"",$G198*C199*$G$5/360,IF(AND(B198<>"",B198=$D$5),SUM($E$10:E198),""))) | F199: =IF(D199<>"",D199+E199,"") | G199: =IF($B199<>"",G198-D199,"")
A200: =IF(B199<$D$5,DATE(YEAR(A199),MONTH(A199)+1,DAY(A199)),IF(B199=$D$5,"Tổng","")) | B200: =IF(B199<$D$5,B199+1,"") | C200: =IF(B200<>"",A200-A199,"") | D200: =IF($B199<$D$5,$D$4/$D$5,IF($B199=$D$5,$D$4,"")) | E200: =IF(AND($B200<>"",$B200<=$G$4),$G199*C200*$D$6/360,IF(B200<>"",$G199*C200*$G$5/360,IF(AND(B199<>"",B199=$D$5),SUM($E$10:E199),""))) | F200: =IF(D200<>"",D200+E200,"") | G200: =IF($B200<>"",G199-D200,"")
A201: =IF(B200<$D$5,DATE(YEAR(A200),MONTH(A200)+1,DAY(A200)),IF(B200=$D$5,"Tổng","")) | B201: =IF(B200<$D$5,B200+1,"") | C201: =IF(B201<>"",A201-A200,"") | D201: =IF($B200<$D$5,$D$4/$D$5,IF($B200=$D$5,$D$4,"")) | E201: =IF(AND($B201<>"",$B201<=$G$4),$G200*C201*$D$6/360,IF(B201<>"",$G200*C201*$G$5/360,IF(AND(B200<>"",B200=$D$5),SUM($E$10:E200),""))) | F201: =IF(D201<>"",D201+E201,"") | G201: =IF($B201<>"",G200-D201,"")
A202: =IF(B201<$D$5,DATE(YEAR(A201),MONTH(A201)+1,DAY(A201)),IF(B201=$D$5,"Tổng","")) | B202: =IF(B201<$D$5,B201+1,"") | C202: =IF(B202<>"",A202-A201,"") | D202: =IF($B201<$D$5,$D$4/$D$5,IF($B201=$D$5,$D$4,"")) | E202: =IF(AND($B202<>"",$B202<=$G$4),$G201*C202*$D$6/360,IF(B202<>"",$G201*C202*$G$5/360,IF(AND(B201<>"",B201=$D$5),SUM($E$10:E201),""))) | F202: =IF(D202<>"",D202+E202,"") | G202: =IF($B202<>"",G201-D202,"")
A203: =IF(B202<$D$5,DATE(YEAR(A202),MONTH(A202)+1,DAY(A202)),IF(B202=$D$5,"Tổng","")) | B203: =IF(B202<$D$5,B202+1,"") | C203: =IF(B203<>"",A203-A202,"") | D203: =IF($B202<$D$5,$D$4/$D$5,IF($B202=$D$5,$D$4,"")) | E203: =IF(AND($B203<>"",$B203<=$G$4),$G202*C203*$D$6/360,IF(B203<>"",$G202*C203*$G$5/360,IF(AND(B202<>"",B202=$D$5),SUM($E$10:E202),""))) | F203: =IF(D203<>"",D203+E203,"") | G203: =IF($B203<>"",G202-D203,"")
A204: =IF(B203<$D$5,DATE(YEAR(A203),MONTH(A203)+1,DAY(A203)),IF(B203=$D$5,"Tổng","")) | B204: =IF(B203<$D$5,B203+1,"") | C204: =IF(B204<>"",A204-A203,"") | D204: =IF($B203<$D$5,$D$4/$D$5,IF($B203=$D$5,$D$4,"")) | E204: =IF(AND($B204<>"",$B204<=$G$4),$G203*C204*$D$6/360,IF(B204<>"",$G203*C204*$G$5/360,IF(AND(B203<>"",B203=$D$5),SUM($E$10:E203),""))) | F204: =IF(D204<>"",D204+E204,"") | G204: =IF($B204<>"",G203-D204,"")
A205: =IF(B204<$D$5,DATE(YEAR(A204),MONTH(A204)+1,DAY(A204)),IF(B204=$D$5,"Tổng","")) | B205: =IF(B204<$D$5,B204+1,"") | C205: =IF(B205<>"",A205-A204,"") | D205: =IF($B204<$D$5,$D$4/$D$5,IF($B204=$D$5,$D$4,"")) | E205: =IF(AND($B205<>"",$B205<=$G$4),$G204*C205*$D$6/360,IF(B205<>"",$G204*C205*$G$5/360,IF(AND(B204<>"",B204=$D$5),SUM($E$10:E204),""))) | F205: =IF(D205<>"",D205+E205,"") | G205: =IF($B205<>"",G204-D205,"")
A206: =IF(B205<$D$5,DATE(YEAR(A205),MONTH(A205)+1,DAY(A205)),IF(B205=$D$5,"Tổng","")) | B206: =IF(B205<$D$5,B205+1,"") | C206: =IF(B206<>"",A206-A205,"") | D206: =IF($B205<$D$5,$D$4/$D$5,IF($B205=$D$5,$D$4,"")) | E206: =IF(AND($B206<>"",$B206<=$G$4),$G205*C206*$D$6/360,IF(B206<>"",$G205*C206*$G$5/360,IF(AND(B205<>"",B205=$D$5),SUM($E$10:E205),""))) | F206: =IF(D206<>"",D206+E206,"") | G206: =IF($B206<>"",G205-D206,"")
A207: =IF(B206<$D$5,DATE(YEAR(A206),MONTH(A206)+1,DAY(A206)),IF(B206=$D$5,"Tổng","")) | B207: =IF(B206<$D$5,B206+1,"") | C207: =IF(B207<>"",A207-A206,"") | D207: =IF($B206<$D$5,$D$4/$D$5,IF($B206=$D$5,$D$4,"")) | E207: =IF(AND($B207<>"",$B207<=$G$4),$G206*C207*$D$6/360,IF(B207<>"",$G206*C207*$G$5/360,IF(AND(B206<>"",B206=$D$5),SUM($E$10:E206),""))) | F207: =IF(D207<>"",D207+E207,"") | G207: =IF($B207<>"",G206-D207,"")
... A251: =IF(B250<$D$5,DATE(YEAR(A250),MONTH(A250)+1,DAY(A250)),IF(B250=$D$5,"Tổng","")) | B251: =IF(B250<$D$5,B250+1,"") | C251: =IF(B251<>"",A251-A250,"") | D251: =IF($B250<$D$5,$D$4/$D$5,IF($B250=$D$5,$D$4,"")) | E251: =IF(AND($B251<>"",$B251<=$G$4),$G250*C251*$D$6/360,IF(B251<>"",$G250*C251*$G$5/360,IF(AND(B250<>"",B250=$D$5),SUM($E$10:E250),""))) | F251: =IF(D251<>"",D251+E251,"") | G251: =IF($B251<>"",G250-D251,"")
A252: =IF(B251<$D$5,DATE(YEAR(A251),MONTH(A251)+1,DAY(A251)),IF(B251=$D$5,"Tổng","")) | B252: =IF(B251<$D$5,B251+1,"") | C252: =IF(B252<>"",A252-A251,"") | D252: =IF($B251<$D$5,$D$4/$D$5,IF($B251=$D$5,$D$4,"")) | E252: =IF(AND($B252<>"",$B252<=$G$4),$G251*C252*$D$6/360,IF(B252<>"",$G251*C252*$G$5/360,IF(AND(B252<>"",B251=$D$5),SUM($E$10:E251),""))) | F252: =IF(D252<>"",D252+E252,"") | G252: =IF($B252<>"",G251-D252,"")
A253: =IF(B252<$D$5,DATE(YEAR(A252),MONTH(A252)+1,DAY(A252)),IF(B252=$D$5,"Tổng","")) | B253: =IF(B252<$D$5,B252+1,"") | C253: =IF(B253<>"",A253-A252,"") | D253: =IF($B252<$D$5,$D$4/$D$5,IF($B252=$D$5,$D$4,"")) | E253: =IF(AND($B253<>"",$B253<=$G$4),$G252*C253*$D$6/360,IF(B253<>"",$G252*C253*$G$5/360,IF(AND(B253<>"",B252=$D$5),SUM($E$10:E252),""))) | F253: =IF(D253<>"",D253+E253,"") | G253: =IF($B253<>"",G252-D253,"")
A254: =IF(B253<$D$5,DATE(YEAR(A253),MONTH(A253)+1,DAY(A253)),IF(B253=$D$5,"Tổng","")) | B254: =IF(B253<$D$5,B253+1,"") | C254: =IF(B254<>"",A254-A253,"") | D254: =IF($B253<$D$5,$D$4/$D$5,IF($B253=$D$5,$D$4,"")) | E254: =IF(AND($B254<>"",$B254<=$G$4),$G253*C254*$D$6/360,IF(B254<>"",$G253*C254*$G$5/360,IF(AND(B254<>"",B253=$D$5),SUM($E$10:E253),""))) | F254: =IF(D254<>"",D254+E254,"") | G254: =IF($B254<>"",G253-D254,"")
A255: =IF(B254<$D$5,DATE(YEAR(A254),MONTH(A254)+1,DAY(A254)),IF(B254=$D$5,"Tổng","")) | B255: =IF(B254<$D$5,B254+1,"") | C255: =IF(B255<>"",A255-A254,"") | D255: =IF($B254<$D$5,$D$4/$D$5,IF($B254=$D$5,$D$4,"")) | E255: =IF(AND($B255<>"",$B255<=$G$4),$G254*C255*$D$6/360,IF(B255<>"",$G254*C255*$G$5/360,IF(AND(B255<>"",B254=$D$5),SUM($E$10:E254),""))) | F255: =IF(D255<>"",D255+E255,"") | G255: =IF($B255<>"",G254-D255,"")
A256: =IF(B255<$D$5,DATE(YEAR(A255),MONTH(A255)+1,DAY(A255)),IF(B255=$D$5,"Tổng","")) | B256: =IF(B255<$D$5,B255+1,"") | C256: =IF(B256<>"",A256-A255,"") | D256: =IF($B255<$D$5,$D$4/$D$5,IF($B255=$D$5,$D$4,"")) | E256: =IF(AND($B256<>"",$B256<=$G$4),$G255*C256*$D$6/360,IF(B256<>"",$G255*C256*$G$5/360,IF(AND(B256<>"",B255=$D$5),SUM($E$10:E255),""))) | F256: =IF(D256<>"",D256+E256,"") | G256: =IF($B256<>"",G255-D256,"")
A257: =IF(B256<$D$5,DATE(YEAR(A256),MONTH(A256)+1,DAY(A256)),IF(B256=$D$5,"Tổng","")) | B257: =IF(B256<$D$5,B256+1,"") | C257: =IF(B257<>"",A257-A256,"") | D257: =IF($B256<$D$5,$D$4/$D$5,IF($B256=$D$5,$D$4,"")) | E257: =IF(AND($B257<>"",$B257<=$G$4),$G256*C257*$D$6/360,IF(B257<>"",$G256*C257*$G$5/360,IF(AND(B257<>"",B256=$D$5),SUM($E$10:E256),""))) | F257: =IF(D257<>"",D257+E257,"") | G257: =IF($B257<>"",G256-D257,"")
A258: =IF(B257<$D$5,DATE(YEAR(A257),MONTH(A257)+1,DAY(A257)),IF(B257=$D$5,"Tổng","")) | B258: =IF(B257<$D$5,B257+1,"") | C258: =IF(B258<>"",A258-A257,"") | D258: =IF($B257<$D$5,$D$4/$D$5,IF($B257=$D$5,$D$4,"")) | E258: =IF(AND($B258<>"",$B258<=$G$4),$G257*C258*$D$6/360,IF(B258<>"",$G257*C258*$G$5/360,IF(AND(B258<>"",B257=$D$5),SUM($E$10:E257),""))) | F258: =IF(D258<>"",D258+E258,"") | G258: =IF($B258<>"",G257-D258,"")
A259: =IF(B258<$D$5,DATE(YEAR(A258),MONTH(A258)+1,DAY(A258)),IF(B258=$D$5,"Tổng","")) | B259: =IF(B258<$D$5,B258+1,"") | C259: =IF(B259<>"",A259-A258,"") | D259: =IF($B258<$D$5,$D$4/$D$5,IF($B258=$D$5,$D$4,"")) | E259: =IF(AND($B259<>"",$B259<=$G$4),$G258*C259*$D$6/360,IF(B259<>"",$G258*C259*$G$5/360,IF(AND(B259<>"",B258=$D$5),SUM($E$10:E258),""))) | F259: =IF(D259<>"",D259+E259,"") | G259: =IF($B259<>"",G258-D259,"")
A260: =IF(B259<$D$5,DATE(YEAR(A259),MONTH(A259)+1,DAY(A259)),IF(B259=$D$5,"Tổng","")) | B260: =IF(B259<$D$5,B259+1,"") | C260: =IF(B260<>"",A260-A259,"") | D260: =IF($B259<$D$5,$D$4/$D$5,IF($B259=$D$5,$D$4,"")) | E260: =IF(AND($B260<>"",$B260<=$G$4),$G259*C260*$D$6/360,IF(B260<>"",$G259*C260*$G$5/360,IF(AND(B260<>"",B259=$D$5),SUM($E$10:E259),""))) | F260: =IF(D260<>"",D260+E260,"") | G260: =IF($B260<>"",G259-D260,"")
A261: =IF(B260<$D$5,DATE(YEAR(A260),MONTH(A260)+1,DAY(A260)),IF(B260=$D$5,"Tổng","")) | B261: =IF(B260<$D$5,B260+1,"") | C261: =IF(B261<>"",A261-A260,"") | D261: =IF($B260<$D$5,$D$4/$D$5,IF($B260=$D$5,$D$4,"")) | E261: =IF(AND($B261<>"",$B261<=$G$4),$G260*C261*$D$6/360,IF(B261<>"",$G260*C261*$G$5/360,IF(AND(B261<>"",B260=$D$5),SUM($E$10:E260),""))) | F261: =IF(D261<>"",D261+E261,"") | G261: =IF($B261<>"",G260-D261,"")
A262: =IF(B261<$D$5,DATE(YEAR(A261),MONTH(A261)+1,DAY(A261)),IF(B261=$D$5,"Tổng","")) | B262: =IF(B261<$D$5,B261+1,"") | C262: =IF(B262<>"",A262-A261,"") | D262: =IF($B261<$D$5,$D$4/$D$5,IF($B261=$D$5,$D$4,"")) | E262: =IF(AND($B262<>"",$B262<=$G$4),$G261*C262*$D$6/360,IF(B262<>"",$G261*C262*$G$5/360,IF(AND(B262<>"",B261=$D$5),SUM($E$10:E261),""))) | F262: =IF(D262<>"",D262+E262,"") | G262: =IF($B262<>"",G261-D262,"")
A263: =IF(B262<$D$5,DATE(YEAR(A262),MONTH(A262)+1,DAY(A262)),IF(B262=$D$5,"Tổng","")) | B263: =IF(B262<$D$5,B262+1,"") | C263: =IF(B263<>"",A263-A262,"") | D263: =IF($B262<$D$5,$D$4/$D$5,IF($B262=$D$5,$D$4,"")) | E263: =IF(AND($B263<>"",$B263<=$G$4),$G262*C263*$D$6/360,IF(B263<>"",$G262*C263*$G$5/360,IF(AND(B263<>"",B262=$D$5),SUM($E$10:E262),""))) | F263: =IF(B263<>"",D263+E263,"") | G263: =IF($B263<>"",G262-D263,"")
A264: =IF(B263<$D$5,DATE(YEAR(A263),MONTH(A263)+1,DAY(A263)),IF(B263=$D$5,"Tổng","")) | B264: =IF(B263<$D$5,B263+1,"") | C264: =IF(B264<>"",A264-A263,"") | D264: =IF($B263<$D$5,$D$4/$D$5,IF($B263=$D$5,$D$4,"")) | E264: =IF(AND($B264<>"",$B264<=$G$4),$G263*C264*$D$6/360,IF(B264<>"",$G263*C264*$G$5/360,IF(AND(B264<>"",B263=$D$5),SUM($E$10:E263),""))) | F264: =IF(B264<>"",D264+E264,"") | G264: =IF($B264<>"",G263-D264,"")
A265: =IF(B264<$D$5,DATE(YEAR(A264),MONTH(A264)+1,DAY(A264)),IF(B264=$D$5,"Tổng","")) | B265: =IF(B264<$D$5,B264+1,"") | C265: =IF(B265<>"",A265-A264,"") | D265: =IF($B264<$D$5,$D$4/$D$5,IF($B264=$D$5,$D$4,"")) | E265: =IF(AND($B265<>"",$B265<=$G$4),$G264*C265*$D$6/360,IF(B265<>"",$G264*C265*$G$5/360,IF(AND(B265<>"",B264=$D$5),SUM($E$10:E264),""))) | F265: =IF(B265<>"",D265+E265,"") | G265: =IF($B265<>"",G264-D265,"")
A266: =IF(B265<$D$5,DATE(YEAR(A265),MONTH(A265)+1,DAY(A265)),IF(B265=$D$5,"Tổng","")) | B266: =IF(B265<$D$5,B265+1,"") | C266: =IF(B266<>"",A266-A265,"") | D266: =IF($B265<$D$5,$D$4/$D$5,IF($B265=$D$5,$D$4,"")) | E266: =IF(AND($B266<>"",$B266<=$G$4),$G265*C266*$D$6/360,IF(B266<>"",$G265*C266*$G$5/360,IF(AND(B266<>"",B265=$D$5),SUM($E$10:E265),""))) | F266: =IF(B266<>"",D266+E266,"") | G266: =IF($B266<>"",G265-D266,"")
A267: =IF(B266<$D$5,DATE(YEAR(A266),MONTH(A266)+1,DAY(A266)),IF(B266=$D$5,"Tổng","")) | B267: =IF(B266<$D$5,B266+1,"") | C267: =IF(B267<>"",A267-A266,"") | D267: =IF($B266<$D$5,$D$4/$D$5,IF($B266=$D$5,$D$4,"")) | E267: =IF(AND($B267<>"",$B267<=$G$4),$G266*C267*$D$6/360,IF(B267<>"",$G266*C267*$G$5/360,IF(AND(B267<>"",B266=$D$5),SUM($E$10:E266),""))) | F267: =IF(B267<>"",D267+E267,"") | G267: =IF($B267<>"",G266-D267,"")
A268: =IF(B267<$D$5,DATE(YEAR(A267),MONTH(A267)+1,DAY(A267)),IF(B267=$D$5,"Tổng","")) | B268: =IF(B267<$D$5,B267+1,"") | C268: =IF(B268<>"",A268-A267,"") | D268: =IF($B267<$D$5,$D$4/$D$5,IF($B267=$D$5,$D$4,"")) | E268: =IF(AND($B268<>"",$B268<=$G$4),$G267*C268*$D$6/360,IF(B268<>"",$G267*C268*$G$5/360,IF(AND(B268<>"",B267=$D$5),SUM($E$10:E267),""))) | F268: =IF(B268<>"",D268+E268,"") | G268: =IF($B268<>"",G267-D268,"")
A269: =IF(B268<$D$5,DATE(YEAR(A268),MONTH(A268)+1,DAY(A268)),IF(B268=$D$5,"Tổng","")) | B269: =IF(B268<$D$5,B268+1,"") | C269: =IF(B269<>"",A269-A268,"") | D269: =IF($B268<$D$5,$D$4/$D$5,IF($B268=$D$5,$D$4,"")) | E269: =IF(AND($B269<>"",$B269<=$G$4),$G268*C269*$D$6/360,IF(B269<>"",$G268*C269*$G$5/360,IF(AND(B269<>"",B268=$D$5),SUM($E$10:E268),""))) | F269: =IF(B269<>"",D269+E269,"") | G269: =IF($B269<>"",G268-D269,"")
A270: =IF(B269<$D$5,DATE(YEAR(A269),MONTH(A269)+1,DAY(A269)),IF(B269=$D$5,"Tổng","")) | B270: =IF(B269<$D$5,B269+1,"") | C270: =IF(B270<>"",A270-A269,"") | D270: =IF($B269<$D$5,$D$4/$D$5,IF($B269=$D$5,$D$4,"")) | E270: =IF(AND($B270<>"",$B270<=$G$4),$G269*C270*$D$6/360,IF(B270<>"",$G269*C270*$G$5/360,IF(AND(B270<>"",B269=$D$5),SUM($E$10:E269),""))) | F270: =IF(B270<>"",D270+E270,"") | G270: =IF($B270<>"",G269-D270,"")
A271: =IF(B270<$D$5,DATE(YEAR(A270),MONTH(A270)+1,DAY(A270)),IF(B270=$D$5,"Tổng","")) | B271: =IF(B270<$D$5,B270+1,"") | C271: =IF(B271<>"",A271-A270,"") | D271: =IF($B270<$D$5,$D$4/$D$5,IF($B270=$D$5,$D$4,"")) | E271: =IF(AND($B271<>"",$B271<=$G$4),$G270*C271*$D$6/360,IF(B271<>"",$G270*C271*$G$5/360,IF(AND(B271<>"",B270=$D$5),SUM($E$10:E270),""))) | F271: =IF(B271<>"",D271+E271,"") | G271: =IF($B271<>"",G270-D271,"")
A272: =IF(B271<$D$5,DATE(YEAR(A271),MONTH(A271)+1,DAY(A271)),IF(B271=$D$5,"Tổng","")) | B272: =IF(B271<$D$5,B271+1,"") | C272: =IF(B272<>"",A272-A271,"") | D272: =IF($B271<$D$5,$D$4/$D$5,IF($B271=$D$5,$D$4,"")) | E272: =IF(AND($B272<>"",$B272<=$G$4),$G271*C272*$D$6/360,IF(B272<>"",$G271*C272*$G$5/360,IF(AND(B272<>"",B271=$D$5),SUM($E$10:E271),""))) | G272: =IF($B272<>"",G271-D272,"")
A273: =IF(B272<$D$5,DATE(YEAR(A272),MONTH(A272)+1,DAY(A272)),IF(B272=$D$5,"Tổng","")) | B273: =IF(B272<$D$5,B272+1,"") | C273: =IF(B273<>"",A273-A272,"") | D273: =IF($B272<$D$5,$D$4/$D$5,IF($B272=$D$5,$D$4,"")) | E273: =IF(AND($B273<>"",$B273<=$G$4),$G272*C273*$D$6/360,IF(B273<>"",$G272*C273*$G$5/360,IF(AND(B273<>"",B272=$D$5),SUM($E$10:E272),""))) | G273: =IF($B273<>"",G272-D273,"")
A274: =IF(B273<$D$5,DATE(YEAR(A273),MONTH(A273)+1,DAY(A273)),IF(B273=$D$5,"Tổng","")) | B274: =IF(B273<$D$5,B273+1,"") | C274: =IF(B274<>"",A274-A273,"") | D274: =IF($B273<$D$5,$D$4/$D$5,IF($B273=$D$5,$D$4,"")) | E274: =IF(AND($B274<>"",$B274<=$G$4),$G273*C274*$D$6/360,IF(B274<>"",$G273*C274*$G$5/360,IF(AND(B274<>"",B273=$D$5),SUM($E$10:E273),""))) | G274: =IF($B274<>"",G273-D274,"")
A275: =IF(B274<$D$5,DATE(YEAR(A274),MONTH(A274)+1,DAY(A274)),IF(B274=$D$5,"Tổng","")) | B275: =IF(B274<$D$5,B274+1,"") | C275: =IF(B275<>"",A275-A274,"") | D275: =IF($B274<$D$5,$D$4/$D$5,IF($B274=$D$5,$D$4,"")) | E275: =IF(AND($B275<>"",$B275<=$G$4),$G274*C275*$D$6/360,IF(B275<>"",$G274*C275*$G$5/360,IF(AND(B275<>"",B274=$D$5),SUM($E$10:E274),""))) | G275: =IF($B275<>"",G274-D275,"")
A276: =IF(B275<$D$5,DATE(YEAR(A275),MONTH(A275)+1,DAY(A275)),IF(B275=$D$5,"Tổng","")) | B276: =IF(B275<$D$5,B275+1,"") | C276: =IF(B276<>"",A276-A275,"") | D276: =IF($B275<$D$5,$D$4/$D$5,IF($B275=$D$5,$D$4,"")) | G276: =IF($B276<>"",G275-D276,"")
A277: =IF(B276<$D$5,DATE(YEAR(A276),MONTH(A276)+1,DAY(A276)),IF(B276=$D$5,"Tổng","")) | B277: =IF(B276<$D$5,B276+1,"") | C277: =IF(B277<>"",A277-A276,"") | D277: =IF($B276<$D$5,$D$4/$D$5,IF($B276=$D$5,$D$4,"")) | G277: =IF($B277<>"",G276-D277,"")
A278: =IF(B277<$D$5,DATE(YEAR(A277),MONTH(A277)+1,DAY(A277)),IF(B277=$D$5,"Tổng","")) | B278: =IF(B277<$D$5,B277+1,"") | C278: =IF(B278<>"",A278-A277,"") | D278: =IF($B277<$D$5,$D$4/$D$5,IF($B277=$D$5,$D$4,"")) | G278: =IF($B278<>"",G277-D278,"")
A279: =IF(B278<$D$5,DATE(YEAR(A278),MONTH(A278)+1,DAY(A278)),IF(B278=$D$5,"Tổng","")) | B279: =IF(B278<$D$5,B278+1,"") | C279: =IF(B279<>"",A279-A278,"") | D279: =IF($B278<$D$5,$D$4/$D$5,IF($B278=$D$5,$D$4,"")) | G279: =IF($B279<>"",G278-D279,"")
A280: =IF(B279<$D$5,DATE(YEAR(A279),MONTH(A279)+1,DAY(A279)),IF(B279=$D$5,"Tổng","")) | B280: =IF(B279<$D$5,B279+1,"") | C280: =IF(B280<>"",A280-A279,"") | D280: =IF($B279<$D$5,$D$4/$D$5,IF($B279=$D$5,$D$4,"")) | G280: =IF($B280<>"",G279-D280,"")
A281: =IF(B280<$D$5,DATE(YEAR(A280),MONTH(A280)+1,DAY(A280)),IF(B280=$D$5,"Tổng","")) | B281: =IF(B280<$D$5,B280+1,"") | C281: =IF(B281<>"",A281-A280,"") | D281: =IF($B280<$D$5,$D$4/$D$5,IF($B280=$D$5,$D$4,"")) | G281: =IF($B281<>"",G280-D281,"")
A282: =IF(B281<$D$5,DATE(YEAR(A281),MONTH(A281)+1,DAY(A281)),IF(B281=$D$5,"Tổng","")) | B282: =IF(B281<$D$5,B281+1,"") | C282: =IF(B282<>"",A282-A281,"") | D282: =IF($B281<$D$5,$D$4/$D$5,IF($B281=$D$5,$D$4,"")) | G282: =IF($B282<>"",G281-D282,"")
A283: =IF(B282<$D$5,DATE(YEAR(A282),MONTH(A282)+1,DAY(A282)),IF(B282=$D$5,"Tổng","")) | B283: =IF(B282<$D$5,B282+1,"") | C283: =IF(B283<>"",A283-A282,"") | D283: =IF($B282<$D$5,$D$4/$D$5,IF($B282=$D$5,$D$4,"")) | G283: =IF($B283<>"",G282-D283,"")
A284: =IF(B283<$D$5,DATE(YEAR(A283),MONTH(A283)+1,DAY(A283)),IF(B283=$D$5,"Tổng","")) | B284: =IF(B283<$D$5,B283+1,"") | C284: =IF(B284<>"",A284-A283,"") | D284: =IF($B283<$D$5,$D$4/$D$5,IF($B283=$D$5,$D$4,"")) | G284: =IF($B284<>"",G283-D284,"")
A285: =IF(B284<$D$5,DATE(YEAR(A284),MONTH(A284)+1,DAY(A284)),IF(B284=$D$5,"Tổng","")) | B285: =IF(B284<$D$5,B284+1,"") | C285: =IF(B285<>"",A285-A284,"") | D285: =IF($B284<$D$5,$D$4/$D$5,IF($B284=$D$5,$D$4,"")) | G285: =IF($B285<>"",G284-D285,"")
A286: =IF(B285<$D$5,DATE(YEAR(A285),MONTH(A285)+1,DAY(A285)),IF(B285=$D$5,"Tổng","")) | B286: =IF(B285<$D$5,B285+1,"") | C286: =IF(B286<>"",A286-A285,"") | D286: =IF($B285<$D$5,$D$4/$D$5,IF($B285=$D$5,$D$4,"")) | G286: =IF($B286<>"",G285-D286,"")
A287: =IF(B286<$D$5,DATE(YEAR(A286),MONTH(A286)+1,DAY(A286)),IF(B286=$D$5,"Tổng","")) | B287: =IF(B286<$D$5,B286+1,"") | C287: =IF(B287<>"",A287-A286,"") | D287: =IF($B286<$D$5,$D$4/$D$5,IF($B286=$D$5,$D$4,"")) | G287: =IF($B287<>"",G286-D287,"")
... A296: =IF(B295<$D$5,DATE(YEAR(A295),MONTH(A295)+1,DAY(A295)),IF(B295=$D$5,"Tổng","")) | B296: =IF(B295<$D$5,B295+1,"") | C296: =IF(B296<>"",A296-A295,"") | D296: =IF($B295<$D$5,$D$4/$D$5,IF($B295=$D$5,$D$4,"")) | G296: =IF($B296<>"",G295-D296,"")
A297: =IF(B296<$D$5,DATE(YEAR(A296),MONTH(A296)+1,DAY(A296)),IF(B296=$D$5,"Tổng","")) | B297: =IF(B296<$D$5,B296+1,"") | C297: =IF(B297<>"",A297-A296,"") | D297: =IF($B296<$D$5,$D$4/$D$5,IF($B296=$D$5,$D$4,""))
A298: =IF(B297<$D$5,DATE(YEAR(A297),MONTH(A297)+1,DAY(A297)),IF(B297=$D$5,"Tổng","")) | B298: =IF(B297<$D$5,B297+1,"") | C298: =IF(B298<>"",A298-A297,"") | D298: =IF($B297<$D$5,$D$4/$D$5,IF($B297=$D$5,$D$4,""))
A299: =IF(B298<$D$5,DATE(YEAR(A298),MONTH(A298)+1,DAY(A298)),IF(B298=$D$5,"Tổng","")) | B299: =IF(B298<$D$5,B298+1,"") | C299: =IF(B299<>"",A299-A298,"") | D299: =IF($B298<$D$5,$D$4/$D$5,IF($B298=$D$5,$D$4,""))
A300: =IF(B299<$D$5,DATE(YEAR(A299),MONTH(A299)+1,DAY(A299)),IF(B299=$D$5,"Tổng","")) | B300: =IF(B299<$D$5,B299+1,"") | C300: =IF(B300<>"",A300-A299,"") | D300: =IF($B299<$D$5,$D$4/$D$5,IF($B299=$D$5,$D$4,""))

Sheet Price Quote
E1: =NOW() -> 45958.743 | F1: Khung thuế HCM | G1: =P10 -> 0 | H1: CHI PHÍ ĐĂNG KÝ | J1: GỐC | K1: KHÔNG XE | L1: CP ỨNG | M1: LƯU Ý THUẾ
D2: Discount gift code: | E2: =RAND()*99999999 -> 37516085 | F2: Lệch | G2: =D14-G1 -> 0 | H2: TP.HCM | I2: 4000000 | J2: 2400000 | K2: Không xe | L2: 1500000
G3: ss | H3: Tây Ninh | I3: 5000000 | J3: 3500000 | K3: Xe | L3: 1500000
A4: Estimation of Car License Fee (Grand new car) | G4: ss | H4: Bình Dương | I4: 4000000 | J4: 2800000 | K4: Không xe | L4: 1000000
F5: =P7 -> 299000000 | H5: Đồng Nai | I5: 4000000 | J5: 2800000 | K5: Không xe | L5: 1500000 | P5: 0
A6: - The quotation is valid for 48 hours from the issuance time. - The estimated costs will be refunded if there is a surplus after the invoice is generated. - Gift vouchers and promotions are subject to availability at the time of vehicle pickup. - The validity period of gift vouchers is 48 hours from the activation time. - Note: Bank payment is estimated based on the current highest interest rate. Customers who are eligible for better loan rates will have better options. | F6: VIP | H6: Vũng Tàu | I6: 5500000 | J6: 3500000 | K6: 6000000 | L6: 1500000
A7: To: | B7: =F6 -> VIP | F7: Dòng xe | G7: VF.3 | H7: Long An | I7: 5000000 | J7: 3500000 | K7: 6000000 | L7: 1500000 | M7: Đăng Ký Xe Định Quán + 1tr5 | N7: 3000000 | P7: =VLOOKUP(G8,Data!B2:C29,2,0) -> 299000000
A8: Car Model : | B8: =G8 -> Vinfast VF3 | F8: Loại xe : | G8: Vinfast VF3 | H8: Ninh Thuận | I8: 7300000 | J8: 5500000 | K8: Xe | N8: 3500000 | P8: =VLOOKUP(G8,Data!F2:G29,2,0) -> 0
A9: Price : | D9: =P7 -> 299000000 | E9: VND | F9: Trả trước : | G9: 0.2 | H9: Bình Thuận | I9: 6200000 | J9: 4500000 | K9: 7000000 | N9: 4000000 | O9: 531000 | P9: =VLOOKUP(G8,Data!N2:O29,2,0) -> 299000000 | Q9: =VLOOKUP(G8,Data!AM2:AN29,2,0) -> 287040000
A10: Discount : | D10: =G19 -> 11960000 | E10: VND | F10: Tổng tiền đưa trước | G10: =D31 -> 86714440 | H10: Bình Phước | I10: 6500000 | J10: 4500000 | K10: 6000000 | L10: 3300000 | N10: 5000000 | O10: 847000 | P10: =VLOOKUP(G8,Data!AE2:AF29,2,0) -> 0
A11: Last Price : | D11: =D9-D10 -> 287040000 | E11: VND | F11: Gia đình : | G11: 531000 | H11: Phan Thiết | I11: 6000000 | J11: 4500000 | N11: 6000000 | O11: 944000 | P11: =P7-P9 -> 0 | Q11: =P7-Q9 -> 11960000
F12: Kinh doanh : | G12: 847000 | H12: Phan Rang | I12: 6500000 | O12: 1205000 | P12: =VLOOKUP(G8,Data!AP2:AQ29,2,0) -> Miễn phí sạc 02 năm tại VGreen
A13: STT | B13: Estimation of Car License Fee | D13: AMOUNT | E13: DISCOUNT | F13: Kinh doanh Taxi : | G13: 1429000 | H13: Nha Trang | I13: 9000000 | J13: 7000000 | K13: Xe | L13: 5000000 | O13: 1429000 | P13: =VLOOKUP(G8,Data!AR2:AS29,2,0) -> Miễn phí bãi đổ xe và ưu tiên hệ sinh thái VINGROUP
A14: 1 | B14: Registration duty (10% of price) | D14: =P8-E14 -> 0 | F14: Gia đình7C: | G14: 943000 | H14: Bình Định | I14: 9500000 | J14: 8000000 | K14: 10000000 | L14: 7500000 | N14: 10000000 | O14: 3240000 | P14: =VLOOKUP(G8,Data!AT2:AU29,2,0) -> 0
A15: 2 | B15: Registration fee (number car) | D15: 20000000 | F15: Kinh Doanh 7C : | G15: 1205000 | H15: Phú Yên | I15: 9200000 | J15: 8000000 | K15: 10000000 | L15: 7000000 | N15: 15000000 | P15: =VLOOKUP(G8,Data!AV2:AW29,2,0) -> 0
A16: 3 | B16: Car certification fee | D16: 45000 | F16: Thuế HN tăng thêm : | G16: =O55-D14 -> 35880000 | H16: Đắk Lắk | I16: 8000000 | J16: 6000000 | L16: 5000000 | N16: 20000000 | P16: =VLOOKUP(G8,Data!AX2:AY29,2,0) -> 0 | Q16: =VLOOKUP(G8,Data!AX2:AY29,2,0) -> 0
A17: 4 | B17: Compulsory assurance 1 year | D17: 2160000 | F17: =IF($P18="*","Tự bù Camera", "Công ty Tặng Camera") -> Công ty Tặng Camera | H17: Đắk Nông | I17: 8000000 | J17: 6500000 | L17: 5000000 | N17: 25000000 | O17: 20000000 | P17: =VLOOKUP(G8,Data!#REF!,2,0) -> #REF!
A18: 5 | B18: Car assurance - optinal 1 year (not contraisn) | D18: 944000 | F18: Giá gốc : | G18: =P7 -> 299000000 | H18: Gia Lai | I18: 8300000 | J18: 5500000 | K18: Không xe | L18: 5000000 | N18: 30000000 | O18: 1000000 | P18: =VLOOKUP(G8,Data!AZ2:BA29,2,0) -> 0
A19: 6 | B19: Fee to protect street in VN 1 year | C19: 0.011 | D19: =D11*C19 -> 3157440 | F19: Giảm giá : | G19: =IF(G20>G21,G20,G21) -> 11960000 | H19: Kom Tum | I19: 9500000 | J19: 9000000 | K19: Xe | L19: 5000000 | N19: 35000000 | O19: 500000
A20: 7 | B20: Car license number service (in HCMC) | D20: 3000000 | F20: Chương Trình 2022 : | G20: =P11 -> 0 | H20: Đà Lạt | I20: 8300000 | J20: 5000000 | L20: 5000000 | N20: 40000000 | O20: 200000 | P20: Trắng | Q20: - 5L Nguyên liệu
A21: 8 | B21: Car decoration package | D21: =G22 -> 0 | F21: Chương Trình 2023 : | G21: =Q11 -> 11960000 | N21: 45000000 | Q21: - Bộ lên kiếng tự động
A22: Total registration fee | D22: =SUM(D14:D21) -> 29306440 | F22: Gói Trang Trí | H22: Đà Nẵng | I22: 10000000 | J22: 9000000 | K22: Không xe | L22: 5000000 | N22: 50000000 | O22: 0 | P22: Bạc | Q22: - Dán phim cách nhiệt Bh 10 Năm
A23: CASH | H23: Huế | I23: 10000000 | K23: Không xe | L23: 5000000 | N23: 60000000 | O23: 0.01 | P23: Đỏ | Q23: - Lót sàn cách âm , chống cháy
B24: Base Price : | D24: =D11 -> 287040000 | H24: Thanh Hóa | I24: 11000000 | J24: 10000000 | K24: Không xe | L24: 5000000 | O24: 0.011 | P24: Đen | Q24: - Lót sàn 5D
B25: Estimation of Car License Fee : | D25: =D22 -> 29306440 | H25: Nghệ An | I25: 11000000 | J25: 9000000 | K25: Không xe | L25: 5000000 | O25: 0.012 | P25: Vàng cát | Q25: - Camera hành trình
B26: Completed : | D26: =D24+D25 -> 316346440 | E26: VND | H26: Tiền Giang | I26: 5000000 | J26: 3500000 | K26: 6000000 | L26: 5000000 | O26: 0.013 | P26: Vàng be | Q26: - Thẻ nhớ hành trình
A27: INSTALLMENT | H27: Bến Tre | I27: 6000000 | J27: 4000000 | K27: Xe | L27: 5000000 | O27: 0.014 | P27: Xanh | Q27: - Tẩu sạc USB
B28: Banking Loan : | C28: =100%-C29 -> 0.8 | D28: =C28*D11-E28 -> 229632000 | F28: Ngân hàng cho vay : | G28: 600000000 | H28: Trà Vinh | I28: 6200000 | J28: 4500000 | K28: 7000000 | L28: 5000000 | O28: 0.015 | P28: Cam | Q28: - Phủ gầm
B29: Deposit | C29: =G9 -> 0.2 | D29: =F5-D28+G19-D10-G19 -> 57408000 | E29: (1) | F29: Chênh lệch | G29: =D28-G28 -> -370368000 | H29: An Giang | I29: 6200000 | J29: 5000000 | K29: 7000000 | L29: 6000000 | O29: 0.016 | P29: Xanh chuối | Q29: - Phủ Ceramic
B30: Estimation of Car License Fee : | D30: =D22 -> 29306440 | E30: (2) | H30: Kiên Giang | I30: 6200000 | J30: 5500000 | K30: 7000000 | L30: 5000000 | O30: 0.017 | Q30: - Viền che mưa
B31: Total (1) + (2) : | D31: =(D11-F5)+D30+D29-G19+D10+G19 -> 86714440 | E31: VND | F31: Tips : Xác định nhu cầu khách hàng | H31: Hậu Giang | I31: 6200000 | J31: 5300000 | K31: 7000000 | L31: 5000000 | O31: 0.018 | Q31: - Bệ bước chân cao cấp
F32: 1. Anh/ chị có dự định nhận xe trong tháng không hay mình tham khảo trước để em tư vấn anh/ chị luôn ạ ! | H32: Cần Thơ | I32: 6200000 | J32: 4500000 | K32: 7000000 | L32: 5000000 | O32: 0.019 | Q32: - Hộp đen kinh doanh
A33: Free gift accessory | B33: - Car cover, floor mat, leather-wrapped steering wheel, fire extinguisher, specialized towel | C33: INSTALLMENT | E33: Amount per month | H33: Đồng Tháp | I33: 6000000 | J33: 4500000 | K33: 8000000 | L33: 1500000 | O33: 0.02 | Q33: - Gói bảo hành nâng cấp 05 năm
C34: - Installment payment for 03 years | E34: =BG03Y!F11 -> 25675199 | F34: 2. Dạ vậy để tiện cho anh trải nghiệm thực tế trước khi quyết định em đem xe cho Anh/ chị lái thử để cảm nhận luôn nha ! | H34: Vĩnh Long | I34: 6200000 | J34: 4000000 | K34: 7000000 | L34: 5000000 | O34: 0.023 | Q34: - Thảm taplo
B35: - The 10% discount code for genuine accessories | C35: - Installment payment for 04 years | E35: =BG04Y!F11 -> 20387449 | H35: Bạc Liêu | I35: 6200000 | J35: 5500000 | K35: 7000000 | L35: 5000000 | O35: 0.025
C36: - Installment payment for 05 years | E36: =BG05Y!F11 -> 17214799 | H36: Sóc Trăng | I36: 6200000 | J36: 5300000 | K36: 7000000 | L36: 5000000 | O36: 0.028
B37: - 5L of raw materials | C37: - Installment payment for 06 years | E37: =BG06Y!F11 -> 15099699 | F37: 3. Trong tuần này Anh/chị có rãnh không ạ, sắp xếp ghé qua Showroom em, sẵn tiện xem xe và em tư vấn kỹ hơn về xe và ngân hàng luôn | H37: Cà Mau | I37: 6200000 | J37: 5500000 | K37: 7000000 | L37: 5000000 | O37: 0.03
B38: =P12 -> Miễn phí sạc 02 năm tại VGreen | C38: - Installment payment for 07 years | E38: =BG07Y!F11 -> 13588913 | H38: Lâm Đồng | I38: 7000000 | J38: 5000000 | L38: 5000000
B39: =P13 -> Miễn phí bãi đổ xe và ưu tiên hệ sinh thái VINGROUP | C39: - Installment payment for 08 years | E39: =BG08Y!F11 -> 12455824 | H39: Hà Tĩnh | I39: 10000000 | K39: Không xe | L39: 6500000
B40: =P14 -> 0 | C40: The estimated monthly amount above is tentative, the actual monthly payment will decrease according to the outstanding balance (less in the following months than in the previous ones) | F40: Tin nhắn nhanh | H40: Hà Nội | I40: 12000000 | J40: 10000000 | K40: Không xe | L40: 5000000
B41: =P15 -> 0 | F41: Dạ mình đã chọn được phiên bản nào chưa ạ, nếu chưa để e tư vấn cho mình thêm để dễ so sánh các bản | H41: Bắc Giang | I41: 19000000 | J41: 17000000 | L41: 6500000
B42: =P16 -> 0
C43: Early settlement for reference | F43: Dạ mình tham kháo giá và chương trình khuyến mãi để cân nhắc lấy xe đúng không ạ
C44: First Year : 4% Third year : 2% Fifth year : Free Second year : 3% Fourth year 4 : 1%
F45: Mình tham khảo lấy xe lăn bánh biển số về đâu ạ, để e tính cho mình bảng giá chi tiết tham khảo cho dễ | H45: Nam Định | I45: 11000000 | J45: 9000000 | K45: Không xe | L45: 8000000
B46: Payment method for cash purchase | D46: Bank loan payment method | H46: Quảng Bình | I46: 11000000 | J46: 9000000 | K46: Không xe | L46: 5000000
F47: Mình dự định mua tiền may luôn hay là chọn hình thức trả góp ạ, bên e có hỗ trợ trả góp tối đa lên tới 85% luôn ạ | H47: Quãng Ngải | I47: 13000000 | J47: 11000000 | K47: Không xe | L47: 5000000 | O47: 1560000 | P47: 10 Ngày
H48: Quảng Nam | I48: 11000000 | J48: 9000000 | K48: Không xe | L48: 5000000 | O48: 2160000 | P48: 10-15 Ngày
F49: Trả góp thì bên e hiện có 2 hình thức : - Ngân hàng nước ngoài : + Ưu điểm : Lãi tốt và Chăm sóc khách hàng tốt, dịch vụ hậu mãi tốt + Nhược điểm : Hồ sơ khó duyệt, phải chứng minh được thu nhập và giấy tờ đầy đủ - Ngân hàng trong nước : + Ưu điểm : Hồ sơ vay dễ và nhanh + Nhược điểm : Lãi cao hơn ngân hàng nước ngoài và các chính sach hậu mãi sẽ không bằng ngân hàng nước ngoài | H49: Hòa Bình | I49: 11000000 | J49: 9000000 | K49: Không xe | L49: 6500000 | O49: 3389000 | P49: 15-25 Ngày
H50: Hà Nam | I50: 11000000 | J50: 9000000 | K50: Không xe | L50: 6500000 | P50: 20-30 Ngày
H51: Bắc Ninh | I51: 11000000 | J51: 9000000 | K51: Không xe | L51: 6500000 | P51: 30 - 45 Ngày
H52: Cao Bằng | I52: 11000000 | J52: 9000000 | K52: Không xe | L52: 6500000 | P52: 45 - 60 Ngày
H53: Hải Phòng | I53: 16300000 | J53: 14700000 | K53: Không xe | L53: 6500000 | P53: 60 - 75 Ngày
H54: Ninh Bình | I54: 11200000 | J54: 9700000 | K54: Không xe | L54: 6500000 | P54: 75 - 90 Ngày
H55: Thái Bình | I55: 17300000 | J55: 15700000 | K55: Không xe | L55: 12000000 | O55: =D9*12% -> 35880000
H56: Sơn La | I56: 10300000 | J56: 8700000 | K56: Không xe | L56: 6500000
F57: Mình có dự định lấy xe trong tháng luôn chưa ạ hay dự định quá tháng mới lấy xe ạ
N70: 23

Sheet CSG
A1: CHÍNH SÁCH GIÁ MỚI NHẤT | Z1: 2025 | AB1: 2024
A2: STT | B2: MODEL | C2: GIÁ NIÊM YẾT | D2: 2025 | K2: 2024 | R2: QUÀ TẶNG | X2: VINFAST
D3: GIẢM GIÁ | E3: LƯƠNG | F3: VINCLUB | G3: THƯỞNG | H3: BIÊN NHÀ MÁY | I3: CHÍNH SÁCH C | J3: THU CŨ ĐỔI MỚI | K3: GIẢM GIÁ | L3: LƯƠNG | M3: VINCLUB | N3: CHÍNH SÁCH A | O3: CHÍNH SÁCH B | P3: CHÍNH SÁCH C | Q3: THU CŨ ĐỔI MỚI
A4: MINIO
A5: 1 | B5: Minio Green | C5: 269000000 | D5: =C5*4% -> 10760000 | E5: 3000000 | F5: 2500000 | H5: 6000000 | R5: Miễn phí sạc 02 năm tại VGreen | S5: Miễn phí bãi đổ xe và ưu tiên hệ sinh thái VINGROUP | X5: =C5-D5 -> 258240000 | Z5: =C5-D5 -> 258240000 | AB5: =C5-K5 -> 269000000
A6: VF.3 | Z6: =C6-K6 -> 0 | AB6: =C6-Q6 -> 0
A7: 1 | B7: Vinfast VF3 | C7: 299000000 | D7: =C7*4% -> 11960000 | E7: 6000000 | F7: 6000000 | G7: 4000000 | H7: 6000000 | J7: 5000000 | R7: Miễn phí sạc 02 năm tại VGreen | S7: Miễn phí bãi đổ xe và ưu tiên hệ sinh thái VINGROUP | X7: =C7-D7 -> 287040000 | Z7: =C7-D7 -> 287040000 | AB7: =C7-K7 -> 299000000
A8: 2 | B8: Vinfast VF3 (NC) | C8: 307000000 | D8: =C8*4% -> 12280000 | E8: 6000000 | F8: 6000000 | G8: 4000000 | H8: 6000000 | J8: 5000000 | R8: Miễn phí sạc 02 năm tại VGreen | S8: Miễn phí bãi đổ xe và ưu tiên hệ sinh thái VINGROUP | X8: =C8-D8 -> 294720000 | Z8: =C8-D8 -> 294720000 | AB8: =C8-K8 -> 307000000
A9: HERIO | Z9: =C9-K9 -> 0 | AB9: =C9-Q9 -> 0
A10: 1 | B10: Herio Green | C10: 499000000 | D10: =C10*4% -> 19960000 | E10: 10000000 | F10: 5000000 | G10: 2000000 | H10: 10000000 | J10: 9500000 | R10: Miễn phí sạc 02 năm tại VGreen | S10: Miễn phí bãi đổ xe và ưu tiên hệ sinh thái VINGROUP | X10: =C10-D10 -> 479040000 | Z10: =C10-D10 -> 479040000 | AB10: =C10-K10 -> 499000000
A11: VF.5 | Z11: =C11-K11 -> 0 | AB11: =C11-Q11 -> 0
A12: 1 | B12: Vinfast VF5 Plus | C12: 529000000 | D12: =C12*4% -> 21160000 | E12: 11000000 | F12: 10000000 | G12: 5000000 | H12: 10000000 | J12: 10000000 | R12: Miễn phí sạc 02 năm tại VGreen | S12: Miễn phí bãi đổ xe và ưu tiên hệ sinh thái VINGROUP | X12: =C12-D12 -> 507840000 | Z12: =C12-D12 -> 507840000 | AB12: =C12-K12 -> 529000000
A13: 2 | B13: Vinfast VF5 Plus (NC) | C13: 537000000 | D13: =C13*4% -> 21480000 | E13: 11000000 | F13: 10000000 | G13: 5000000 | H13: 10000000 | J13: 10000000 | R13: Miễn phí sạc 02 năm tại VGreen | S13: Miễn phí bãi đổ xe và ưu tiên hệ sinh thái VINGROUP | X13: =C13-D13 -> 515520000 | Z13: =C13-D13 -> 515520000 | AB13: =C13-K13 -> 537000000
A14: NERIO | Z14: =C14-K14 -> 0 | AB14: =C14-Q14 -> 0
A15: 1 | B15: Nerio Green | C15: 668000000 | D15: =C15*4% -> 26720000 | E15: 13000000 | F15: 6500000 | J15: 9500000 | R15: Miễn phí sạc 02 năm tại VGreen | S15: Miễn phí bãi đổ xe và ưu tiên hệ sinh thái VINGROUP | X15: =C15-D15 -> 641280000 | Z15: =C15-D15 -> 641280000 | AB15: =C15-K15 -> 668000000
A16: VF.6 | Z16: =C16-K16 -> 0 | AB16: =C16-Q16 -> 0
A17: 1 | B17: Vinfast VF6 Eco | C17: 689000000 | D17: =C17*4% -> 27560000 | E17: 18000000 | F17: 15000000 | G17: 3000000 | H17: 12000000 | J17: 15000000 | R17: Miễn phí sạc 02 năm tại VGreen | S17: Miễn phí bãi đổ xe và ưu tiên hệ sinh thái VINGROUP | X17: =C17-D17 -> 661440000 | Z17: =C17-D17 -> 661440000 | AB17: =C17-K17 -> 689000000
A18: 2 | B18: Vinfast VF6 Eco (NC) | C18: 694000000 | D18: =C18*4% -> 27760000 | E18: 18000000 | F18: 15000000 | G18: 3000000 | H18: 12000000 | J18: 15000000 | R18: Miễn phí sạc 02 năm tại VGreen | S18: Miễn phí bãi đổ xe và ưu tiên hệ sinh thái VINGROUP | X18: =C18-D18 -> 666240000 | Z18: =C18-D18 -> 666240000 | AB18: =C18-K18 -> 694000000
A19: 3 | B19: Vinfast VF6 Plus | C19: 749000000 | D19: =C19*4% -> 29960000 | E19: 18000000 | F19: 15000000 | G19: 3000000 | H19: 12000000 | J19: 15000000 | R19: Miễn phí sạc 02 năm tại VGreen | S19: Miễn phí bãi đổ xe và ưu tiên hệ sinh thái VINGROUP | X19: =C19-D19 -> 719040000 | Z19: =C19-D19 -> 719040000 | AB19: =C19-K19 -> 749000000
A20: 4 | B20: Vinfast VF6 Plus (NC) | C20: 759000000 | D20: =C20*4% -> 30360000 | E20: 18000000 | F20: 15000000 | G20: 3000000 | H20: 12000000 | J20: 15000000 | R20: Miễn phí sạc 02 năm tại VGreen | S20: Miễn phí bãi đổ xe và ưu tiên hệ sinh thái VINGROUP | X20: =C20-D20 -> 728640000 | Z20: =C20-D20 -> 728640000 | AB20: =C20-K20 -> 759000000
A21: LIMO | Z21: =C21-D21 -> 0 | AB21: =C21-K21 -> 0
A22: 1 | B22: Limo Green | C22: 749000000 | D22: =C22*4% -> 29960000 | E22: 16000000 | F22: 7500000 | H22: 12000000 | J22: 15000000 | R22: Miễn phí sạc 02 năm tại VGreen | S22: Miễn phí bãi đổ xe và ưu tiên hệ sinh thái VINGROUP | X22: =C22-D22 -> 719040000 | Z22: =C22-D22 -> 719040000 | AB22: =C22-K22 -> 749000000
A23: VF.7 | Z23: =C23-K23 -> 0 | AB23: =C23-Q23 -> 0
A24: 1 | B24: Vinfast VF7 Eco | C24: 799000000 | D24: =C24*4% -> 31960000 | E24: 18000000 | F24: 35000000 | G24: 10000000 | H24: 15000000 | J24: 50000000 | R24: Miễn phí sạc 02 năm tại VGreen | S24: Miễn phí bãi đổ xe và ưu tiên hệ sinh thái VINGROUP | X24: =C24-D24 -> 767040000 | Z24: =C24-D24 -> 767040000 | AB24: =C24-K24 -> 799000000
A25: 2 | B25: Vinfast VF7 Plus (TC) - Thép | C25: 949000000 | D25: =C25*4% -> 37960000 | E25: 20000000 | F25: 35000000 | G25: 10000000 | H25: 15000000 | J25: 50000000 | R25: Miễn phí sạc 02 năm tại VGreen | S25: Miễn phí bãi đổ xe và ưu tiên hệ sinh thái VINGROUP | X25: =C25-D25 -> 911040000 | Z25: =C25-D25 -> 911040000 | AB25: =C25-K25 -> 949000000
A26: 3 | B26: Vinfast VF7 Plus (NC) - Thép | C26: 999000000 | D26: =C26*4% -> 39960000 | E26: 20000000 | F26: 35000000 | G26: 10000000 | H26: 15000000 | J26: 50000000 | R26: Miễn phí sạc 02 năm tại VGreen | S26: Miễn phí bãi đổ xe và ưu tiên hệ sinh thái VINGROUP | X26: =C26-D26 -> 959040000 | Z26: =C26-D26 -> 959040000 | AB26: =C26-K26 -> 999000000
A27: 4 | B27: Vinfast VF7 Plus (TC) - Kính | C27: 969000000 | D27: =C27*4% -> 38760000 | E27: 20000000 | F27: 35000000 | G27: 10000000 | H27: 15000000 | J27: 50000000 | R27: Miễn phí sạc 02 năm tại VGreen | S27: Miễn phí bãi đổ xe và ưu tiên hệ sinh thái VINGROUP | X27: =C27-D27 -> 930240000 | Z27: =C27-D27 -> 930240000 | AB27: =C27-K27 -> 969000000
A28: 5 | B28: Vinfast VF7 Plus (NC) - Kính | C28: 1019000000 | D28: =C28*4% -> 40760000 | E28: 20000000 | F28: 35000000 | G28: 10000000 | H28: 15000000 | J28: 50000000 | R28: Miễn phí sạc 02 năm tại VGreen | S28: Miễn phí bãi đổ xe và ưu tiên hệ sinh thái VINGROUP | X28: =C28-D28 -> 978240000 | Z28: =C28-D28 -> 978240000 | AB28: =C28-K28 -> 1019000000
A29: VF.8 | Z29: =C29-K29 -> 0 | AB29: =C29-Q29 -> 0
A30: 1 | B30: Vinfast VF8 Eco (TC) | C30: 1019000000 | D30: =C30*4% -> 40760000 | E30: 30000000 | F30: 50000000 | G30: 15000000 | H30: 20000000 | J30: 70000000 | R30: Miễn phí sạc 02 năm tại VGreen | S30: Miễn phí bãi đổ xe và ưu tiên hệ sinh thái VINGROUP | X30: =C30-D30 -> 978240000 | Z30: =C30-D30 -> 978240000 | AB30: =C30-K30 -> 1019000000
A31: 2 | B31: Vinfast VF8 Eco (NC) | C31: 1069000000 | D31: =C31*4% -> 42760000 | E31: 30000000 | F31: 50000000 | G31: 15000000 | H31: 20000000 | J31: 70000000 | R31: Miễn phí sạc 02 năm tại VGreen | S31: Miễn phí bãi đổ xe và ưu tiên hệ sinh thái VINGROUP | X31: =C31-D31 -> 1026240000 | Z31: =C31-D31 -> 1026240000 | AB31: =C31-K31 -> 1069000000
A32: 3 | B32: Vinfast VF8 Plus | C32: 1199000000 | D32: =C32*4% -> 47960000 | E32: 35000000 | F32: 50000000 | G32: 15000000 | H32: 20000000 | J32: 70000000 | R32: Miễn phí sạc 02 năm tại VGreen | S32: Miễn phí bãi đổ xe và ưu tiên hệ sinh thái VINGROUP | X32: =C32-D32 -> 1151040000 | Z32: =C32-D32 -> 1151040000 | AB32: =C32-K32 -> 1199000000
A33: VF.9
A34: 1 | B34: Vinfast VF9 Eco - 7 Chỗ | C34: 1499000000 | D34: =C34*4% -> 59960000 | E34: 40000000 | F34: 70000000 | G34: 30000000 | H34: 25000000 | J34: 100000000 | R34: Miễn phí sạc 02 năm tại VGreen | S34: Miễn phí bãi đổ xe và ưu tiên hệ sinh thái VINGROUP | X34: =C34-D34 -> 1439040000 | Z34: =C34-D34 -> 1439040000 | AB34: =C34-K34 -> 1499000000
A35: 2 | B35: Vinfast VF9 Plus - Trần Thép (7C) | C35: 1699000000 | D35: =C35*4% -> 67960000 | E35: 45000000 | F35: 70000000 | G35: 30000000 | H35: 25000000 | J35: 100000000 | R35: Miễn phí sạc 02 năm tại VGreen | S35: Miễn phí bãi đổ xe và ưu tiên hệ sinh thái VINGROUP | X35: =C35-D35 -> 1631040000 | Z35: =C35-D35 -> 1631040000 | AB35: =C35-K35 -> 1699000000
A36: 3 | B36: Vinfast VF9 Plus - Trần Kính (7C) | C36: =C35+29000000 -> 1728000000 | D36: =C36*4% -> 69120000 | E36: 45000000 | F36: 70000000 | G36: 30000000 | H36: 25000000 | J36: 100000000 | R36: Miễn phí sạc 02 năm tại VGreen | S36: Miễn phí bãi đổ xe và ưu tiên hệ sinh thái VINGROUP | X36: =C36-D36 -> 1658880000 | Z36: =C36-D36 -> 1658880000 | AB36: =C36-K36 -> 1728000000
A37: 4 | B37: Vinfast VF9 Plus - Trần Kính (6C) | C37: =C38+29000000 -> 1760000000 | D37: =C37*4% -> 70400000 | E37: 45000000 | F37: 70000000 | G37: 30000000 | H37: 25000000 | J37: 100000000 | R37: Miễn phí sạc 02 năm tại VGreen | S37: Miễn phí bãi đổ xe và ưu tiên hệ sinh thái VINGROUP | X37: =C37-D37 -> 1689600000 | Z37: =C37-D37 -> 1689600000 | AB37: =C37-K37 -> 1760000000
A38: 5 | B38: Vinfast VF9 Plus - Trần Thép (6C) | C38: 1731000000 | D38: =C38*4% -> 69240000 | E38: 45000000 | F38: 70000000 | G38: 30000000 | H38: 25000000 | J38: 100000000 | R38: Miễn phí sạc 02 năm tại VGreen | S38: Miễn phí bãi đổ xe và ưu tiên hệ sinh thái VINGROUP | X38: =C38-D38 -> 1661760000 | Z38: =C38-D38 -> 1661760000 | AB38: =C38-K38 -> 1731000000
A39: LAC.HONG
A40: 1 | B40: Vinfast Lạc Hồng | C40: 5000000000 | D40: =C40*4% -> 200000000 | E40: 200000000 | F40: 200000000 | R40: Miễn phí sạc 02 năm tại VGreen | S40: Miễn phí bãi đổ xe và ưu tiên hệ sinh thái VINGROUP | X40: =C40-D40 -> 4800000000 | Z40: =C40-D40 -> 4800000000 | AB40: =C40-K40 -> 5000000000
A41: 2 | B41: Vinfast Lạc Hồng (Chống Đạn) | C41: 34000000000 | D41: =C41*4% -> 1360000000 | E41: 500000000 | F41: 200000000 | R41: Miễn phí sạc 02 năm tại VGreen | S41: Miễn phí bãi đổ xe và ưu tiên hệ sinh thái VINGROUP | X41: =C41-D41 -> 32640000000 | Z41: =C41-D41 -> 32640000000 | AB41: =C41-K41 -> 34000000000
A42: ECVAN
A43: 1 | B43: EC Van TC | C43: 285000000 | D43: =C43*4% -> 11400000 | E43: 5000000 | R43: Miễn phí sạc 02 năm tại VGreen | S43: Miễn phí bãi đổ xe và ưu tiên hệ sinh thái VINGROUP | X43: =C43-D43 -> 273600000 | Z43: =C43-D43 -> 273600000 | AB43: =C43-K43 -> 285000000
A44: 2 | B44: EC Van NC | C44: 305000000 | D44: =C44*4% -> 12200000 | E44: 5000000 | R44: Miễn phí sạc 02 năm tại VGreen | S44: Miễn phí bãi đổ xe và ưu tiên hệ sinh thái VINGROUP | X44: =C44-D44 -> 292800000 | Z44: =C44-D44 -> 292800000 | AB44: =C44-K44 -> 305000000

Sheet Data
A1: TÊN XE | C1: GIÁ XE | E1: Tên Xe | G1: THUẾ BẠ HIỂN THỊ | H1: THUẾ BẠ | I1: ĐIỀU CHỈNH | M1: Tên Xe | O1: Giá xe | P1: Giảm | Q1: CSA | R1: CSB | S1: CSC | T1: Lương | V1: Thưởng | X1: Biên Nhà Máy | Z1: Vinclub | AB1: Thu cũ đổi mới | AD1: Tên Xe | AF1: Thuế bạ HCM | AH1: Mã Nhóm 1 | AI1: Tên Nhóm 1 | AM1: XE TP>HCM | AN1: Giảm | AP1: Dòng xe | AQ1: Phụ kiện | BC1: THÔNG SỐ
A2: =J2 -> MINIO | B2: =CSG!B5 -> Minio Green | C2: =CSG!C5 -> 269000000 | E2: =A2 -> MINIO | F2: =B2 -> Minio Green | H2: =G2-I2 -> 0 | J2: =CSG!A4 -> MINIO | K2: Minio Green | M2: =E2 -> MINIO | N2: =B2 -> Minio Green | O2: =C2 -> 269000000 | P2: =CSG!D5 -> 10760000 | Q2: =CSG!G5 -> 0 | R2: =CSG!H5 -> 6000000 | S2: =CSG!I5 -> 0 | T2: =N2 -> Minio Green | U2: =CSG!E5 -> 3000000 | V2: =T2 -> Minio Green | W2: =CSG!G5 -> 0 | X2: =V2 -> Minio Green | Y2: =CSG!H5 -> 6000000 | Z2: =N2 -> Minio Green | AA2: =CSG!F5 -> 2500000 | AB2: =N2 -> Minio Green | AC2: =CSG!J5 -> 0 | AD2: Grand I10 | AE2: =N2 -> Minio Green | AF2: =H2 -> 0 | AH2: NAM | AI2: Miền Nam | AM2: =AE2 -> Minio Green | AN2: =CSG!Z5 -> 258240000 | AP2: =AM2 -> Minio Green | AQ2: =CSG!R5 -> Miễn phí sạc 02 năm tại VGreen | AR2: =AP2 -> Minio Green | AS2: =CSG!S5 -> Miễn phí bãi đổ xe và ưu tiên hệ sinh thái VINGROUP | AT2: =AR2 -> Minio Green | AU2: =CSG!T5 -> 0 | AV2: =AR2 -> Minio Green | AW2: =CSG!U5 -> 0 | AX2: =AP2 -> Minio Green | AY2: =CSG!V5 -> 0 | AZ2: =AP2 -> Minio Green | BA2: =CSG!W5 -> 0 | BC2: =AZ2 -> Minio Green | BD2: Thời gian nạp pin (10 - 70% trong 36 phút | BE2: =BC2 -> Minio Green | BF2: Công suất tối đa 30 kW/43 hp | BG2: =BE2 -> Minio Green | BH2: Lazang 13 Inch | BI2: =BG2 -> Minio Green | BJ2: Không trang bị | BK2: =BI2 -> Minio Green | BL2: Quãng đường di chuyển dự kiến 210Km
A3: =J3 -> VF.3 | B3: =CSG!B7 -> Vinfast VF3 | C3: =CSG!C7 -> 299000000 | E3: =A3 -> VF.3 | F3: =B3 -> Vinfast VF3 | H3: =G3-I3 -> 0 | J3: =CSG!A6 -> VF.3 | K3: Vinfast VF3 | M3: =E3 -> VF.3 | N3: =B3 -> Vinfast VF3 | O3: =C3 -> 299000000 | P3: =CSG!D7 -> 11960000 | Q3: =CSG!G7 -> 4000000 | R3: =CSG!H7 -> 6000000 | S3: =CSG!I7 -> 0 | T3: =N3 -> Vinfast VF3 | U3: =CSG!E7 -> 6000000 | V3: =T3 -> Vinfast VF3 | W3: =CSG!G7 -> 4000000 | X3: =V3 -> Vinfast VF3 | Y3: =CSG!H7 -> 6000000 | Z3: =N3 -> Vinfast VF3 | AA3: =CSG!F7 -> 6000000 | AB3: =N3 -> Vinfast VF3 | AC3: =CSG!J7 -> 5000000 | AD3: =M3 -> VF.3 | AE3: =N3 -> Vinfast VF3 | AF3: =H3 -> 0 | AH3: TAY | AI3: Miền Tây | AM3: =AE3 -> Vinfast VF3 | AN3: =CSG!Z7 -> 287040000 | AP3: =AM3 -> Vinfast VF3 | AQ3: =CSG!R7 -> Miễn phí sạc 02 năm tại VGreen | AR3: =AP3 -> Vinfast VF3 | AS3: =CSG!S7 -> Miễn phí bãi đổ xe và ưu tiên hệ sinh thái VINGROUP | AT3: =AR3 -> Vinfast VF3 | AU3: =CSG!T7 -> 0 | AV3: =AR3 -> Vinfast VF3 | AW3: =CSG!U7 -> 0 | AX3: =AP3 -> Vinfast VF3 | AY3: =CSG!V7 -> 0 | AZ3: =AP3 -> Vinfast VF3 | BA3: =CSG!W7 -> 0 | BC3: =AZ3 -> Vinfast VF3 | BD3: Thời gian nạp pin (10 - 70% trong 36 phút | BE3: =BC3 -> Vinfast VF3 | BF3: Công suất tối đa 30 kW/43 hp | BG3: =BE3 -> Vinfast VF3 | BH3: Lazang 16 Inch | BI3: =BG3 -> Vinfast VF3 | BJ3: Trang bị 01 túi khí | BK3: =BI3 -> Vinfast VF3 | BL3: Quãng đường di chuyển dự kiến 210Km
B4: =CSG!B8 -> Vinfast VF3 (NC) | C4: =CSG!C8 -> 307000000 | F4: =B4 -> Vinfast VF3 (NC) | J4: =CSG!A9 -> HERIO | K4: Herio Green | N4: =B4 -> Vinfast VF3 (NC) | O4: =C4 -> 307000000 | P4: =CSG!D8 -> 12280000 | Q4: =CSG!G8 -> 4000000 | R4: =CSG!H8 -> 6000000 | S4: =CSG!I8 -> 0 | T4: =N4 -> Vinfast VF3 (NC) | U4: =CSG!E8 -> 6000000 | V4: =T4 -> Vinfast VF3 (NC) | W4: =CSG!G8 -> 4000000 | X4: =V4 -> Vinfast VF3 (NC) | Y4: =CSG!H8 -> 6000000 | Z4: =N4 -> Vinfast VF3 (NC) | AA4: =CSG!F8 -> 6000000 | AB4: =N4 -> Vinfast VF3 (NC) | AC4: =CSG!J8 -> 5000000 | AE4: =N4 -> Vinfast VF3 (NC) | AM4: =AE4 -> Vinfast VF3 (NC) | AN4: =CSG!Z8 -> 294720000 | AP4: =AM4 -> Vinfast VF3 (NC) | AQ4: =CSG!R8 -> Miễn phí sạc 02 năm tại VGreen | AR4: =AP4 -> Vinfast VF3 (NC) | AS4: =CSG!S8 -> Miễn phí bãi đổ xe và ưu tiên hệ sinh thái VINGROUP | AT4: =AR4 -> Vinfast VF3 (NC) | AU4: =CSG!T8 -> 0 | AV4: =AR4 -> Vinfast VF3 (NC) | AW4: =CSG!U8 -> 0 | AX4: =AP4 -> Vinfast VF3 (NC) | AY4: =CSG!V8 -> 0 | AZ4: =AP4 -> Vinfast VF3 (NC) | BA4: =CSG!W8 -> 0 | BC4: =AZ4 -> Vinfast VF3 (NC) | BD4: Thời gian nạp pin (10 - 70% trong 36 phút | BE4: =BC4 -> Vinfast VF3 (NC) | BF4: Công suất tối đa 30 kW/43 hp | BG4: =BE4 -> Vinfast VF3 (NC) | BH4: Lazang 16 Inch | BI4: =BG4 -> Vinfast VF3 (NC) | BJ4: Trang bị 01 túi khí | BK4: =BI4 -> Vinfast VF3 (NC) | BL4: Quãng đường di chuyển dự kiến 210Km
A5: =J4 -> HERIO | B5: =CSG!B10 -> Herio Green | C5: =CSG!C10 -> 499000000 | E5: =A5 -> HERIO | F5: =B5 -> Herio Green | H5: =G5-I5 -> 0 | J5: =CSG!A11 -> VF.5 | K5: Vinfast VF5 | M5: =E5 -> HERIO | N5: =B5 -> Herio Green | O5: =C5 -> 499000000 | P5: =CSG!D10 -> 19960000 | Q5: =CSG!G10 -> 2000000 | R5: =CSG!H10 -> 10000000 | S5: =CSG!I10 -> 0 | T5: =N5 -> Herio Green | U5: =CSG!E10 -> 10000000 | V5: =T5 -> Herio Green | W5: =CSG!G10 -> 2000000 | X5: =V5 -> Herio Green | Y5: =CSG!H10 -> 10000000 | Z5: =N5 -> Herio Green | AA5: =CSG!F10 -> 5000000 | AB5: =N5 -> Herio Green | AC5: =CSG!J10 -> 9500000 | AD5: =M5 -> HERIO | AE5: =N5 -> Herio Green | AF5: =H5 -> 0 | AM5: =AE5 -> Herio Green | AN5: =CSG!Z10 -> 479040000 | AP5: =AM5 -> Herio Green | AQ5: =CSG!R10 -> Miễn phí sạc 02 năm tại VGreen | AR5: =AP5 -> Herio Green | AS5: =CSG!S10 -> Miễn phí bãi đổ xe và ưu tiên hệ sinh thái VINGROUP | AT5: =AR5 -> Herio Green | AU5: =CSG!T10 -> 0 | AV5: =AR5 -> Herio Green | AW5: =CSG!U10 -> 0 | AX5: =AP5 -> Herio Green | AY5: =CSG!V10 -> 0 | AZ5: =AP5 -> Herio Green | BA5: =CSG!W10 -> 0 | BC5: =AZ5 -> Herio Green | BD5: Thời gian nạp pin (10 - 70%) trong 33 phút | BE5: =BC5 -> Herio Green | BF5: Công suất tối đa 100 kW/134 hp | BG5: =BE5 -> Herio Green | BH5: Lazang 16 Inch | BI5: =BG5 -> Herio Green | BJ5: Trang bị 02 túi khí | BK5: =BI5 -> Herio Green | BL5: Quãng đường di chuyển dự kiến 326Km
A6: =J5 -> VF.5 | B6: =CSG!B12 -> Vinfast VF5 Plus | C6: =CSG!C12 -> 529000000 | E6: =A6 -> VF.5 | F6: =B6 -> Vinfast VF5 Plus | H6: =G6-I6 -> 0 | J6: =CSG!A14 -> NERIO | K6: Nerio Green | M6: =E6 -> VF.5 | N6: =B6 -> Vinfast VF5 Plus | O6: =C6 -> 529000000 | P6: =CSG!D12 -> 21160000 | Q6: =CSG!G12 -> 5000000 | R6: =CSG!H12 -> 10000000 | S6: =CSG!I12 -> 0 | T6: =N6 -> Vinfast VF5 Plus | U6: =CSG!E12 -> 11000000 | V6: =T6 -> Vinfast VF5 Plus | W6: =CSG!G12 -> 5000000 | X6: =V6 -> Vinfast VF5 Plus | Y6: =CSG!H12 -> 10000000 | Z6: =N6 -> Vinfast VF5 Plus | AA6: =CSG!F12 -> 10000000 | AB6: =N6 -> Vinfast VF5 Plus | AC6: =CSG!J12 -> 10000000 | AD6: =M6 -> VF.5 | AE6: =N6 -> Vinfast VF5 Plus | AF6: =H6 -> 0 | AH6: TRUNG | AI6: Miền Trung | AM6: =AE6 -> Vinfast VF5 Plus | AN6: =CSG!Z12 -> 507840000 | AP6: =AM6 -> Vinfast VF5 Plus | AQ6: =CSG!R12 -> Miễn phí sạc 02 năm tại VGreen | AR6: =AP6 -> Vinfast VF5 Plus | AS6: =CSG!S12 -> Miễn phí bãi đổ xe và ưu tiên hệ sinh thái VINGROUP | AT6: =AR6 -> Vinfast VF5 Plus | AU6: =CSG!T12 -> 0 | AV6: =AR6 -> Vinfast VF5 Plus | AW6: =CSG!U12 -> 0 | AX6: =AP6 -> Vinfast VF5 Plus | AY6: =CSG!V12 -> 0 | AZ6: =AP6 -> Vinfast VF5 Plus | BA6: =CSG!W12 -> 0 | BC6: =AZ6 -> Vinfast VF5 Plus | BD6: Thời gian nạp pin (10 - 70%) trong 33 phút | BE6: =BC6 -> Vinfast VF5 Plus | BF6: Công suất tối đa 100 kW/134 hp | BG6: =BE6 -> Vinfast VF5 Plus | BH6: Lazang 17 Inch | BI6: =BE6 -> Vinfast VF5 Plus | BJ6: Trang bị 06 túi khí | BK6: =BG6 -> Vinfast VF5 Plus | BL6: Quãng đường di chuyển dự kiến 326Km
B7: =CSG!B13 -> Vinfast VF5 Plus (NC) | C7: =CSG!C13 -> 537000000 | F7: =B7 -> Vinfast VF5 Plus (NC) | H7: =G7-I7 -> 0 | J7: =CSG!A16 -> VF.6 | K7: Vinfast VF6 | N7: =B7 -> Vinfast VF5 Plus (NC) | O7: =C7 -> 537000000 | P7: =CSG!D13 -> 21480000 | Q7: =CSG!G13 -> 5000000 | R7: =CSG!H13 -> 10000000 | S7: =CSG!I13 -> 0 | T7: =N7 -> Vinfast VF5 Plus (NC) | U7: =CSG!E13 -> 11000000 | V7: =T7 -> Vinfast VF5 Plus (NC) | W7: =CSG!G13 -> 5000000 | X7: =V7 -> Vinfast VF5 Plus (NC) | Y7: =CSG!H13 -> 10000000 | Z7: =N7 -> Vinfast VF5 Plus (NC) | AA7: =CSG!F13 -> 10000000 | AB7: =N7 -> Vinfast VF5 Plus (NC) | AC7: =CSG!J13 -> 10000000 | AE7: =N7 -> Vinfast VF5 Plus (NC) | AM7: =AE7 -> Vinfast VF5 Plus (NC) | AN7: =CSG!Z13 -> 515520000 | AP7: =AM7 -> Vinfast VF5 Plus (NC) | AQ7: =CSG!R13 -> Miễn phí sạc 02 năm tại VGreen | AR7: =AP7 -> Vinfast VF5 Plus (NC) | AS7: =CSG!S13 -> Miễn phí bãi đổ xe và ưu tiên hệ sinh thái VINGROUP | AT7: =AR7 -> Vinfast VF5 Plus (NC) | AU7: =CSG!T13 -> 0 | AV7: =AR7 -> Vinfast VF5 Plus (NC) | AW7: =CSG!U13 -> 0 | AX7: =AP7 -> Vinfast VF5 Plus (NC) | AY7: =CSG!V13 -> 0 | AZ7: =AP7 -> Vinfast VF5 Plus (NC) | BA7: =CSG!W13 -> 0 | BC7: =AZ7 -> Vinfast VF5 Plus (NC) | BD7: Thời gian nạp pin (10 - 70%) trong 33 phút | BE7: =BC7 -> Vinfast VF5 Plus (NC) | BF7: Công suất tối đa 100 kW/134 hp | BG7: =BE7 -> Vinfast VF5 Plus (NC) | BH7: Lazang 17 Inch | BI7: =BG7 -> Vinfast VF5 Plus (NC) | BJ7: Trang bị 06 túi khí | BK7: =BI7 -> Vinfast VF5 Plus (NC) | BL7: Quãng đường di chuyển dự kiến 326Km
A8: =J6 -> NERIO | B8: =CSG!B15 -> Nerio Green | C8: =CSG!C15 -> 668000000 | E8: =A8 -> NERIO | F8: =B8 -> Nerio Green | H8: =G8-I8 -> 0 | J8: =CSG!A21 -> LIMO | K8: Limo Green | M8: =E8 -> NERIO | N8: =B8 -> Nerio Green | O8: =C8 -> 668000000 | P8: =CSG!D15 -> 26720000 | Q8: =CSG!G15 -> 0 | R8: =CSG!H15 -> 0 | S8: =CSG!I15 -> 0 | T8: =N8 -> Nerio Green | U8: =CSG!E15 -> 13000000 | V8: =T8 -> Nerio Green | W8: =CSG!G15 -> 0 | X8: =V8 -> Nerio Green | Y8: =CSG!H15 -> 0 | Z8: =N8 -> Nerio Green | AA8: =CSG!F15 -> 6500000 | AB8: =N8 -> Nerio Green | AC8: =CSG!J15 -> 9500000 | AD8: =M8 -> NERIO | AE8: =N8 -> Nerio Green | AF8: =H8 -> 0 | AH8: BAC | AI8: Miền Bắc | AM8: =AE8 -> Nerio Green | AN8: =CSG!Z15 -> 641280000 | AP8: =AM8 -> Nerio Green | AQ8: =CSG!R15 -> Miễn phí sạc 02 năm tại VGreen | AR8: =AP8 -> Nerio Green | AS8: =CSG!S15 -> Miễn phí bãi đổ xe và ưu tiên hệ sinh thái VINGROUP | AT8: =AR8 -> Nerio Green | AU8: =CSG!T15 -> 0 | AV8: =AR8 -> Nerio Green | AW8: =CSG!U15 -> 0 | AX8: =AP8 -> Nerio Green | AY8: =CSG!V15 -> 0 | AZ8: =AP8 -> Nerio Green | BA8: =CSG!W15 -> 0 | BC8: =AZ8 -> Nerio Green | BD8: Thời gian nạp pin (10 - 70%) trong 27 phút | BE8: =BC8 -> Nerio Green | BF8: Công suất tối đa 100 kW/147 hp | BG8: =BE8 -> Nerio Green | BH8: Lazang 17 Inch | BI8: =BG8 -> Nerio Green | BJ8: Trang bị 06 túi khí | BK8: =BI8 -> Nerio Green | BL8: Quãng đường di chuyển dự kiến 318Km
A9: =CSG!A16 -> VF.6 | B9: =CSG!B17 -> Vinfast VF6 Eco | C9: =CSG!C17 -> 689000000 | E9: =A9 -> VF.6 | F9: =B9 -> Vinfast VF6 Eco | H9: =G9-I9 -> 0 | J9: =CSG!A23 -> VF.7 | K9: Vinfast VF7 | M9: =E9 -> VF.6 | N9: =B9 -> Vinfast VF6 Eco | O9: =C9 -> 689000000 | P9: =CSG!D17 -> 27560000 | Q9: =CSG!G17 -> 3000000 | R9: =CSG!H17 -> 12000000 | S9: =CSG!I17 -> 0 | T9: =N9 -> Vinfast VF6 Eco | U9: =CSG!E17 -> 18000000 | V9: =T9 -> Vinfast VF6 Eco | W9: =CSG!G17 -> 3000000 | X9: =V9 -> Vinfast VF6 Eco | Y9: =CSG!H17 -> 12000000 | Z9: =N9 -> Vinfast VF6 Eco | AA9: =CSG!F17 -> 15000000 | AB9: =N9 -> Vinfast VF6 Eco | AC9: =CSG!J17 -> 15000000 | AD9: =M9 -> VF.6 | AE9: =N9 -> Vinfast VF6 Eco | AF9: =H9 -> 0 | AM9: =AE9 -> Vinfast VF6 Eco | AN9: =CSG!Z17 -> 661440000 | AP9: =AM9 -> Vinfast VF6 Eco | AQ9: =CSG!R17 -> Miễn phí sạc 02 năm tại VGreen | AR9: =AP9 -> Vinfast VF6 Eco | AS9: =CSG!S17 -> Miễn phí bãi đổ xe và ưu tiên hệ sinh thái VINGROUP | AT9: =AR9 -> Vinfast VF6 Eco | AU9: =CSG!T17 -> 0 | AV9: =AR9 -> Vinfast VF6 Eco | AW9: =CSG!U17 -> 0 | AX9: =AP9 -> Vinfast VF6 Eco | AY9: =CSG!V17 -> 0 | AZ9: =AP9 -> Vinfast VF6 Eco | BA9: =CSG!W17 -> 0 | BC9: =AZ9 -> Vinfast VF6 Eco | BD9: Thời gian nạp pin (10 - 70%) trong 25 phút | BE9: =BC9 -> Vinfast VF6 Eco | BF9: Công suất tối đa 130 kW/174 hp | BG9: =BE9 -> Vinfast VF6 Eco | BH9: Lazang 17 Inch | BI9: =BG9 -> Vinfast VF6 Eco | BJ9: Trang bị 04 túi khí | BK9: =BI9 -> Vinfast VF6 Eco | BL9: Quãng đường di chuyển dự kiến 480Km
B10: =CSG!B18 -> Vinfast VF6 Eco (NC) | C10: =CSG!C18 -> 694000000 | F10: =B10 -> Vinfast VF6 Eco (NC) | H10: =G10-I10 -> 0 | J10: =CSG!A29 -> VF.8 | K10: Vinfast VF8 | N10: =B10 -> Vinfast VF6 Eco (NC) | O10: =C10 -> 694000000 | P10: =CSG!D18 -> 27760000 | Q10: =CSG!G18 -> 3000000 | R10: =CSG!H18 -> 12000000 | S10: =CSG!I18 -> 0 | T10: =N10 -> Vinfast VF6 Eco (NC) | U10: =CSG!E18 -> 18000000 | V10: =T10 -> Vinfast VF6 Eco (NC) | W10: =CSG!G18 -> 3000000 | X10: =V10 -> Vinfast VF6 Eco (NC) | Y10: =CSG!H18 -> 12000000 | Z10: =N10 -> Vinfast VF6 Eco (NC) | AA10: =CSG!F18 -> 15000000 | AB10: =N10 -> Vinfast VF6 Eco (NC) | AC10: =CSG!J18 -> 15000000 | AE10: =N10 -> Vinfast VF6 Eco (NC) | AF10: =H10 -> 0 | AM10: =AE10 -> Vinfast VF6 Eco (NC) | AN10: =CSG!Z18 -> 666240000 | AP10: =AM10 -> Vinfast VF6 Eco (NC) | AQ10: =CSG!R18 -> Miễn phí sạc 02 năm tại VGreen | AR10: =AP10 -> Vinfast VF6 Eco (NC) | AS10: =CSG!S18 -> Miễn phí bãi đổ xe và ưu tiên hệ sinh thái VINGROUP | AT10: =AR10 -> Vinfast VF6 Eco (NC) | AU10: =CSG!T18 -> 0 | AV10: =AR10 -> Vinfast VF6 Eco (NC) | AW10: =CSG!U18 -> 0 | AX10: =AP10 -> Vinfast VF6 Eco (NC) | AY10: =CSG!V18 -> 0 | AZ10: =AP10 -> Vinfast VF6 Eco (NC) | BA10: =CSG!W18 -> 0 | BC10: =AZ10 -> Vinfast VF6 Eco (NC) | BD10: Thời gian nạp pin (10 - 70%) trong 25 phút | BE10: =BC10 -> Vinfast VF6 Eco (NC) | BF10: Công suất tối đa 130 kW/174 hp | BG10: =BE10 -> Vinfast VF6 Eco (NC) | BH10: Lazang 17 Inch | BI10: =BG10 -> Vinfast VF6 Eco (NC) | BJ10: Trang bị 04 túi khí | BK10: =BI10 -> Vinfast VF6 Eco (NC) | BL10: Quãng đường di chuyển dự kiến 480Km
B11: =CSG!B19 -> Vinfast VF6 Plus | C11: =CSG!C19 -> 749000000 | F11: =B11 -> Vinfast VF6 Plus | H11: =G11-I11 -> 0 | J11: =CSG!A33 -> VF.9 | K11: Vinfast VF9 | N11: =B11 -> Vinfast VF6 Plus | O11: =C11 -> 749000000 | P11: =CSG!D19 -> 29960000 | Q11: =CSG!G19 -> 3000000 | R11: =CSG!H19 -> 12000000 | S11: =CSG!I19 -> 0 | T11: =N11 -> Vinfast VF6 Plus | U11: =CSG!E19 -> 18000000 | V11: =T11 -> Vinfast VF6 Plus | W11: =CSG!G19 -> 3000000 | X11: =V11 -> Vinfast VF6 Plus | Y11: =CSG!H19 -> 12000000 | Z11: =N11 -> Vinfast VF6 Plus | AA11: =CSG!F19 -> 15000000 | AB11: =N11 -> Vinfast VF6 Plus | AC11: =CSG!J19 -> 15000000 | AE11: =N11 -> Vinfast VF6 Plus | AF11: =H11 -> 0 | AM11: =AE11 -> Vinfast VF6 Plus | AN11: =CSG!Z19 -> 719040000 | AP11: =AM11 -> Vinfast VF6 Plus | AQ11: =CSG!R19 -> Miễn phí sạc 02 năm tại VGreen | AR11: =AP11 -> Vinfast VF6 Plus | AS11: =CSG!S19 -> Miễn phí bãi đổ xe và ưu tiên hệ sinh thái VINGROUP | AT11: =AR11 -> Vinfast VF6 Plus | AU11: =CSG!T19 -> 0 | AV11: =AR11 -> Vinfast VF6 Plus | AW11: =CSG!U19 -> 0 | AX11: =AP11 -> Vinfast VF6 Plus | AY11: =CSG!V19 -> 0 | AZ11: =AP11 -> Vinfast VF6 Plus | BA11: =CSG!W19 -> 0 | BC11: =AZ11 -> Vinfast VF6 Plus | BD11: Thời gian nạp pin (10 - 70%) trong 25 phút | BE11: =BC11 -> Vinfast VF6 Plus | BF11: Công suất tối đa 150 kW/201 hp | BG11: =BE11 -> Vinfast VF6 Plus | BH11: Lazang 19 Inch | BI11: =BG11 -> Vinfast VF6 Plus | BJ11: Trang bị 08 túi khí | BK11: =BI11 -> Vinfast VF6 Plus | BL11: Quãng đường di chuyển dự kiến 460Km
B12: =CSG!B20 -> Vinfast VF6 Plus (NC) | C12: =CSG!C20 -> 759000000 | F12: =B12 -> Vinfast VF6 Plus (NC) | H12: =G12-I12 -> 0 | J12: =A27 -> LAC.HONG | K12: Lạc Hồng | N12: =B12 -> Vinfast VF6 Plus (NC) | O12: =C12 -> 759000000 | P12: =CSG!D20 -> 30360000 | Q12: =CSG!G20 -> 3000000 | R12: =CSG!H20 -> 12000000 | S12: =CSG!I20 -> 0 | T12: =N12 -> Vinfast VF6 Plus (NC) | U12: =CSG!E20 -> 18000000 | V12: =T12 -> Vinfast VF6 Plus (NC) | W12: =CSG!G20 -> 3000000 | X12: =V12 -> Vinfast VF6 Plus (NC) | Y12: =CSG!H20 -> 12000000 | Z12: =N12 -> Vinfast VF6 Plus (NC) | AA12: =CSG!F20 -> 15000000 | AB12: =N12 -> Vinfast VF6 Plus (NC) | AC12: =CSG!J20 -> 15000000 | AE12: =N12 -> Vinfast VF6 Plus (NC) | AF12: =H12 -> 0 | AM12: =AE12 -> Vinfast VF6 Plus (NC) | AN12: =CSG!Z20 -> 728640000 | AP12: =AM12 -> Vinfast VF6 Plus (NC) | AQ12: =CSG!R20 -> Miễn phí sạc 02 năm tại VGreen | AR12: =AP12 -> Vinfast VF6 Plus (NC) | AS12: =CSG!S20 -> Miễn phí bãi đổ xe và ưu tiên hệ sinh thái VINGROUP | AT12: =AR12 -> Vinfast VF6 Plus (NC) | AU12: =CSG!T20 -> 0 | AV12: =AR12 -> Vinfast VF6 Plus (NC) | AW12: =CSG!U20 -> 0 | AX12: =AP12 -> Vinfast VF6 Plus (NC) | AY12: =CSG!V20 -> 0 | AZ12: =AP12 -> Vinfast VF6 Plus (NC) | BA12: =CSG!W20 -> 0 | BC12: =AZ12 -> Vinfast VF6 Plus (NC) | BD12: Thời gian nạp pin (10 - 70%) trong 25 phút | BE12: =BC12 -> Vinfast VF6 Plus (NC) | BF12: Công suất tối đa 150 kW/201 hp | BG12: =BE12 -> Vinfast VF6 Plus (NC) | BH12: Lazang 19 Inch | BI12: =BG12 -> Vinfast VF6 Plus (NC) | BJ12: Trang bị 08 túi khí | BK12: =BI12 -> Vinfast VF6 Plus (NC) | BL12: Quãng đường di chuyển dự kiến 460Km
A13: =CSG!A21 -> LIMO | B13: Limo Green | C13: =CSG!C22 -> 749000000 | E13: =A13 -> LIMO | F13: =B13 -> Limo Green | H13: =G13-I13 -> 0 | J13: =CSG!A42 -> ECVAN | K13: AC Van | M13: =E13 -> LIMO | N13: =F13 -> Limo Green | O13: =C13 -> 749000000 | P13: =CSG!D22 -> 29960000 | Q13: =CSG!G22 -> 0 | R13: =CSG!H22 -> 12000000 | S13: =CSG!I22 -> 0 | T13: =N13 -> Limo Green | U13: =CSG!E22 -> 16000000 | V13: =T13 -> Limo Green | W13: =CSG!G22 -> 0 | X13: =V13 -> Limo Green | Y13: =CSG!H22 -> 12000000 | Z13: =N13 -> Limo Green | AA13: =CSG!F22 -> 7500000 | AB13: =N13 -> Limo Green | AC13: =CSG!J22 -> 15000000 | AD13: =M13 -> LIMO | AE13: =N13 -> Limo Green | AF13: =H13 -> 0 | AH13: MẪ NHÓM 2 | AI13: TÊN NHÓM 2 | AM13: =AE13 -> Limo Green | AN13: =CSG!Z22 -> 719040000 | AP13: =AM13 -> Limo Green | AQ13: =CSG!R22 -> Miễn phí sạc 02 năm tại VGreen | AR13: =AP13 -> Limo Green | AS13: =CSG!S22 -> Miễn phí bãi đổ xe và ưu tiên hệ sinh thái VINGROUP | AT13: =AR13 -> Limo Green | AU13: =CSG!T22 -> 0 | AV13: =AR13 -> Limo Green | AW13: =CSG!U22 -> 0 | AX13: =AP13 -> Limo Green | AY13: =CSG!V22 -> 0 | AZ13: =AX13 -> Limo Green | BA13: =CSG!W22 -> 0 | BC13: =AZ13 -> Limo Green | BD13: Thời gian nạp pin (10 - 70%) trong 30 phút | BE13: =BC13 -> Limo Green | BF13: Công suất tối đa 150 kW/201 hp | BG13: =BE13 -> Limo Green | BH13: Lazang 18 Inch | BI13: =BG13 -> Limo Green | BJ13: Trang bị 06 túi khí | BK13: =BI13 -> Limo Green | BL13: Quãng đường di chuyển dự kiến 450Km
A14: =CSG!A23 -> VF.7 | B14: =CSG!B24 -> Vinfast VF7 Eco | C14: =CSG!C24 -> 799000000 | E14: =A14 -> VF.7 | F14: =B14 -> Vinfast VF7 Eco | H14: =G14-I14 -> 0 | M14: =E14 -> VF.7 | N14: =F14 -> Vinfast VF7 Eco | O14: =C14 -> 799000000 | P14: =CSG!D24 -> 31960000 | Q14: =CSG!G24 -> 10000000 | R14: =CSG!H24 -> 15000000 | S14: =CSG!I24 -> 0 | T14: =N14 -> Vinfast VF7 Eco | U14: =CSG!E24 -> 18000000 | V14: =T14 -> Vinfast VF7 Eco | W14: =CSG!G24 -> 10000000 | X14: =V14 -> Vinfast VF7 Eco | Y14: =CSG!H24 -> 15000000 | Z14: =N14 -> Vinfast VF7 Eco | AA14: =CSG!F24 -> 35000000 | AB14: =N14 -> Vinfast VF7 Eco | AC14: =CSG!J24 -> 50000000 | AD14: =M14 -> VF.7 | AE14: =N14 -> Vinfast VF7 Eco | AF14: =H14 -> 0 | AH14: 2019 | AI14: XE 2019 | AM14: =AE14 -> Vinfast VF7 Eco | AN14: =CSG!Z24 -> 767040000 | AP14: =AM14 -> Vinfast VF7 Eco | AQ14: =CSG!R24 -> Miễn phí sạc 02 năm tại VGreen | AR14: =AP14 -> Vinfast VF7 Eco | AS14: =CSG!S24 -> Miễn phí bãi đổ xe và ưu tiên hệ sinh thái VINGROUP | AT14: =AR14 -> Vinfast VF7 Eco | AU14: =CSG!T24 -> 0 | AV14: =AR14 -> Vinfast VF7 Eco | AW14: =CSG!U24 -> 0 | AX14: =AP14 -> Vinfast VF7 Eco | AY14: =CSG!V24 -> 0 | AZ14: =AX14 -> Vinfast VF7 Eco | BA14: =CSG!W24 -> 0 | BC14: =AZ14 -> Vinfast VF7 Eco | BD14: Thời gian nạp pin (10 - 70%) < 25 phút | BE14: =BC14 -> Vinfast VF7 Eco | BF14: Công suất tối đa 130 kW/174 hp | BG14: =BE14 -> Vinfast VF7 Eco | BH14: Lazang 19 Inch | BI14: =BG14 -> Vinfast VF7 Eco | BJ14: Trang bị 06 túi khí | BK14: =BI14 -> Vinfast VF7 Eco | BL14: Quãng đường di chuyển dự kiến 498Km
B15: =CSG!B25 -> Vinfast VF7 Plus (TC) - Thép | C15: =CSG!C25 -> 949000000 | F15: =B15 -> Vinfast VF7 Plus (TC) - Thép | H15: =G15-I15 -> 0 | N15: =F15 -> Vinfast VF7 Plus (TC) - Thép | O15: =C15 -> 949000000 | P15: =CSG!D25 -> 37960000 | Q15: =CSG!G25 -> 10000000 | R15: =CSG!H25 -> 15000000 | S15: =CSG!I25 -> 0 | T15: =N15 -> Vinfast VF7 Plus (TC) - Thép | U15: =CSG!E25 -> 20000000 | V15: =T15 -> Vinfast VF7 Plus (TC) - Thép | W15: =CSG!G25 -> 10000000 | X15: =V15 -> Vinfast VF7 Plus (TC) - Thép | Y15: =CSG!H25 -> 15000000 | Z15: =N15 -> Vinfast VF7 Plus (TC) - Thép | AA15: =CSG!F25 -> 35000000 | AB15: =N15 -> Vinfast VF7 Plus (TC) - Thép | AC15: =CSG!J25 -> 50000000 | AE15: =N15 -> Vinfast VF7 Plus (TC) - Thép | AF15: =H15 -> 0 | AH15: 2020 | AI15: XE 2020 | AM15: =AE15 -> Vinfast VF7 Plus (TC) - Thép | AN15: =CSG!Z25 -> 911040000 | AP15: =AM15 -> Vinfast VF7 Plus (TC) - Thép | AQ15: =CSG!R25 -> Miễn phí sạc 02 năm tại VGreen | AR15: =AP15 -> Vinfast VF7 Plus (TC) - Thép | AS15: =CSG!S25 -> Miễn phí bãi đổ xe và ưu tiên hệ sinh thái VINGROUP | AT15: =AR15 -> Vinfast VF7 Plus (TC) - Thép | AU15: =CSG!T25 -> 0 | AV15: =AR15 -> Vinfast VF7 Plus (TC) - Thép | AW15: =CSG!U25 -> 0 | AX15: =AP15 -> Vinfast VF7 Plus (TC) - Thép | AY15: =CSG!V25 -> 0 | AZ15: =AX15 -> Vinfast VF7 Plus (TC) - Thép | BA15: =CSG!W25 -> 0 | BC15: =AZ15 -> Vinfast VF7 Plus (TC) - Thép | BD15: Thời gian nạp pin (10 - 70%) < 28 phút | BE15: =BC15 -> Vinfast VF7 Plus (TC) - Thép | BF15: Công suất tối đa 150 kW/201 hp | BG15: =BE15 -> Vinfast VF7 Plus (TC) - Thép | BH15: Lazang 20 Inch | BI15: =BG15 -> Vinfast VF7 Plus (TC) - Thép | BJ15: Trang bị 08 túi khí | BK15: =BI15 -> Vinfast VF7 Plus (TC) - Thép | BL15: Quãng đường di chuyển dự kiến 496Km
B16: =CSG!B26 -> Vinfast VF7 Plus (NC) - Thép | C16: =CSG!C26 -> 999000000 | F16: =B16 -> Vinfast VF7 Plus (NC) - Thép | H16: =G16-I16 -> 0 | N16: =F16 -> Vinfast VF7 Plus (NC) - Thép | O16: =C16 -> 999000000 | P16: =CSG!D26 -> 39960000 | Q16: =CSG!G26 -> 10000000 | R16: =CSG!H26 -> 15000000 | S16: =CSG!I26 -> 0 | T16: =N16 -> Vinfast VF7 Plus (NC) - Thép | U16: =CSG!E26 -> 20000000 | V16: =T16 -> Vinfast VF7 Plus (NC) - Thép | W16: =CSG!G26 -> 10000000 | X16: =V16 -> Vinfast VF7 Plus (NC) - Thép | Y16: =CSG!H26 -> 15000000 | Z16: =N16 -> Vinfast VF7 Plus (NC) - Thép | AA16: =CSG!F26 -> 35000000 | AB16: =N16 -> Vinfast VF7 Plus (NC) - Thép | AC16: =CSG!J26 -> 50000000 | AE16: =N16 -> Vinfast VF7 Plus (NC) - Thép | AF16: =H16 -> 0 | AM16: =AE16 -> Vinfast VF7 Plus (NC) - Thép | AN16: =CSG!Z26 -> 959040000 | AP16: =AM16 -> Vinfast VF7 Plus (NC) - Thép | AQ16: =CSG!R26 -> Miễn phí sạc 02 năm tại VGreen | AR16: =AP16 -> Vinfast VF7 Plus (NC) - Thép | AS16: =CSG!S26 -> Miễn phí bãi đổ xe và ưu tiên hệ sinh thái VINGROUP | AT16: =AR16 -> Vinfast VF7 Plus (NC) - Thép | AU16: =CSG!T26 -> 0 | AV16: =AR16 -> Vinfast VF7 Plus (NC) - Thép | AW16: =CSG!U26 -> 0 | AX16: =AP16 -> Vinfast VF7 Plus (NC) - Thép | AY16: =CSG!V26 -> 0 | AZ16: =AX16 -> Vinfast VF7 Plus (NC) - Thép | BA16: =CSG!W26 -> 0 | BC16: =AZ16 -> Vinfast VF7 Plus (NC) - Thép | BD16: Thời gian nạp pin (10 - 70%) < 28 phút | BE16: =BC16 -> Vinfast VF7 Plus (NC) - Thép | BF16: Công suất tối đa 260 kW/349 hp | BG16: =BE16 -> Vinfast VF7 Plus (NC) - Thép | BH16: Lazang 20 Inch | BI16: =BG16 -> Vinfast VF7 Plus (NC) - Thép | BJ16: Trang bị 08 túi khí | BK16: =BI16 -> Vinfast VF7 Plus (NC) - Thép | BL16: Quãng đường di chuyển dự kiến 496Km
B17: =CSG!B27 -> Vinfast VF7 Plus (TC) - Kính | C17: =CSG!C27 -> 969000000 | F17: =B17 -> Vinfast VF7 Plus (TC) - Kính | H17: =G17-I17 -> 0 | N17: =F17 -> Vinfast VF7 Plus (TC) - Kính | O17: =C17 -> 969000000 | P17: =CSG!D27 -> 38760000 | Q17: =CSG!G27 -> 10000000 | R17: =CSG!H27 -> 15000000 | S17: =CSG!I27 -> 0 | T17: =N17 -> Vinfast VF7 Plus (TC) - Kính | U17: =CSG!E27 -> 20000000 | V17: =T17 -> Vinfast VF7 Plus (TC) - Kính | W17: =CSG!G27 -> 10000000 | X17: =V17 -> Vinfast VF7 Plus (TC) - Kính | Y17: =CSG!H27 -> 15000000 | Z17: =N17 -> Vinfast VF7 Plus (TC) - Kính | AA17: =CSG!F27 -> 35000000 | AB17: =N17 -> Vinfast VF7 Plus (TC) - Kính | AC17: =CSG!J27 -> 50000000 | AE17: =N17 -> Vinfast VF7 Plus (TC) - Kính | AF17: =H17 -> 0 | AM17: =AE17 -> Vinfast VF7 Plus (TC) - Kính | AN17: =CSG!Z27 -> 930240000 | AP17: =AM17 -> Vinfast VF7 Plus (TC) - Kính | AQ17: =CSG!R27 -> Miễn phí sạc 02 năm tại VGreen | AR17: =AP17 -> Vinfast VF7 Plus (TC) - Kính | AS17: =CSG!S27 -> Miễn phí bãi đổ xe và ưu tiên hệ sinh thái VINGROUP | AT17: =AR17 -> Vinfast VF7 Plus (TC) - Kính | AU17: =CSG!T27 -> 0 | AV17: =AR17 -> Vinfast VF7 Plus (TC) - Kính | AW17: =CSG!U27 -> 0 | AX17: =AV17 -> Vinfast VF7 Plus (TC) - Kính | AY17: =CSG!V27 -> 0 | AZ17: =AX17 -> Vinfast VF7 Plus (TC) - Kính | BA17: =CSG!W27 -> 0 | BC17: =AZ17 -> Vinfast VF7 Plus (TC) - Kính | BD17: Thời gian nạp pin (10 - 70%) < 28 phút | BE17: =BC17 -> Vinfast VF7 Plus (TC) - Kính | BF17: Công suất tối đa 150 kW/201 hp | BG17: =BE17 -> Vinfast VF7 Plus (TC) - Kính | BH17: Lazang 20 Inch | BI17: =BG17 -> Vinfast VF7 Plus (TC) - Kính | BJ17: Trang bị 08 túi khí | BK17: =BI17 -> Vinfast VF7 Plus (TC) - Kính | BL17: Quãng đường di chuyển dự kiến 496Km
B18: =CSG!B28 -> Vinfast VF7 Plus (NC) - Kính | C18: =CSG!C28 -> 1019000000 | F18: =B18 -> Vinfast VF7 Plus (NC) - Kính | H18: =G18-I18 -> 0 | N18: =F18 -> Vinfast VF7 Plus (NC) - Kính | O18: =C18 -> 1019000000 | P18: =CSG!D28 -> 40760000 | Q18: =CSG!G28 -> 10000000 | R18: =CSG!H28 -> 15000000 | S18: =CSG!I28 -> 0 | T18: =N18 -> Vinfast VF7 Plus (NC) - Kính | U18: =CSG!E28 -> 20000000 | V18: =T18 -> Vinfast VF7 Plus (NC) - Kính | W18: =CSG!G28 -> 10000000 | X18: =V18 -> Vinfast VF7 Plus (NC) - Kính | Y18: =CSG!H28 -> 15000000 | Z18: =N18 -> Vinfast VF7 Plus (NC) - Kính | AA18: =CSG!F28 -> 35000000 | AB18: =N18 -> Vinfast VF7 Plus (NC) - Kính | AC18: =CSG!J28 -> 50000000 | AE18: =N18 -> Vinfast VF7 Plus (NC) - Kính | AF18: =H18 -> 0 | AM18: =AE18 -> Vinfast VF7 Plus (NC) - Kính | AN18: =CSG!Z28 -> 978240000 | AP18: =AM18 -> Vinfast VF7 Plus (NC) - Kính | AQ18: =CSG!R28 -> Miễn phí sạc 02 năm tại VGreen | AR18: =AP18 -> Vinfast VF7 Plus (NC) - Kính | AS18: =CSG!S28 -> Miễn phí bãi đổ xe và ưu tiên hệ sinh thái VINGROUP | AT18: =AR18 -> Vinfast VF7 Plus (NC) - Kính | AU18: =CSG!T28 -> 0 | AV18: =AT18 -> Vinfast VF7 Plus (NC) - Kính | AW18: =CSG!U28 -> 0 | AX18: =AV18 -> Vinfast VF7 Plus (NC) - Kính | AY18: =CSG!V28 -> 0 | AZ18: =AX18 -> Vinfast VF7 Plus (NC) - Kính | BA18: =CSG!W28 -> 0 | BC18: =AZ18 -> Vinfast VF7 Plus (NC) - Kính | BD18: Thời gian nạp pin (10 - 70%) < 28 phút | BE18: =BC18 -> Vinfast VF7 Plus (NC) - Kính | BF18: Công suất tối đa 260 kW/349 hp | BG18: =BE18 -> Vinfast VF7 Plus (NC) - Kính | BH18: Lazang 20 Inch | BI18: =BG18 -> Vinfast VF7 Plus (NC) - Kính | BJ18: Trang bị 08 túi khí | BK18: =BI18 -> Vinfast VF7 Plus (NC) - Kính | BL18: Quãng đường di chuyển dự kiến 496Km
A19: =CSG!A29 -> VF.8 | B19: =CSG!B30 -> Vinfast VF8 Eco (TC) | C19: =CSG!C30 -> 1019000000 | E19: =A19 -> VF.8 | F19: =B19 -> Vinfast VF8 Eco (TC) | H19: =G19-I19 -> 0 | M19: =E19 -> VF.8 | N19: =B19 -> Vinfast VF8 Eco (TC) | O19: =C19 -> 1019000000 | P19: =CSG!D30 -> 40760000 | Q19: =CSG!G30 -> 15000000 | R19: =CSG!H30 -> 20000000 | S19: =CSG!I30 -> 0 | T19: =N19 -> Vinfast VF8 Eco (TC) | U19: =CSG!E30 -> 30000000 | V19: =T19 -> Vinfast VF8 Eco (TC) | W19: =CSG!G30 -> 15000000 | X19: =V19 -> Vinfast VF8 Eco (TC) | Y19: =CSG!H30 -> 20000000 | Z19: =N19 -> Vinfast VF8 Eco (TC) | AA19: =CSG!F30 -> 50000000 | AB19: =N19 -> Vinfast VF8 Eco (TC) | AC19: =CSG!J30 -> 70000000 | AD19: Elantra | AE19: =B19 -> Vinfast VF8 Eco (TC) | AF19: =H19 -> 0 | AM19: =B19 -> Vinfast VF8 Eco (TC) | AN19: =CSG!Z30 -> 978240000 | AP19: =AM19 -> Vinfast VF8 Eco (TC) | AQ19: =CSG!R30 -> Miễn phí sạc 02 năm tại VGreen | AR19: =AP19 -> Vinfast VF8 Eco (TC) | AS19: =CSG!S30 -> Miễn phí bãi đổ xe và ưu tiên hệ sinh thái VINGROUP | AT19: =AR19 -> Vinfast VF8 Eco (TC) | AU19: =CSG!T30 -> 0 | AV19: =AR19 -> Vinfast VF8 Eco (TC) | AW19: =CSG!U30 -> 0 | AX19: =AP19 -> Vinfast VF8 Eco (TC) | AY19: =CSG!V30 -> 0 | AZ19: =AX19 -> Vinfast VF8 Eco (TC) | BA19: =CSG!W30 -> 0 | BC19: =AZ19 -> Vinfast VF8 Eco (TC) | BD19: Thời gian nạp pin (10 - 70%) < 28 phút | BE19: =BC19 -> Vinfast VF8 Eco (TC) | BF19: Công suất tối đa 150 kW/201 hp | BG19: =BE19 -> Vinfast VF8 Eco (TC) | BH19: Lazang 19 Inch | BI19: =BG19 -> Vinfast VF8 Eco (TC) | BJ19: Trang bị 10 túi khí | BK19: =BI19 -> Vinfast VF8 Eco (TC) | BL19: Quãng đường di chuyển dự kiến 562 Km
B20: =CSG!B31 -> Vinfast VF8 Eco (NC) | C20: =CSG!C31 -> 1069000000 | F20: =B20 -> Vinfast VF8 Eco (NC) | H20: =G20-I20 -> 0 | N20: =B20 -> Vinfast VF8 Eco (NC) | O20: =C20 -> 1069000000 | P20: =CSG!D31 -> 42760000 | Q20: =CSG!G31 -> 15000000 | R20: =CSG!H31 -> 20000000 | S20: =CSG!I31 -> 0 | T20: =N20 -> Vinfast VF8 Eco (NC) | U20: =CSG!E31 -> 30000000 | V20: =T20 -> Vinfast VF8 Eco (NC) | W20: =CSG!G31 -> 15000000 | X20: =V20 -> Vinfast VF8 Eco (NC) | Y20: =CSG!H31 -> 20000000 | Z20: =N20 -> Vinfast VF8 Eco (NC) | AA20: =CSG!F31 -> 50000000 | AB20: =N20 -> Vinfast VF8 Eco (NC) | AC20: =CSG!J31 -> 70000000 | AE20: =B20 -> Vinfast VF8 Eco (NC) | AF20: =H20 -> 0 | AM20: =B20 -> Vinfast VF8 Eco (NC) | AN20: =CSG!Z31 -> 1026240000 | AP20: =AM20 -> Vinfast VF8 Eco (NC) | AQ20: =CSG!R31 -> Miễn phí sạc 02 năm tại VGreen | AR20: =AP20 -> Vinfast VF8 Eco (NC) | AS20: =CSG!S31 -> Miễn phí bãi đổ xe và ưu tiên hệ sinh thái VINGROUP | AT20: =AR20 -> Vinfast VF8 Eco (NC) | AU20: =CSG!T31 -> 0 | AV20: =AR20 -> Vinfast VF8 Eco (NC) | AW20: =CSG!U31 -> 0 | AX20: =AP20 -> Vinfast VF8 Eco (NC) | AY20: =CSG!V31 -> 0 | AZ20: =AX20 -> Vinfast VF8 Eco (NC) | BA20: =CSG!W31 -> 0 | BC20: =AZ20 -> Vinfast VF8 Eco (NC) | BD20: Thời gian nạp pin (10 - 70%) < 28 phút | BE20: =BC20 -> Vinfast VF8 Eco (NC) | BF20: Công suất tối đa 150 kW/201 hp | BG20: =BE20 -> Vinfast VF8 Eco (NC) | BH20: Lazang 20 Inch | BI20: =BG20 -> Vinfast VF8 Eco (NC) | BJ20: Trang bị 11 túi khí | BK20: =BI20 -> Vinfast VF8 Eco (NC) | BL20: Quãng đường di chuyển dự kiến 562 Km
B21: =CSG!B32 -> Vinfast VF8 Plus | C21: =CSG!C32 -> 1199000000 | F21: =B21 -> Vinfast VF8 Plus | H21: =G21-I21 -> 0 | N21: =B21 -> Vinfast VF8 Plus | O21: =C21 -> 1199000000 | P21: =CSG!D32 -> 47960000 | Q21: =CSG!G32 -> 15000000 | R21: =CSG!H32 -> 20000000 | S21: =CSG!I32 -> 0 | T21: =N21 -> Vinfast VF8 Plus | U21: =CSG!E32 -> 35000000 | V21: =T21 -> Vinfast VF8 Plus | W21: =CSG!G32 -> 15000000 | X21: =V21 -> Vinfast VF8 Plus | Y21: =CSG!H32 -> 20000000 | Z21: =N21 -> Vinfast VF8 Plus | AA21: =CSG!F32 -> 50000000 | AB21: =N21 -> Vinfast VF8 Plus | AC21: =CSG!J32 -> 70000000 | AE21: =B21 -> Vinfast VF8 Plus | AF21: =H21 -> 0 | AM21: =B21 -> Vinfast VF8 Plus | AN21: =CSG!Z32 -> 1151040000 | AP21: =AM21 -> Vinfast VF8 Plus | AQ21: =CSG!R32 -> Miễn phí sạc 02 năm tại VGreen | AR21: =AP21 -> Vinfast VF8 Plus | AS21: =CSG!S32 -> Miễn phí bãi đổ xe và ưu tiên hệ sinh thái VINGROUP | AT21: =AR21 -> Vinfast VF8 Plus | AU21: =CSG!T32 -> 0 | AV21: =AR21 -> Vinfast VF8 Plus | AW21: =CSG!U32 -> 0 | AX21: =AP21 -> Vinfast VF8 Plus | AY21: =CSG!V32 -> 0 | AZ21: =AX21 -> Vinfast VF8 Plus | BA21: =CSG!W32 -> 0 | BC21: =AZ21 -> Vinfast VF8 Plus | BD21: Thời gian nạp pin (10 - 70%) < 28 phút | BE21: =BC21 -> Vinfast VF8 Plus | BF21: Công suất tối đa 300 kW/402 hp | BG21: =BE21 -> Vinfast VF8 Plus | BH21: Lazang 20 Inch | BI21: =BG21 -> Vinfast VF8 Plus | BJ21: Trang bị 11 túi khí | BK21: =BI21 -> Vinfast VF8 Plus | BL21: Quãng đường di chuyển dự kiến 457 Km
A22: =CSG!A33 -> VF.9 | B22: =CSG!B34 -> Vinfast VF9 Eco - 7 Chỗ | C22: =CSG!C34 -> 1499000000 | E22: =A22 -> VF.9 | F22: =B22 -> Vinfast VF9 Eco - 7 Chỗ | H22: =G22-I22 -> 0 | M22: =A22 -> VF.9 | N22: =F22 -> Vinfast VF9 Eco - 7 Chỗ | O22: =C22 -> 1499000000 | P22: =CSG!D34 -> 59960000 | Q22: =CSG!G34 -> 30000000 | R22: =CSG!H34 -> 25000000 | S22: =CSG!I34 -> 0 | T22: =N22 -> Vinfast VF9 Eco - 7 Chỗ | U22: =CSG!E34 -> 40000000 | V22: =T22 -> Vinfast VF9 Eco - 7 Chỗ | W22: =CSG!G34 -> 30000000 | X22: =V22 -> Vinfast VF9 Eco - 7 Chỗ | Y22: =CSG!H34 -> 25000000 | Z22: =N22 -> Vinfast VF9 Eco - 7 Chỗ | AA22: =CSG!F34 -> 70000000 | AB22: =N22 -> Vinfast VF9 Eco - 7 Chỗ | AC22: =CSG!J34 -> 100000000 | AD22: =M22 -> VF.9 | AE22: =N22 -> Vinfast VF9 Eco - 7 Chỗ | AF22: =H22 -> 0 | AM22: =AE22 -> Vinfast VF9 Eco - 7 Chỗ | AN22: =CSG!Z34 -> 1439040000 | AP22: =AM22 -> Vinfast VF9 Eco - 7 Chỗ | AQ22: =CSG!R34 -> Miễn phí sạc 02 năm tại VGreen | AR22: =AP22 -> Vinfast VF9 Eco - 7 Chỗ | AS22: =CSG!S34 -> Miễn phí bãi đổ xe và ưu tiên hệ sinh thái VINGROUP | AT22: =AR22 -> Vinfast VF9 Eco - 7 Chỗ | AU22: =CSG!T34 -> 0 | AV22: =AR22 -> Vinfast VF9 Eco - 7 Chỗ | AW22: =CSG!U34 -> 0 | AX22: =AV22 -> Vinfast VF9 Eco - 7 Chỗ | AY22: =CSG!V34 -> 0 | AZ22: =AX22 -> Vinfast VF9 Eco - 7 Chỗ | BA22: =CSG!W34 -> 0 | BC22: =AZ22 -> Vinfast VF9 Eco - 7 Chỗ | BD22: Thời gian nạp pin (10 - 70%) trong 35 phút | BE22: =BC22 -> Vinfast VF9 Eco - 7 Chỗ | BF22: Công suất tối đa 300 kW/402 hp | BG22: =BE22 -> Vinfast VF9 Eco - 7 Chỗ | BH22: Lazang 20 Inch | BI22: =BG22 -> Vinfast VF9 Eco - 7 Chỗ | BJ22: Trang bị 11 túi khí | BK22: =BI22 -> Vinfast VF9 Eco - 7 Chỗ | BL22: Quãng đường di chuyển dự kiến 626 Km
B23: =CSG!B35 -> Vinfast VF9 Plus - Trần Thép (7C) | C23: =CSG!C35 -> 1699000000 | F23: =B23 -> Vinfast VF9 Plus - Trần Thép (7C) | H23: =G23-I23 -> 0 | N23: =F23 -> Vinfast VF9 Plus - Trần Thép (7C) | O23: =C23 -> 1699000000 | P23: =CSG!D35 -> 67960000 | Q23: =CSG!G35 -> 30000000 | R23: =CSG!H35 -> 25000000 | S23: =CSG!I35 -> 0 | T23: =N23 -> Vinfast VF9 Plus - Trần Thép (7C) | U23: =CSG!E35 -> 45000000 | V23: =T23 -> Vinfast VF9 Plus - Trần Thép (7C) | W23: =CSG!G35 -> 30000000 | X23: =V23 -> Vinfast VF9 Plus - Trần Thép (7C) | Y23: =CSG!H35 -> 25000000 | Z23: =N23 -> Vinfast VF9 Plus - Trần Thép (7C) | AA23: =CSG!F35 -> 70000000 | AB23: =N23 -> Vinfast VF9 Plus - Trần Thép (7C) | AC23: =CSG!J35 -> 100000000 | AE23: =N23 -> Vinfast VF9 Plus - Trần Thép (7C) | AF23: =H23 -> 0 | AM23: =AE23 -> Vinfast VF9 Plus - Trần Thép (7C) | AN23: =CSG!Z35 -> 1631040000 | AP23: =AM23 -> Vinfast VF9 Plus - Trần Thép (7C) | AQ23: =CSG!R35 -> Miễn phí sạc 02 năm tại VGreen | AR23: =AP23 -> Vinfast VF9 Plus - Trần Thép (7C) | AS23: =CSG!S35 -> Miễn phí bãi đổ xe và ưu tiên hệ sinh thái VINGROUP | AT23: =AR23 -> Vinfast VF9 Plus - Trần Thép (7C) | AU23: =CSG!T35 -> 0 | AV23: =AR23 -> Vinfast VF9 Plus - Trần Thép (7C) | AW23: =CSG!U35 -> 0 | AX23: =AV23 -> Vinfast VF9 Plus - Trần Thép (7C) | AY23: =CSG!V35 -> 0 | AZ23: =AX23 -> Vinfast VF9 Plus - Trần Thép (7C) | BA23: =CSG!W35 -> 0 | BC23: =AZ23 -> Vinfast VF9 Plus - Trần Thép (7C) | BD23: Thời gian nạp pin (10 - 70%) trong 35 phút | BE23: =BC23 -> Vinfast VF9 Plus - Trần Thép (7C) | BF23: Công suất tối đa 300 kW/402 hp | BG23: =BE23 -> Vinfast VF9 Plus - Trần Thép (7C) | BH23: Lazang 21 Inch | BI23: =BG23 -> Vinfast VF9 Plus - Trần Thép (7C) | BJ23: Trang bị 11 túi khí | BK23: =BI23 -> Vinfast VF9 Plus - Trần Thép (7C) | BL23: Quãng đường di chuyển dự kiến 602 Km
B24: =CSG!B36 -> Vinfast VF9 Plus - Trần Kính (7C) | C24: =CSG!C36 -> 1728000000 | F24: =B24 -> Vinfast VF9 Plus - Trần Kính (7C) | H24: =G24-I24 -> 0 | N24: =F24 -> Vinfast VF9 Plus - Trần Kính (7C) | O24: =C24 -> 1728000000 | P24: =CSG!D36 -> 69120000 | Q24: =CSG!G36 -> 30000000 | R24: =CSG!H36 -> 25000000 | S24: =CSG!I36 -> 0 | T24: =N24 -> Vinfast VF9 Plus - Trần Kính (7C) | U24: =CSG!E36 -> 45000000 | V24: =T24 -> Vinfast VF9 Plus - Trần Kính (7C) | W24: =CSG!G36 -> 30000000 | X24: =V24 -> Vinfast VF9 Plus - Trần Kính (7C) | Y24: =CSG!H36 -> 25000000 | Z24: =N24 -> Vinfast VF9 Plus - Trần Kính (7C) | AA24: =CSG!F36 -> 70000000 | AB24: =N24 -> Vinfast VF9 Plus - Trần Kính (7C) | AC24: =CSG!J36 -> 100000000 | AE24: =N24 -> Vinfast VF9 Plus - Trần Kính (7C) | AF24: =H24 -> 0 | AM24: =AE24 -> Vinfast VF9 Plus - Trần Kính (7C) | AN24: =CSG!Z36 -> 1658880000 | AP24: =AM24 -> Vinfast VF9 Plus - Trần Kính (7C) | AQ24: =CSG!R36 -> Miễn phí sạc 02 năm tại VGreen | AR24: =AP24 -> Vinfast VF9 Plus - Trần Kính (7C) | AS24: =CSG!S36 -> Miễn phí bãi đổ xe và ưu tiên hệ sinh thái VINGROUP | AT24: =AR24 -> Vinfast VF9 Plus - Trần Kính (7C) | AU24: =CSG!T36 -> 0 | AV24: =AR24 -> Vinfast VF9 Plus - Trần Kính (7C) | AW24: =CSG!U36 -> 0 | AX24: =AV24 -> Vinfast VF9 Plus - Trần Kính (7C) | AY24: =CSG!V36 -> 0 | AZ24: =AX24 -> Vinfast VF9 Plus - Trần Kính (7C) | BA24: =CSG!W36 -> 0 | BC24: =AZ24 -> Vinfast VF9 Plus - Trần Kính (7C) | BD24: Thời gian nạp pin (10 - 70%) trong 35 phút | BE24: =BC24 -> Vinfast VF9 Plus - Trần Kính (7C) | BF24: Công suất tối đa 300 kW/402 hp | BG24: =BE24 -> Vinfast VF9 Plus - Trần Kính (7C) | BH24: Lazang 21 Inch | BI24: =BG24 -> Vinfast VF9 Plus - Trần Kính (7C) | BJ24: Trang bị 11 túi khí | BK24: =BI24 -> Vinfast VF9 Plus - Trần Kính (7C) | BL24: Quãng đường di chuyển dự kiến 602 Km
B25: =CSG!B37 -> Vinfast VF9 Plus - Trần Kính (6C) | C25: =CSG!C37 -> 1760000000 | F25: =B25 -> Vinfast VF9 Plus - Trần Kính (6C) | H25: =G25-I25 -> 0 | N25: =F25 -> Vinfast VF9 Plus - Trần Kính (6C) | O25: =C25 -> 1760000000 | P25: =CSG!D37 -> 70400000 | Q25: =CSG!G37 -> 30000000 | R25: =CSG!H37 -> 25000000 | S25: =CSG!I37 -> 0 | T25: =N25 -> Vinfast VF9 Plus - Trần Kính (6C) | U25: =CSG!E37 -> 45000000 | V25: =T25 -> Vinfast VF9 Plus - Trần Kính (6C) | W25: =CSG!G37 -> 30000000 | X25: =V25 -> Vinfast VF9 Plus - Trần Kính (6C) | Y25: =CSG!H37 -> 25000000 | Z25: =N25 -> Vinfast VF9 Plus - Trần Kính (6C) | AA25: =CSG!F37 -> 70000000 | AB25: =N25 -> Vinfast VF9 Plus - Trần Kính (6C) | AC25: =CSG!J37 -> 100000000 | AE25: =N25 -> Vinfast VF9 Plus - Trần Kính (6C) | AF25: =H25 -> 0 | AM25: =AE25 -> Vinfast VF9 Plus - Trần Kính (6C) | AN25: =CSG!Z37 -> 1689600000 | AP25: =AM25 -> Vinfast VF9 Plus - Trần Kính (6C) | AQ25: =CSG!R37 -> Miễn phí sạc 02 năm tại VGreen | AR25: =AP25 -> Vinfast VF9 Plus - Trần Kính (6C) | AS25: =CSG!S37 -> Miễn phí bãi đổ xe và ưu tiên hệ sinh thái VINGROUP | AT25: =AR25 -> Vinfast VF9 Plus - Trần Kính (6C) | AU25: =CSG!T37 -> 0 | AV25: =AR25 -> Vinfast VF9 Plus - Trần Kính (6C) | AW25: =CSG!U37 -> 0 | AX25: =AV25 -> Vinfast VF9 Plus - Trần Kính (6C) | AY25: =CSG!V37 -> 0 | AZ25: =AX25 -> Vinfast VF9 Plus - Trần Kính (6C) | BA25: =CSG!W37 -> 0 | BC25: =AZ25 -> Vinfast VF9 Plus - Trần Kính (6C) | BD25: Thời gian nạp pin (10 - 70%) trong 35 phút | BE25: =BC25 -> Vinfast VF9 Plus - Trần Kính (6C) | BF25: Công suất tối đa 300 kW/402 hp | BG25: =BE25 -> Vinfast VF9 Plus - Trần Kính (6C) | BH25: Lazang 21 Inch | BI25: =BG25 -> Vinfast VF9 Plus - Trần Kính (6C) | BJ25: Trang bị 11 túi khí | BK25: =BI25 -> Vinfast VF9 Plus - Trần Kính (6C) | BL25: Quãng đường di chuyển dự kiến 602 Km
B26: =CSG!B38 -> Vinfast VF9 Plus - Trần Thép (6C) | C26: =CSG!C38 -> 1731000000 | F26: =B26 -> Vinfast VF9 Plus - Trần Thép (6C) | H26: =G26-I26 -> 0 | N26: =F26 -> Vinfast VF9 Plus - Trần Thép (6C) | O26: =C26 -> 1731000000 | P26: =CSG!D38 -> 69240000 | Q26: =CSG!G38 -> 30000000 | R26: =CSG!H38 -> 25000000 | S26: =CSG!I38 -> 0 | T26: =N26 -> Vinfast VF9 Plus - Trần Thép (6C) | U26: =CSG!E38 -> 45000000 | V26: =T26 -> Vinfast VF9 Plus - Trần Thép (6C) | W26: =CSG!G38 -> 30000000 | X26: =V26 -> Vinfast VF9 Plus - Trần Thép (6C) | Y26: =CSG!H38 -> 25000000 | Z26: =N26 -> Vinfast VF9 Plus - Trần Thép (6C) | AA26: =CSG!F38 -> 70000000 | AB26: =N26 -> Vinfast VF9 Plus - Trần Thép (6C) | AC26: =CSG!J38 -> 100000000 | AE26: =N26 -> Vinfast VF9 Plus - Trần Thép (6C) | AF26: =H26 -> 0 | AM26: =AE26 -> Vinfast VF9 Plus - Trần Thép (6C) | AN26: =CSG!Z38 -> 1661760000 | AP26: =AM26 -> Vinfast VF9 Plus - Trần Thép (6C) | AQ26: =CSG!R38 -> Miễn phí sạc 02 năm tại VGreen | AR26: =AP26 -> Vinfast VF9 Plus - Trần Thép (6C) | AS26: =CSG!S38 -> Miễn phí bãi đổ xe và ưu tiên hệ sinh thái VINGROUP | AT26: =AR26 -> Vinfast VF9 Plus - Trần Thép (6C) | AU26: =CSG!T38 -> 0 | AV26: =AR26 -> Vinfast VF9 Plus - Trần Thép (6C) | AW26: =CSG!U38 -> 0 | AX26: =AV26 -> Vinfast VF9 Plus - Trần Thép (6C) | AY26: =CSG!V38 -> 0 | AZ26: =AX26 -> Vinfast VF9 Plus - Trần Thép (6C) | BA26: =CSG!W38 -> 0 | BC26: =AZ26 -> Vinfast VF9 Plus - Trần Thép (6C) | BD26: Thời gian nạp pin (10 - 70%) trong 35 phút | BE26: =BC26 -> Vinfast VF9 Plus - Trần Thép (6C) | BF26: Công suất tối đa 300 kW/402 hp | BG26: =BE26 -> Vinfast VF9 Plus - Trần Thép (6C) | BH26: Lazang 21 Inch | BI26: =BG26 -> Vinfast VF9 Plus - Trần Thép (6C) | BJ26: Trang bị 11 túi khí | BK26: =BI26 -> Vinfast VF9 Plus - Trần Thép (6C) | BL26: Quãng đường di chuyển dự kiến 602 Km
A27: =CSG!A39 -> LAC.HONG | B27: =CSG!B40 -> Vinfast Lạc Hồng | C27: =CSG!C40 -> 5000000000 | E27: =A27 -> LAC.HONG | F27: =B27 -> Vinfast Lạc Hồng | H27: =G27-I27 -> 0 | M27: =E27 -> LAC.HONG | N27: =F27 -> Vinfast Lạc Hồng | O27: =C27 -> 5000000000 | P27: =CSG!D40 -> 200000000 | Q27: =CSG!G40 -> 0 | R27: =CSG!H40 -> 0 | T27: =N27 -> Vinfast Lạc Hồng | U27: =CSG!E40 -> 200000000 | V27: =T27 -> Vinfast Lạc Hồng | W27: =CSG!G40 -> 0 | X27: =V27 -> Vinfast Lạc Hồng | Y27: =CSG!H40 -> 0 | Z27: =X27 -> Vinfast Lạc Hồng | AA27: =CSG!F40 -> 200000000 | AB27: =N27 -> Vinfast Lạc Hồng | AC27: =CSG!J40 -> 0 | AD27: =M22 -> VF.9 | AE27: =N27 -> Vinfast Lạc Hồng | AF27: =H27 -> 0 | AM27: =AE27 -> Vinfast Lạc Hồng | AN27: =CSG!Z40 -> 4800000000 | AP27: =AM27 -> Vinfast Lạc Hồng | AQ27: =CSG!R40 -> Miễn phí sạc 02 năm tại VGreen | AR27: =AP27 -> Vinfast Lạc Hồng | AS27: =CSG!S40 -> Miễn phí bãi đổ xe và ưu tiên hệ sinh thái VINGROUP | AT27: =AR27 -> Vinfast Lạc Hồng | AU27: =CSG!T40 -> 0 | AV27: =AR27 -> Vinfast Lạc Hồng | AW27: =CSG!U40 -> 0 | AX27: =AV27 -> Vinfast Lạc Hồng | AY27: =CSG!V40 -> 0 | AZ27: =AX27 -> Vinfast Lạc Hồng | BA27: =CSG!W40 -> 0 | BC27: =AZ27 -> Vinfast Lạc Hồng | BD27: Thời gian nạp pin (10 - 70%) trong 35 phút | BE27: =BC27 -> Vinfast Lạc Hồng | BF27: Công suất tối đa 300 kW/402 hp | BG27: =BE27 -> Vinfast Lạc Hồng | BH27: Lazang 21 Inch | BI27: =BG27 -> Vinfast Lạc Hồng | BJ27: Trang bị 11 túi khí | BK27: =BI27 -> Vinfast Lạc Hồng | BL27: Quãng đường di chuyển dự kiến 595 Km
B28: =CSG!B41 -> Vinfast Lạc Hồng (Chống Đạn) | C28: =CSG!C41 -> 34000000000 | F28: =B28 -> Vinfast Lạc Hồng (Chống Đạn) | H28: =G28-I28 -> 0 | N28: =F28 -> Vinfast Lạc Hồng (Chống Đạn) | O28: =C28 -> 34000000000 | P28: =CSG!D41 -> 1360000000 | Q28: =CSG!G41 -> 0 | R28: =CSG!H41 -> 0 | T28: =N28 -> Vinfast Lạc Hồng (Chống Đạn) | U28: =CSG!E41 -> 500000000 | V28: =T28 -> Vinfast Lạc Hồng (Chống Đạn) | W28: =CSG!G41 -> 0 | X28: =V28 -> Vinfast Lạc Hồng (Chống Đạn) | Y28: =CSG!H41 -> 0 | Z28: =X28 -> Vinfast Lạc Hồng (Chống Đạn) | AA28: =CSG!F41 -> 200000000 | AB28: =N28 -> Vinfast Lạc Hồng (Chống Đạn) | AC28: =CSG!J41 -> 0 | AE28: =N28 -> Vinfast Lạc Hồng (Chống Đạn) | AF28: =H28 -> 0 | AM28: =AE28 -> Vinfast Lạc Hồng (Chống Đạn) | AN28: =CSG!Z41 -> 32640000000 | AP28: =AM28 -> Vinfast Lạc Hồng (Chống Đạn) | AQ28: =CSG!R41 -> Miễn phí sạc 02 năm tại VGreen | AR28: =AP28 -> Vinfast Lạc Hồng (Chống Đạn) | AS28: =CSG!S41 -> Miễn phí bãi đổ xe và ưu tiên hệ sinh thái VINGROUP | AT28: =AR28 -> Vinfast Lạc Hồng (Chống Đạn) | AU28: =CSG!T41 -> 0 | AV28: =AR28 -> Vinfast Lạc Hồng (Chống Đạn) | AW28: =CSG!U41 -> 0 | AX28: =AV28 -> Vinfast Lạc Hồng (Chống Đạn) | AY28: =CSG!V41 -> 0 | AZ28: =AX28 -> Vinfast Lạc Hồng (Chống Đạn) | BA28: =CSG!W41 -> 0 | BC28: =AZ28 -> Vinfast Lạc Hồng (Chống Đạn) | BD28: Thời gian nạp pin (10 - 70%) trong 35 phút | BE28: =BC28 -> Vinfast Lạc Hồng (Chống Đạn) | BF28: Công suất tối đa 340 kW/455 hp | BG28: =BE28 -> Vinfast Lạc Hồng (Chống Đạn) | BH28: Lazang 21 Inch | BI28: =BG28 -> Vinfast Lạc Hồng (Chống Đạn) | BJ28: Trang bị 11 túi khí | BK28: =BI28 -> Vinfast Lạc Hồng (Chống Đạn) | BL28: Quãng đường di chuyển dự kiến 450 Km
A29: =CSG!A42 -> ECVAN | B29: =CSG!B43 -> EC Van TC | C29: =CSG!C43 -> 285000000 | E29: =A29 -> ECVAN | F29: =B29 -> EC Van TC | H29: =G29-I29 -> 0 | M29: =E29 -> ECVAN | N29: =F29 -> EC Van TC | O29: =C29 -> 285000000 | P29: =CSG!D43 -> 11400000 | Q29: =CSG!G43 -> 0 | R29: =CSG!H43 -> 0 | S29: =CSG!I43 -> 0 | T29: =N29 -> EC Van TC | U29: =CSG!E43 -> 5000000 | V29: =T29 -> EC Van TC | W29: =CSG!G43 -> 0 | X29: =V29 -> EC Van TC | Y29: =CSG!I43 -> 0 | Z29: =N29 -> EC Van TC | AA29: =CSG!F42 -> 0 | AB29: =N29 -> EC Van TC | AC29: =CSG!J43 -> 0 | AD29: =M29 -> ECVAN | AE29: =N29 -> EC Van TC | AF29: =H29 -> 0 | AM29: =AE29 -> EC Van TC | AN29: =CSG!Z43 -> 273600000 | AP29: =AM29 -> EC Van TC | AQ29: =CSG!R43 -> Miễn phí sạc 02 năm tại VGreen | AR29: =AP29 -> EC Van TC | AS29: =CSG!S43 -> Miễn phí bãi đổ xe và ưu tiên hệ sinh thái VINGROUP | AT29: =AR29 -> EC Van TC | AU29: =CSG!T43 -> 0 | AV29: =AR29 -> EC Van TC | AW29: =CSG!U43 -> 0 | AX29: =AV29 -> EC Van TC | AY29: =CSG!V43 -> 0 | AZ29: =AX29 -> EC Van TC | BA29: =CSG!W43 -> 0 | BC29: =AZ29 -> EC Van TC | BE29: =BC29 -> EC Van TC | BG29: =BE29 -> EC Van TC | BI29: =BG29 -> EC Van TC | BK29: =BI29 -> EC Van TC
B30: =CSG!B44 -> EC Van NC | C30: =CSG!C44 -> 305000000 | F30: =B30 -> EC Van NC | N30: =F30 -> EC Van NC | O30: =C30 -> 305000000 | P30: =CSG!D44 -> 12200000 | Q30: =CSG!G44 -> 0 | R30: =CSG!H44 -> 0 | S30: =CSG!I44 -> 0 | T30: =N30 -> EC Van NC | U30: =CSG!E44 -> 5000000 | V30: =T30 -> EC Van NC | W30: =CSG!G44 -> 0 | X30: =V30 -> EC Van NC | Y30: =CSG!I44 -> 0 | Z30: =N30 -> EC Van NC | AA30: =CSG!F43 -> 0 | AB30: =N30 -> EC Van NC | AC30: =CSG!J44 -> 0 | AE30: =N30 -> EC Van NC | AF30: =H30 -> 0 | AM30: =AE30 -> EC Van NC | AN30: =CSG!Z44 -> 292800000 | AP30: =AM30 -> EC Van NC | AQ30: =CSG!R44 -> Miễn phí sạc 02 năm tại VGreen | AR30: =AP30 -> EC Van NC | AS30: =CSG!S44 -> Miễn phí bãi đổ xe và ưu tiên hệ sinh thái VINGROUP | AT30: =AR30 -> EC Van NC | AU30: =CSG!T44 -> 0 | AV30: =AR30 -> EC Van NC | AW30: =CSG!U44 -> 0 | AX30: =AV30 -> EC Van NC | AY30: =CSG!V44 -> 0 | AZ30: =AX30 -> EC Van NC | BA30: =CSG!W44 -> 0 | BC30: =AZ30 -> EC Van NC | BE30: =BC30 -> EC Van NC | BG30: =BE30 -> EC Van NC | BI30: =BG30 -> EC Van NC | BK30: =BI30 -> EC Van NC
A35: =A3 -> VF.3 | B35: #VALUE!
A36: =A5 -> HERIO | B36: #VALUE!
A37: =A6 -> VF.5 | B37: #VALUE!
A38: =A8 -> NERIO | B38: #VALUE!
A39: =A9 -> VF.6 | B39: #VALUE!
A40: =A13 -> LIMO | B40: #VALUE!
A41: =A14 -> VF.7 | B41: #VALUE!
A42: =A19 -> VF.8 | B42: #VALUE!
A43: =A22 -> VF.9 | B43: #VALUE!
A44: LAC.HONG | B44: #VALUE!
A45: =A29 -> ECVAN | B45: #VALUE!

Sheet DVDK
A1: BẢNG GIÁ DVDK VINFAST 2025
A2: STT | B2: Địa điểm đăng ký | C2: =B2 -> Địa điểm đăng ký | D2: DỊCH VỤ KHÁCH HÀNG | G2: GHI CHÚ | H2: SỐ KM
A4: [HCM] | B4: VNEID TOÀN TRÌNH - KHÔNG XE | C4: =CONCATENATE($A$4," ",B4) -> [HCM] VNEID TOÀN TRÌNH - KHÔNG XE | D4: 3000000 | E4: =IF(ISNUMBER(SEARCH($I$4,C4)),MAX($E$3:E3)+1,"") | F4: =C4 -> [HCM] VNEID TOÀN TRÌNH - KHÔNG XE | I4: ='BG New'!N9 -> Hưng | J4: =IFERROR(INDEX(C4:C399,MATCH(ROW()-3,E4:E399,0),1),"") -> [Hà Tĩnh] Hưng Khê | K4: =VLOOKUP(J4,CPDK,2,0) -> 10000000 | L4: =VLOOKUP(J4,F4:G399,2,0) -> 0
B5: VNEID - TRUYỀN THỐNG (KHÔNG XE) | C5: =CONCATENATE($A$4," ",B5) -> [HCM] VNEID - TRUYỀN THỐNG (KHÔNG XE) | D5: 3000000 | E5: =IF(ISNUMBER(SEARCH($I$4,C5)),MAX($E$3:E4)+1,"") | F5: =C5 -> [HCM] VNEID - TRUYỀN THỐNG (KHÔNG XE) | J5: =IFERROR(INDEX(C5:C400,MATCH(ROW()-3,E5:E400,0),1),"") | K5: =VLOOKUP(J5,CPDK,2,0) -> #N/A | L5: =VLOOKUP(J5,F5:G400,2,0) -> #N/A
B6: PHÍ CÀ VẸT NHANH | C6: =CONCATENATE($A$4," ",B6) -> [HCM] PHÍ CÀ VẸT NHANH | D6: 1500000 | E6: =IF(ISNUMBER(SEARCH($I$4,C6)),MAX($E$3:E5)+1,"") | F6: =C6 -> [HCM] PHÍ CÀ VẸT NHANH | J6: =IFERROR(INDEX(C6:C401,MATCH(ROW()-3,E6:E401,0),1),"") | K6: =VLOOKUP(J6,CPDK,2,0) -> #N/A | L6: =VLOOKUP(J6,F6:G401,2,0) -> #N/A
C7: =CONCATENATE($A$4," ",B7) -> [HCM] | E7: =IF(ISNUMBER(SEARCH($I$4,C7)),MAX($E$3:E6)+1,"") | F7: =C7 -> [HCM] | J7: =IFERROR(INDEX(C7:C402,MATCH(ROW()-3,E7:E402,0),1),"") | K7: =VLOOKUP(J7,CPDK,2,0) -> #N/A | L7: =VLOOKUP(J7,F7:G402,2,0) -> #N/A
C8: =CONCATENATE($A$4," ",B8) -> [HCM] | E8: =IF(ISNUMBER(SEARCH($I$4,C8)),MAX($E$3:E7)+1,"") | F8: =C8 -> [HCM] | J8: =IFERROR(INDEX(C8:C403,MATCH(ROW()-3,E8:E403,0),1),"") | K8: =VLOOKUP(J8,CPDK,2,0) -> #N/A | L8: =VLOOKUP(J8,F8:G403,2,0) -> #N/A
C9: =CONCATENATE($A$4," ",B9) -> [HCM] | E9: =IF(ISNUMBER(SEARCH($I$4,C9)),MAX($E$3:E8)+1,"") | F9: =C9 -> [HCM] | J9: =IFERROR(INDEX(C9:C404,MATCH(ROW()-3,E9:E404,0),1),"") | K9: =VLOOKUP(J9,CPDK,2,0) -> #N/A | L9: =VLOOKUP(J9,F9:G404,2,0) -> #N/A
A10: [Bình Dương] | B10: VNEID - TOÀN TRÌNH (KHÔNG XE) | C10: =CONCATENATE($A$10," ",B10) -> [Bình Dương] VNEID - TOÀN TRÌNH (KHÔNG XE) | D10: 3000000 | E10: =IF(ISNUMBER(SEARCH($I$4,C10)),MAX($E$3:E9)+1,"") | F10: =C10 -> [Bình Dương] VNEID - TOÀN TRÌNH (KHÔNG XE) | J10: =IFERROR(INDEX(C10:C405,MATCH(ROW()-3,E10:E405,0),1),"") | K10: =VLOOKUP(J10,CPDK,2,0) -> #N/A | L10: =VLOOKUP(J10,F10:G405,2,0) -> #N/A
B11: VNEID - TRUYỀN THỐNG (CÓ XE) | C11: =CONCATENATE($A$10," ",B11) -> [Bình Dương] VNEID - TRUYỀN THỐNG (CÓ XE) | D11: 3100000 | E11: =IF(ISNUMBER(SEARCH($I$4,C11)),MAX($E$3:E10)+1,"") | F11: =C11 -> [Bình Dương] VNEID - TRUYỀN THỐNG (CÓ XE) | J11: =IFERROR(INDEX(C11:C406,MATCH(ROW()-3,E11:E406,0),1),"") | K11: =VLOOKUP(J11,CPDK,2,0) -> #N/A | L11: =VLOOKUP(J11,F11:G406,2,0) -> #N/A
B12: PHÍ CÀ VẸT NHANH | C12: =CONCATENATE($A$10," ",B12) -> [Bình Dương] PHÍ CÀ VẸT NHANH | E12: =IF(ISNUMBER(SEARCH($I$4,C12)),MAX($E$3:E11)+1,"") | F12: =C12 -> [Bình Dương] PHÍ CÀ VẸT NHANH | J12: =IFERROR(INDEX(C12:C407,MATCH(ROW()-3,E12:E407,0),1),"") | K12: =VLOOKUP(J12,CPDK,2,0) -> #N/A | L12: =VLOOKUP(J12,F12:G407,2,0) -> #N/A
C13: =CONCATENATE($A$10," ",B13) -> [Bình Dương] | E13: =IF(ISNUMBER(SEARCH($I$4,C13)),MAX($E$3:E12)+1,"") | F13: =C13 -> [Bình Dương] | J13: =IFERROR(INDEX(C13:C408,MATCH(ROW()-3,E13:E408,0),1),"") | K13: =VLOOKUP(J13,CPDK,2,0) -> #N/A | L13: =VLOOKUP(J13,F13:G408,2,0) -> #N/A
C14: =CONCATENATE($A$10," ",B14) -> [Bình Dương] | E14: =IF(ISNUMBER(SEARCH($I$4,C14)),MAX($E$3:E13)+1,"") | F14: =C14 -> [Bình Dương] | J14: =IFERROR(INDEX(C14:C409,MATCH(ROW()-3,E14:E409,0),1),"") | K14: =VLOOKUP(J14,CPDK,2,0) -> #N/A | L14: =VLOOKUP(J14,F14:G409,2,0) -> #N/A
C15: =CONCATENATE($A$10," ",B15) -> [Bình Dương] | E15: =IF(ISNUMBER(SEARCH($I$4,C15)),MAX($E$3:E14)+1,"") | F15: =C15 -> [Bình Dương] | J15: =IFERROR(INDEX(C15:C410,MATCH(ROW()-3,E15:E410,0),1),"") | K15: =VLOOKUP(J15,CPDK,2,0) -> #N/A | L15: =VLOOKUP(J15,F15:G410,2,0) -> #N/A
C16: =CONCATENATE($A$10," ",B16) -> [Bình Dương] | E16: =IF(ISNUMBER(SEARCH($I$4,C16)),MAX($E$3:E15)+1,"") | F16: =C16 -> [Bình Dương] | J16: =IFERROR(INDEX(C16:C411,MATCH(ROW()-3,E16:E411,0),1),"") | K16: =VLOOKUP(J16,CPDK,2,0) -> #N/A | L16: =VLOOKUP(J16,F16:G411,2,0) -> #N/A
C17: =CONCATENATE($A$10," ",B17) -> [Bình Dương] | E17: =IF(ISNUMBER(SEARCH($I$4,C17)),MAX($E$3:E16)+1,"") | F17: =C17 -> [Bình Dương] | J17: =IFERROR(INDEX(C17:C412,MATCH(ROW()-3,E17:E412,0),1),"") | K17: =VLOOKUP(J17,CPDK,2,0) -> #N/A | L17: =VLOOKUP(J17,F17:G412,2,0) -> #N/A
C18: =CONCATENATE($A$10," ",B18) -> [Bình Dương] | E18: =IF(ISNUMBER(SEARCH($I$4,C18)),MAX($E$3:E17)+1,"") | F18: =C18 -> [Bình Dương] | J18: =IFERROR(INDEX(C18:C413,MATCH(ROW()-3,E18:E413,0),1),"") | K18: =VLOOKUP(J18,CPDK,2,0) -> #N/A | L18: =VLOOKUP(J18,F18:G413,2,0) -> #N/A
A19: [Đồng Nai] | B19: VNEID - TOÀN TRÌNH (KHÔNG XE) | C19: =CONCATENATE($A$19," ",B19) -> [Đồng Nai] VNEID - TOÀN TRÌNH (KHÔNG XE) | D19: 3200000 | E19: =IF(ISNUMBER(SEARCH($I$4,C19)),MAX($E$3:E18)+1,"") | F19: =C19 -> [Đồng Nai] VNEID - TOÀN TRÌNH (KHÔNG XE) | J19: =IFERROR(INDEX(C19:C414,MATCH(ROW()-3,E19:E414,0),1),"") | K19: =VLOOKUP(J19,CPDK,2,0) -> #N/A | L19: =VLOOKUP(J19,F19:G414,2,0) -> #N/A
B20: VNEID - TRUYỀN THỐNG (CÓ XE) | C20: =CONCATENATE($A$19," ",B20) -> [Đồng Nai] VNEID - TRUYỀN THỐNG (CÓ XE) | D20: 3400000 | E20: =IF(ISNUMBER(SEARCH($I$4,C20)),MAX($E$3:E19)+1,"") | F20: =C20 -> [Đồng Nai] VNEID - TRUYỀN THỐNG (CÓ XE) | J20: =IFERROR(INDEX(C20:C415,MATCH(ROW()-3,E20:E415,0),1),"") | K20: =VLOOKUP(J20,CPDK,2,0) -> #N/A | L20: =VLOOKUP(J20,F20:G415,2,0) -> #N/A
B21: PHÍ CÀ VẸT NHANH | C21: =CONCATENATE($A$19," ",B21) -> [Đồng Nai] PHÍ CÀ VẸT NHANH | D21: 1500000 | E21: =IF(ISNUMBER(SEARCH($I$4,C21)),MAX($E$3:E20)+1,"") | F21: =C21 -> [Đồng Nai] PHÍ CÀ VẸT NHANH | J21: =IFERROR(INDEX(C21:C416,MATCH(ROW()-3,E21:E416,0),1),"") | K21: =VLOOKUP(J21,CPDK,2,0) -> #N/A | L21: =VLOOKUP(J21,F21:G416,2,0) -> #N/A
C22: =CONCATENATE($A$19," ",B22) -> [Đồng Nai] | E22: =IF(ISNUMBER(SEARCH($I$4,C22)),MAX($E$3:E21)+1,"") | F22: =C22 -> [Đồng Nai] | J22: =IFERROR(INDEX(C22:C417,MATCH(ROW()-3,E22:E417,0),1),"") | K22: =VLOOKUP(J22,CPDK,2,0) -> #N/A | L22: =VLOOKUP(J22,F22:G417,2,0) -> #N/A
C23: =CONCATENATE($A$19," ",B23) -> [Đồng Nai] | E23: =IF(ISNUMBER(SEARCH($I$4,C23)),MAX($E$3:E22)+1,"") | F23: =C23 -> [Đồng Nai] | J23: =IFERROR(INDEX(C23:C418,MATCH(ROW()-3,E23:E418,0),1),"") | K23: =VLOOKUP(J23,CPDK,2,0) -> #N/A | L23: =VLOOKUP(J23,F23:G418,2,0) -> #N/A
C24: =CONCATENATE($A$19," ",B24) -> [Đồng Nai] | E24: =IF(ISNUMBER(SEARCH($I$4,C24)),MAX($E$3:E23)+1,"") | F24: =C24 -> [Đồng Nai] | J24: =IFERROR(INDEX(C24:C419,MATCH(ROW()-3,E24:E419,0),1),"") | K24: =VLOOKUP(J24,CPDK,2,0) -> #N/A | L24: =VLOOKUP(J24,F24:G419,2,0) -> #N/A
C25: =CONCATENATE($A$19," ",B25) -> [Đồng Nai] | E25: =IF(ISNUMBER(SEARCH($I$4,C25)),MAX($E$3:E24)+1,"") | F25: =C25 -> [Đồng Nai] | J25: =IFERROR(INDEX(C25:C420,MATCH(ROW()-3,E25:E420,0),1),"") | K25: =VLOOKUP(J25,CPDK,2,0) -> #N/A | L25: =VLOOKUP(J25,F25:G420,2,0) -> #N/A
C26: =CONCATENATE($A$19," ",B26) -> [Đồng Nai] | E26: =IF(ISNUMBER(SEARCH($I$4,C26)),MAX($E$3:E25)+1,"") | F26: =C26 -> [Đồng Nai] | J26: =IFERROR(INDEX(C26:C421,MATCH(ROW()-3,E26:E421,0),1),"") | K26: =VLOOKUP(J26,CPDK,2,0) -> #N/A | L26: =VLOOKUP(J26,F26:G421,2,0) -> #N/A
C27: =CONCATENATE($A$19," ",B27) -> [Đồng Nai] | E27: =IF(ISNUMBER(SEARCH($I$4,C27)),MAX($E$3:E26)+1,"") | F27: =C27 -> [Đồng Nai] | J27: =IFERROR(INDEX(C27:C422,MATCH(ROW()-3,E27:E422,0),1),"") | K27: =VLOOKUP(J27,CPDK,2,0) -> #N/A | L27: =VLOOKUP(J27,F27:G422,2,0) -> #N/A
C28: =CONCATENATE($A$19," ",B28) -> [Đồng Nai] | E28: =IF(ISNUMBER(SEARCH($I$4,C28)),MAX($E$3:E27)+1,"") | F28: =C28 -> [Đồng Nai] | J28: =IFERROR(INDEX(C28:C423,MATCH(ROW()-3,E28:E423,0),1),"") | K28: =VLOOKUP(J28,CPDK,2,0) -> #N/A | L28: =VLOOKUP(J28,F28:G423,2,0) -> #N/A
C29: =CONCATENATE($A$19," ",B29) -> [Đồng Nai] | E29: =IF(ISNUMBER(SEARCH($I$4,C29)),MAX($E$3:E28)+1,"") | F29: =C29 -> [Đồng Nai] | J29: =IFERROR(INDEX(C29:C424,MATCH(ROW()-3,E29:E424,0),1),"") | K29: =VLOOKUP(J29,CPDK,2,0) -> #N/A | L29: =VLOOKUP(J29,F29:G424,2,0) -> #N/A
A30: [Bình Phước] | B30: VNEID - TOÀN TRÌNH (KHÔNG XE) | C30: =CONCATENATE($A$30," ",B30) -> [Bình Phước] VNEID - TOÀN TRÌNH (KHÔNG XE) | D30: 3700000 | E30: =IF(ISNUMBER(SEARCH($I$4,C30)),MAX($E$3:E29)+1,"") | F30: =C30 -> [Bình Phước] VNEID - TOÀN TRÌNH (KHÔNG XE) | J30: =IFERROR(INDEX(C30:C425,MATCH(ROW()-3,E30:E425,0),1),"") | K30: =VLOOKUP(J30,CPDK,2,0) -> #N/A | L30: =VLOOKUP(J30,F30:G425,2,0) -> #N/A
B31: VNEID - TRUYỀN THỐNG (CÓ XE) | C31: =CONCATENATE($A$30," ",B31) -> [Bình Phước] VNEID - TRUYỀN THỐNG (CÓ XE) | D31: 3900000 | E31: =IF(ISNUMBER(SEARCH($I$4,C31)),MAX($E$3:E30)+1,"") | F31: =C31 -> [Bình Phước] VNEID - TRUYỀN THỐNG (CÓ XE) | J31: =IFERROR(INDEX(C31:C426,MATCH(ROW()-3,E31:E426,0),1),"") | K31: =VLOOKUP(J31,CPDK,2,0) -> #N/A | L31: =VLOOKUP(J31,F31:G426,2,0) -> #N/A
B32: PHÍ CÀ VẸT NHANH | C32: =CONCATENATE($A$30," ",B32) -> [Bình Phước] PHÍ CÀ VẸT NHANH | D32: 1500000 | E32: =IF(ISNUMBER(SEARCH($I$4,C32)),MAX($E$3:E31)+1,"") | F32: =C32 -> [Bình Phước] PHÍ CÀ VẸT NHANH | J32: =IFERROR(INDEX(C32:C427,MATCH(ROW()-3,E32:E427,0),1),"") | K32: =VLOOKUP(J32,CPDK,2,0) -> #N/A | L32: =VLOOKUP(J32,F32:G427,2,0) -> #N/A
C33: =CONCATENATE($A$30," ",B33) -> [Bình Phước] | E33: =IF(ISNUMBER(SEARCH($I$4,C33)),MAX($E$3:E32)+1,"") | F33: =C33 -> [Bình Phước] | J33: =IFERROR(INDEX(C33:C428,MATCH(ROW()-3,E33:E428,0),1),"") | K33: =VLOOKUP(J33,CPDK,2,0) -> #N/A | L33: =VLOOKUP(J33,F33:G428,2,0) -> #N/A
C34: =CONCATENATE($A$30," ",B34) -> [Bình Phước] | E34: =IF(ISNUMBER(SEARCH($I$4,C34)),MAX($E$3:E33)+1,"") | F34: =C34 -> [Bình Phước] | J34: =IFERROR(INDEX(C34:C429,MATCH(ROW()-3,E34:E429,0),1),"") | K34: =VLOOKUP(J34,CPDK,2,0) -> #N/A | L34: =VLOOKUP(J34,F34:G429,2,0) -> #N/A
C35: =CONCATENATE($A$30," ",B35) -> [Bình Phước] | E35: =IF(ISNUMBER(SEARCH($I$4,C35)),MAX($E$3:E34)+1,"") | F35: =C35 -> [Bình Phước] | J35: =IFERROR(INDEX(C35:C430,MATCH(ROW()-3,E35:E430,0),1),"") | K35: =VLOOKUP(J35,CPDK,2,0) -> #N/A | L35: =VLOOKUP(J35,F35:G430,2,0) -> #N/A
C36: =CONCATENATE($A$30," ",B36) -> [Bình Phước] | E36: =IF(ISNUMBER(SEARCH($I$4,C36)),MAX($E$3:E35)+1,"") | F36: =C36 -> [Bình Phước] | J36: =IFERROR(INDEX(C36:C431,MATCH(ROW()-3,E36:E431,0),1),"") | K36: =VLOOKUP(J36,CPDK,2,0) -> #N/A | L36: =VLOOKUP(J36,F36:G431,2,0) -> #N/A
C37: =CONCATENATE($A$30," ",B37) -> [Bình Phước] | E37: =IF(ISNUMBER(SEARCH($I$4,C37)),MAX($E$3:E36)+1,"") | F37: =C37 -> [Bình Phước] | J37: =IFERROR(INDEX(C37:C432,MATCH(ROW()-3,E37:E432,0),1),"") | K37: =VLOOKUP(J37,CPDK,2,0) -> #N/A | L37: =VLOOKUP(J37,F37:G432,2,0) -> #N/A
C38: =CONCATENATE($A$30," ",B38) -> [Bình Phước] | E38: =IF(ISNUMBER(SEARCH($I$4,C38)),MAX($E$3:E37)+1,"") | F38: =C38 -> [Bình Phước] | J38: =IFERROR(INDEX(C38:C433,MATCH(ROW()-3,E38:E433,0),1),"") | K38: =VLOOKUP(J38,CPDK,2,0) -> #N/A | L38: =VLOOKUP(J38,F38:G433,2,0) -> #N/A
C39: =CONCATENATE($A$30," ",B39) -> [Bình Phước] | E39: =IF(ISNUMBER(SEARCH($I$4,C39)),MAX($E$3:E38)+1,"") | F39: =C39 -> [Bình Phước] | J39: =IFERROR(INDEX(C39:C434,MATCH(ROW()-3,E39:E434,0),1),"") | K39: =VLOOKUP(J39,CPDK,2,0) -> #N/A | L39: =VLOOKUP(J39,F39:G434,2,0) -> #N/A
C40: =CONCATENATE($A$30," ",B40) -> [Bình Phước] | E40: =IF(ISNUMBER(SEARCH($I$4,C40)),MAX($E$3:E39)+1,"") | F40: =C40 -> [Bình Phước] | J40: =IFERROR(INDEX(C40:C435,MATCH(ROW()-3,E40:E435,0),1),"") | K40: =VLOOKUP(J40,CPDK,2,0) -> #N/A | L40: =VLOOKUP(J40,F40:G435,2,0) -> #N/A
A41: [Vũng Tàu] | B41: VNEID - TOÀN TRÌNH (KHÔNG XE) | C41: =CONCATENATE($A$41," ",B41) -> [Vũng Tàu] VNEID - TOÀN TRÌNH (KHÔNG XE) | D41: 3700000 | E41: =IF(ISNUMBER(SEARCH($I$4,C41)),MAX($E$3:E40)+1,"") | F41: =C41 -> [Vũng Tàu] VNEID - TOÀN TRÌNH (KHÔNG XE) | J41: =IFERROR(INDEX(C41:C436,MATCH(ROW()-3,E41:E436,0),1),"") | K41: =VLOOKUP(J41,CPDK,2,0) -> #N/A | L41: =VLOOKUP(J41,F41:G436,2,0) -> #N/A
B42: VNEID - TRUYỀN THỐNG (CÓ XE) | C42: =CONCATENATE($A$41," ",B42) -> [Vũng Tàu] VNEID - TRUYỀN THỐNG (CÓ XE) | D42: 3900000 | E42: =IF(ISNUMBER(SEARCH($I$4,C42)),MAX($E$3:E41)+1,"") | F42: =C42 -> [Vũng Tàu] VNEID - TRUYỀN THỐNG (CÓ XE) | J42: =IFERROR(INDEX(C42:C437,MATCH(ROW()-3,E42:E437,0),1),"") | K42: =VLOOKUP(J42,CPDK,2,0) -> #N/A | L42: =VLOOKUP(J42,F42:G437,2,0) -> #N/A
B43: PHÍ CÀ VẸT NHANH | C43: =CONCATENATE($A$41," ",B43) -> [Vũng Tàu] PHÍ CÀ VẸT NHANH | D43: 1500000 | E43: =IF(ISNUMBER(SEARCH($I$4,C43)),MAX($E$3:E42)+1,"") | F43: =C43 -> [Vũng Tàu] PHÍ CÀ VẸT NHANH | J43: =IFERROR(INDEX(C43:C438,MATCH(ROW()-3,E43:E438,0),1),"") | K43: =VLOOKUP(J43,CPDK,2,0) -> #N/A | L43: =VLOOKUP(J43,F43:G438,2,0) -> #N/A
C44: =CONCATENATE($A$41," ",B44) -> [Vũng Tàu] | E44: =IF(ISNUMBER(SEARCH($I$4,C44)),MAX($E$3:E43)+1,"") | F44: =C44 -> [Vũng Tàu] | J44: =IFERROR(INDEX(C44:C439,MATCH(ROW()-3,E44:E439,0),1),"") | K44: =VLOOKUP(J44,CPDK,2,0) -> #N/A | L44: =VLOOKUP(J44,F44:G439,2,0) -> #N/A
C45: =CONCATENATE($A$41," ",B45) -> [Vũng Tàu] | E45: =IF(ISNUMBER(SEARCH($I$4,C45)),MAX($E$3:E44)+1,"") | F45: =C45 -> [Vũng Tàu] | J45: =IFERROR(INDEX(C45:C440,MATCH(ROW()-3,E45:E440,0),1),"") | K45: =VLOOKUP(J45,CPDK,2,0) -> #N/A | L45: =VLOOKUP(J45,F45:G440,2,0) -> #N/A
C46: =CONCATENATE($A$41," ",B46) -> [Vũng Tàu] | E46: =IF(ISNUMBER(SEARCH($I$4,C46)),MAX($E$3:E45)+1,"") | F46: =C46 -> [Vũng Tàu] | J46: =IFERROR(INDEX(C46:C441,MATCH(ROW()-3,E46:E441,0),1),"") | K46: =VLOOKUP(J46,CPDK,2,0) -> #N/A | L46: =VLOOKUP(J46,F46:G441,2,0) -> #N/A
C47: =CONCATENATE($A$41," ",B47) -> [Vũng Tàu] | E47: =IF(ISNUMBER(SEARCH($I$4,C47)),MAX($E$3:E46)+1,"") | F47: =C47 -> [Vũng Tàu] | J47: =IFERROR(INDEX(C47:C442,MATCH(ROW()-3,E47:E442,0),1),"") | K47: =VLOOKUP(J47,CPDK,2,0) -> #N/A | L47: =VLOOKUP(J47,F47:G442,2,0) -> #N/A
C48: =CONCATENATE($A$41," ",B48) -> [Vũng Tàu] | E48: =IF(ISNUMBER(SEARCH($I$4,C48)),MAX($E$3:E47)+1,"") | F48: =C48 -> [Vũng Tàu] | J48: =IFERROR(INDEX(C48:C443,MATCH(ROW()-3,E48:E443,0),1),"") | K48: =VLOOKUP(J48,CPDK,2,0) -> #N/A | L48: =VLOOKUP(J48,F48:G443,2,0) -> #N/A
A49: [Tây Ninh] | B49: VNEID - TOÀN TRÌNH (KHÔNG XE) | C49: =CONCATENATE($A$49," ",B49) -> [Tây Ninh] VNEID - TOÀN TRÌNH (KHÔNG XE) | D49: 3500000 | E49: =IF(ISNUMBER(SEARCH($I$4,C49)),MAX($E$3:E48)+1,"") | F49: =C49 -> [Tây Ninh] VNEID - TOÀN TRÌNH (KHÔNG XE) | J49: =IFERROR(INDEX(C49:C444,MATCH(ROW()-3,E49:E444,0),1),"") | K49: =VLOOKUP(J49,CPDK,2,0) -> #N/A | L49: =VLOOKUP(J49,F49:G444,2,0) -> #N/A
B50: VNEID - TRUYỀN THỐNG (CÓ XE) | C50: =CONCATENATE($A$49," ",B50) -> [Tây Ninh] VNEID - TRUYỀN THỐNG (CÓ XE) | D50: 3800000 | E50: =IF(ISNUMBER(SEARCH($I$4,C50)),MAX($E$3:E49)+1,"") | F50: =C50 -> [Tây Ninh] VNEID - TRUYỀN THỐNG (CÓ XE) | J50: =IFERROR(INDEX(C50:C445,MATCH(ROW()-3,E50:E445,0),1),"") | K50: =VLOOKUP(J50,CPDK,2,0) -> #N/A | L50: =VLOOKUP(J50,F50:G445,2,0) -> #N/A
B51: PHÍ CÀ VẸT NHANH | C51: =CONCATENATE($A$49," ",B51) -> [Tây Ninh] PHÍ CÀ VẸT NHANH | D51: 1500000 | E51: =IF(ISNUMBER(SEARCH($I$4,C51)),MAX($E$3:E50)+1,"") | F51: =C51 -> [Tây Ninh] PHÍ CÀ VẸT NHANH | J51: =IFERROR(INDEX(C51:C446,MATCH(ROW()-3,E51:E446,0),1),"") | K51: =VLOOKUP(J51,CPDK,2,0) -> #N/A | L51: =VLOOKUP(J51,F51:G446,2,0) -> #N/A
C52: =CONCATENATE($A$49," ",B52) -> [Tây Ninh] | E52: =IF(ISNUMBER(SEARCH($I$4,C52)),MAX($E$3:E51)+1,"") | F52: =C52 -> [Tây Ninh] | J52: =IFERROR(INDEX(C52:C447,MATCH(ROW()-3,E52:E447,0),1),"") | K52: =VLOOKUP(J52,CPDK,2,0) -> #N/A | L52: =VLOOKUP(J52,F52:G447,2,0) -> #N/A
C53: =CONCATENATE($A$49," ",B53) -> [Tây Ninh] | E53: =IF(ISNUMBER(SEARCH($I$4,C53)),MAX($E$3:E52)+1,"") | F53: =C53 -> [Tây Ninh] | J53: =IFERROR(INDEX(C53:C448,MATCH(ROW()-3,E53:E448,0),1),"") | K53: =VLOOKUP(J53,CPDK,2,0) -> #N/A | L53: =VLOOKUP(J53,F53:G448,2,0) -> #N/A
C54: =CONCATENATE($A$49," ",B54) -> [Tây Ninh] | E54: =IF(ISNUMBER(SEARCH($I$4,C54)),MAX($E$3:E53)+1,"") | F54: =C54 -> [Tây Ninh] | J54: =IFERROR(INDEX(C54:C449,MATCH(ROW()-3,E54:E449,0),1),"") | K54: =VLOOKUP(J54,CPDK,2,0) -> #N/A | L54: =VLOOKUP(J54,F54:G449,2,0) -> #N/A
C55: =CONCATENATE($A$49," ",B55) -> [Tây Ninh] | E55: =IF(ISNUMBER(SEARCH($I$4,C55)),MAX($E$3:E54)+1,"") | F55: =C55 -> [Tây Ninh] | J55: =IFERROR(INDEX(C55:C450,MATCH(ROW()-3,E55:E450,0),1),"") | K55: =VLOOKUP(J55,CPDK,2,0) -> #N/A | L55: =VLOOKUP(J55,F55:G450,2,0) -> #N/A
C56: =CONCATENATE($A$49," ",B56) -> [Tây Ninh] | E56: =IF(ISNUMBER(SEARCH($I$4,C56)),MAX($E$3:E55)+1,"") | F56: =C56 -> [Tây Ninh] | J56: =IFERROR(INDEX(C56:C451,MATCH(ROW()-3,E56:E451,0),1),"") | K56: =VLOOKUP(J56,CPDK,2,0) -> #N/A | L56: =VLOOKUP(J56,F56:G451,2,0) -> #N/A
C57: =CONCATENATE($A$49," ",B57) -> [Tây Ninh] | E57: =IF(ISNUMBER(SEARCH($I$4,C57)),MAX($E$3:E56)+1,"") | F57: =C57 -> [Tây Ninh] | J57: =IFERROR(INDEX(C57:C452,MATCH(ROW()-3,E57:E452,0),1),"") | K57: =VLOOKUP(J57,CPDK,2,0) -> #N/A | L57: =VLOOKUP(J57,F57:G452,2,0) -> #N/A
A58: [Đắk Lắk] | B58: VNEID - TOÀN TRÌNH (KHÔNG XE) | C58: =CONCATENATE($A$58," ",B58) -> [Đắk Lắk] VNEID - TOÀN TRÌNH (KHÔNG XE) | D58: 5000000 | E58: =IF(ISNUMBER(SEARCH($I$4,C58)),MAX($E$3:E57)+1,"") | F58: =C58 -> [Đắk Lắk] VNEID - TOÀN TRÌNH (KHÔNG XE) | J58: =IFERROR(INDEX(C58:C453,MATCH(ROW()-3,E58:E453,0),1),"") | K58: =VLOOKUP(J58,CPDK,2,0) -> #N/A | L58: =VLOOKUP(J58,F58:G453,2,0) -> #N/A
B59: VNEID - TRUYỀN THỐNG (CÓ XE) | C59: =CONCATENATE($A$58," ",B59) -> [Đắk Lắk] VNEID - TRUYỀN THỐNG (CÓ XE) | D59: 6000000 | E59: =IF(ISNUMBER(SEARCH($I$4,C59)),MAX($E$3:E58)+1,"") | F59: =C59 -> [Đắk Lắk] VNEID - TRUYỀN THỐNG (CÓ XE) | J59: =IFERROR(INDEX(C59:C454,MATCH(ROW()-3,E59:E454,0),1),"") | K59: =VLOOKUP(J59,CPDK,2,0) -> #N/A | L59: =VLOOKUP(J59,F59:G454,2,0) -> #N/A
B60: PHÍ CÀ VẸT NHANH | C60: =CONCATENATE($A$58," ",B60) -> [Đắk Lắk] PHÍ CÀ VẸT NHANH | D60: 1500000 | E60: =IF(ISNUMBER(SEARCH($I$4,C60)),MAX($E$3:E59)+1,"") | F60: =C60 -> [Đắk Lắk] PHÍ CÀ VẸT NHANH | J60: =IFERROR(INDEX(C60:C455,MATCH(ROW()-3,E60:E455,0),1),"") | K60: =VLOOKUP(J60,CPDK,2,0) -> #N/A | L60: =VLOOKUP(J60,F60:G455,2,0) -> #N/A
A61: [Quy Nhơn] | B61: VNEID - TOÀN TRÌNH (KHÔNG XE) | C61: =CONCATENATE($A$61," ",B61) -> [Quy Nhơn] VNEID - TOÀN TRÌNH (KHÔNG XE) | D61: 6000000 | E61: =IF(ISNUMBER(SEARCH($I$4,C61)),MAX($E$3:E60)+1,"") | F61: =C61 -> [Quy Nhơn] VNEID - TOÀN TRÌNH (KHÔNG XE) | J61: =IFERROR(INDEX(C61:C456,MATCH(ROW()-3,E61:E456,0),1),"") | K61: =VLOOKUP(J61,CPDK,2,0) -> #N/A | L61: =VLOOKUP(J61,F61:G456,2,0) -> #N/A
B62: VNEID - TRUYỀN THỐNG (CÓ XE) | C62: =CONCATENATE($A$61," ",B62) -> [Quy Nhơn] VNEID - TRUYỀN THỐNG (CÓ XE) | D62: 6500000 | E62: =IF(ISNUMBER(SEARCH($I$4,C62)),MAX($E$3:E61)+1,"") | F62: =C62 -> [Quy Nhơn] VNEID - TRUYỀN THỐNG (CÓ XE) | J62: =IFERROR(INDEX(C62:C457,MATCH(ROW()-3,E62:E457,0),1),"") | K62: =VLOOKUP(J62,CPDK,2,0) -> #N/A | L62: =VLOOKUP(J62,F62:G457,2,0) -> #N/A
B63: PHÍ CÀ VẸT NHANH | C63: =CONCATENATE($A$61," ",B63) -> [Quy Nhơn] PHÍ CÀ VẸT NHANH | D63: 1000000 | E63: =IF(ISNUMBER(SEARCH($I$4,C63)),MAX($E$3:E62)+1,"") | F63: =C63 -> [Quy Nhơn] PHÍ CÀ VẸT NHANH | J63: =IFERROR(INDEX(C63:C458,MATCH(ROW()-3,E63:E458,0),1),"") | K63: =VLOOKUP(J63,CPDK,2,0) -> #N/A | L63: =VLOOKUP(J63,F63:G458,2,0) -> #N/A
C64: =CONCATENATE($A$58," ",B64) -> [Đắk Lắk] | E64: =IF(ISNUMBER(SEARCH($I$4,C64)),MAX($E$3:E63)+1,"") | F64: =C64 -> [Đắk Lắk] | J64: =IFERROR(INDEX(C64:C459,MATCH(ROW()-3,E64:E459,0),1),"") | K64: =VLOOKUP(J64,CPDK,2,0) -> #N/A | L64: =VLOOKUP(J64,F64:G459,2,0) -> #N/A
C65: =CONCATENATE($A$58," ",B65) -> [Đắk Lắk] | E65: =IF(ISNUMBER(SEARCH($I$4,C65)),MAX($E$3:E64)+1,"") | F65: =C65 -> [Đắk Lắk] | J65: =IFERROR(INDEX(C65:C460,MATCH(ROW()-3,E65:E460,0),1),"") | K65: =VLOOKUP(J65,CPDK,2,0) -> #N/A | L65: =VLOOKUP(J65,F65:G460,2,0) -> #N/A
C66: =CONCATENATE($A$58," ",B66) -> [Đắk Lắk] | E66: =IF(ISNUMBER(SEARCH($I$4,C66)),MAX($E$3:E65)+1,"") | F66: =C66 -> [Đắk Lắk] | J66: =IFERROR(INDEX(C66:C461,MATCH(ROW()-3,E66:E461,0),1),"") | K66: =VLOOKUP(J66,CPDK,2,0) -> #N/A | L66: =VLOOKUP(J66,F66:G461,2,0) -> #N/A
C67: =CONCATENATE($A$58," ",B67) -> [Đắk Lắk] | E67: =IF(ISNUMBER(SEARCH($I$4,C67)),MAX($E$3:E66)+1,"") | F67: =C67 -> [Đắk Lắk] | J67: =IFERROR(INDEX(C67:C462,MATCH(ROW()-3,E67:E462,0),1),"") | K67: =VLOOKUP(J67,CPDK,2,0) -> #N/A | L67: =VLOOKUP(J67,F67:G462,2,0) -> #N/A
C68: =CONCATENATE($A$58," ",B68) -> [Đắk Lắk] | E68: =IF(ISNUMBER(SEARCH($I$4,C68)),MAX($E$3:E67)+1,"") | F68: =C68 -> [Đắk Lắk] | J68: =IFERROR(INDEX(C68:C463,MATCH(ROW()-3,E68:E463,0),1),"") | K68: =VLOOKUP(J68,CPDK,2,0) -> #N/A | L68: =VLOOKUP(J68,F68:G463,2,0) -> #N/A
C69: =CONCATENATE($A$58," ",B69) -> [Đắk Lắk] | E69: =IF(ISNUMBER(SEARCH($I$4,C69)),MAX($E$3:E68)+1,"") | F69: =C69 -> [Đắk Lắk] | J69: =IFERROR(INDEX(C69:C464,MATCH(ROW()-3,E69:E464,0),1),"") | K69: =VLOOKUP(J69,CPDK,2,0) -> #N/A | L69: =VLOOKUP(J69,F69:G464,2,0) -> #N/A
C70: =CONCATENATE($A$58," ",B70) -> [Đắk Lắk] | E70: =IF(ISNUMBER(SEARCH($I$4,C70)),MAX($E$3:E69)+1,"") | F70: =C70 -> [Đắk Lắk] | J70: =IFERROR(INDEX(C70:C465,MATCH(ROW()-3,E70:E465,0),1),"") | K70: =VLOOKUP(J70,CPDK,2,0) -> #N/A | L70: =VLOOKUP(J70,F70:G465,2,0) -> #N/A
C71: =CONCATENATE($A$58," ",B71) -> [Đắk Lắk] | E71: =IF(ISNUMBER(SEARCH($I$4,C71)),MAX($E$3:E70)+1,"") | F71: =C71 -> [Đắk Lắk] | J71: =IFERROR(INDEX(C71:C466,MATCH(ROW()-3,E71:E466,0),1),"") | K71: =VLOOKUP(J71,CPDK,2,0) -> #N/A | L71: =VLOOKUP(J71,F71:G466,2,0) -> #N/A
C72: =CONCATENATE($A$58," ",B72) -> [Đắk Lắk] | E72: =IF(ISNUMBER(SEARCH($I$4,C72)),MAX($E$3:E71)+1,"") | F72: =C72 -> [Đắk Lắk] | J72: =IFERROR(INDEX(C72:C467,MATCH(ROW()-3,E72:E467,0),1),"") | K72: =VLOOKUP(J72,CPDK,2,0) -> #N/A | L72: =VLOOKUP(J72,F72:G467,2,0) -> #N/A
A73: [Đắk Nông] | B73: VNEID - TOÀN TRÌNH (KHÔNG XE) | C73: =CONCATENATE($A$73," ",B73) -> [Đắk Nông] VNEID - TOÀN TRÌNH (KHÔNG XE) | D73: 6500000 | E73: =IF(ISNUMBER(SEARCH($I$4,C73)),MAX($E$3:E72)+1,"") | F73: =C73 -> [Đắk Nông] VNEID - TOÀN TRÌNH (KHÔNG XE) | J73: =IFERROR(INDEX(C73:C468,MATCH(ROW()-3,E73:E468,0),1),"") | K73: =VLOOKUP(J73,CPDK,2,0) -> #N/A | L73: =VLOOKUP(J73,F73:G468,2,0) -> #N/A
B74: VNEID - TRUYỀN THỐNG (CÓ XE) | C74: =CONCATENATE($A$73," ",B74) -> [Đắk Nông] VNEID - TRUYỀN THỐNG (CÓ XE) | D74: 6800000 | E74: =IF(ISNUMBER(SEARCH($I$4,C74)),MAX($E$3:E73)+1,"") | F74: =C74 -> [Đắk Nông] VNEID - TRUYỀN THỐNG (CÓ XE) | J74: =IFERROR(INDEX(C74:C469,MATCH(ROW()-3,E74:E469,0),1),"") | K74: =VLOOKUP(J74,CPDK,2,0) -> #N/A | L74: =VLOOKUP(J74,F74:G469,2,0) -> #N/A
B75: PHÍ CÀ VẸT NHANH | C75: =CONCATENATE($A$73," ",B75) -> [Đắk Nông] PHÍ CÀ VẸT NHANH | D75: 1000000 | E75: =IF(ISNUMBER(SEARCH($I$4,C75)),MAX($E$3:E74)+1,"") | F75: =C75 -> [Đắk Nông] PHÍ CÀ VẸT NHANH | J75: =IFERROR(INDEX(C75:C470,MATCH(ROW()-3,E75:E470,0),1),"") | K75: =VLOOKUP(J75,CPDK,2,0) -> #N/A | L75: =VLOOKUP(J75,F75:G470,2,0) -> #N/A
C76: =CONCATENATE($A$73," ",B76) -> [Đắk Nông] | E76: =IF(ISNUMBER(SEARCH($I$4,C76)),MAX($E$3:E75)+1,"") | F76: =C76 -> [Đắk Nông] | J76: =IFERROR(INDEX(C76:C471,MATCH(ROW()-3,E76:E471,0),1),"") | K76: =VLOOKUP(J76,CPDK,2,0) -> #N/A | L76: =VLOOKUP(J76,F76:G471,2,0) -> #N/A
C77: =CONCATENATE($A$73," ",B77) -> [Đắk Nông] | E77: =IF(ISNUMBER(SEARCH($I$4,C77)),MAX($E$3:E76)+1,"") | F77: =C77 -> [Đắk Nông] | J77: =IFERROR(INDEX(C77:C472,MATCH(ROW()-3,E77:E472,0),1),"") | K77: =VLOOKUP(J77,CPDK,2,0) -> #N/A | L77: =VLOOKUP(J77,F77:G472,2,0) -> #N/A
C78: =CONCATENATE($A$73," ",B78) -> [Đắk Nông] | E78: =IF(ISNUMBER(SEARCH($I$4,C78)),MAX($E$3:E77)+1,"") | F78: =C78 -> [Đắk Nông] | J78: =IFERROR(INDEX(C78:C473,MATCH(ROW()-3,E78:E473,0),1),"") | K78: =VLOOKUP(J78,CPDK,2,0) -> #N/A | L78: =VLOOKUP(J78,F78:G473,2,0) -> #N/A
C79: =CONCATENATE($A$73," ",B79) -> [Đắk Nông] | E79: =IF(ISNUMBER(SEARCH($I$4,C79)),MAX($E$3:E78)+1,"") | F79: =C79 -> [Đắk Nông] | J79: =IFERROR(INDEX(C79:C474,MATCH(ROW()-3,E79:E474,0),1),"") | K79: =VLOOKUP(J79,CPDK,2,0) -> #N/A | L79: =VLOOKUP(J79,F79:G474,2,0) -> #N/A
C80: =CONCATENATE($A$73," ",B80) -> [Đắk Nông] | E80: =IF(ISNUMBER(SEARCH($I$4,C80)),MAX($E$3:E79)+1,"") | F80: =C80 -> [Đắk Nông] | J80: =IFERROR(INDEX(C80:C475,MATCH(ROW()-3,E80:E475,0),1),"") | K80: =VLOOKUP(J80,CPDK,2,0) -> #N/A | L80: =VLOOKUP(J80,F80:G475,2,0) -> #N/A
A81: [Gia Lai] | B81: VNEID - TOÀN TRÌNH (KHÔNG XE) | C81: =CONCATENATE($A$81," ",B81) -> [Gia Lai] VNEID - TOÀN TRÌNH (KHÔNG XE) | D81: 6500000 | E81: =IF(ISNUMBER(SEARCH($I$4,C81)),MAX($E$3:E80)+1,"") | F81: =C81 -> [Gia Lai] VNEID - TOÀN TRÌNH (KHÔNG XE) | J81: =IFERROR(INDEX(C81:C476,MATCH(ROW()-3,E81:E476,0),1),"") | K81: =VLOOKUP(J81,CPDK,2,0) -> #N/A | L81: =VLOOKUP(J81,F81:G476,2,0) -> #N/A
B82: VNEID - TRUYỀN THỐNG (CÓ XE) | C82: =CONCATENATE($A$81," ",B82) -> [Gia Lai] VNEID - TRUYỀN THỐNG (CÓ XE) | D82: 7500000 | E82: =IF(ISNUMBER(SEARCH($I$4,C82)),MAX($E$3:E81)+1,"") | F82: =C82 -> [Gia Lai] VNEID - TRUYỀN THỐNG (CÓ XE) | J82: =IFERROR(INDEX(C82:C477,MATCH(ROW()-3,E82:E477,0),1),"") | K82: =VLOOKUP(J82,CPDK,2,0) -> #N/A | L82: =VLOOKUP(J82,F82:G477,2,0) -> #N/A
B83: PHÍ CÀ VẸT NHANH | C83: =CONCATENATE($A$81," ",B83) -> [Gia Lai] PHÍ CÀ VẸT NHANH | D83: 1000000 | E83: =IF(ISNUMBER(SEARCH($I$4,C83)),MAX($E$3:E82)+1,"") | F83: =C83 -> [Gia Lai] PHÍ CÀ VẸT NHANH | J83: =IFERROR(INDEX(C83:C478,MATCH(ROW()-3,E83:E478,0),1),"") | K83: =VLOOKUP(J83,CPDK,2,0) -> #N/A | L83: =VLOOKUP(J83,F83:G478,2,0) -> #N/A
A84: [Cần Thơ] | B84: VNEID - TOÀN TRÌNH (KHÔNG XE) | C84: =CONCATENATE($A$84," ",B84) -> [Cần Thơ] VNEID - TOÀN TRÌNH (KHÔNG XE) | D84: 4500000 | E84: =IF(ISNUMBER(SEARCH($I$4,C84)),MAX($E$3:E83)+1,"") | F84: =C84 -> [Cần Thơ] VNEID - TOÀN TRÌNH (KHÔNG XE) | J84: =IFERROR(INDEX(C84:C479,MATCH(ROW()-3,E84:E479,0),1),"") | K84: =VLOOKUP(J84,CPDK,2,0) -> #N/A | L84: =VLOOKUP(J84,F84:G479,2,0) -> #N/A
B85: VNEID - TRUYỀN THỐNG (CÓ XE) | C85: =CONCATENATE($A$84," ",B85) -> [Cần Thơ] VNEID - TRUYỀN THỐNG (CÓ XE) | D85: 4800000 | E85: =IF(ISNUMBER(SEARCH($I$4,C85)),MAX($E$3:E84)+1,"") | F85: =C85 -> [Cần Thơ] VNEID - TRUYỀN THỐNG (CÓ XE) | J85: =IFERROR(INDEX(C85:C480,MATCH(ROW()-3,E85:E480,0),1),"") | K85: =VLOOKUP(J85,CPDK,2,0) -> #N/A | L85: =VLOOKUP(J85,F85:G480,2,0) -> #N/A
B86: PHÍ CÀ VẸT NHANH | C86: =CONCATENATE($A$84," ",B86) -> [Cần Thơ] PHÍ CÀ VẸT NHANH | D86: 1500000 | E86: =IF(ISNUMBER(SEARCH($I$4,C86)),MAX($E$3:E85)+1,"") | F86: =C86 -> [Cần Thơ] PHÍ CÀ VẸT NHANH | J86: =IFERROR(INDEX(C86:C481,MATCH(ROW()-3,E86:E481,0),1),"") | K86: =VLOOKUP(J86,CPDK,2,0) -> #N/A | L86: =VLOOKUP(J86,F86:G481,2,0) -> #N/A
C87: =CONCATENATE($A$84," ",B87) -> [Cần Thơ] | E87: =IF(ISNUMBER(SEARCH($I$4,C87)),MAX($E$3:E86)+1,"") | F87: =C87 -> [Cần Thơ] | J87: =IFERROR(INDEX(C87:C482,MATCH(ROW()-3,E87:E482,0),1),"") | K87: =VLOOKUP(J87,CPDK,2,0) -> #N/A | L87: =VLOOKUP(J87,F87:G482,2,0) -> #N/A
C88: =CONCATENATE($A$81," ",B88) -> [Gia Lai] | E88: =IF(ISNUMBER(SEARCH($I$4,C88)),MAX($E$3:E87)+1,"") | F88: =C88 -> [Gia Lai] | J88: =IFERROR(INDEX(C88:C483,MATCH(ROW()-3,E88:E483,0),1),"") | K88: =VLOOKUP(J88,CPDK,2,0) -> #N/A | L88: =VLOOKUP(J88,F88:G483,2,0) -> #N/A
C89: =CONCATENATE($A$81," ",B89) -> [Gia Lai] | E89: =IF(ISNUMBER(SEARCH($I$4,C89)),MAX($E$3:E88)+1,"") | F89: =C89 -> [Gia Lai] | J89: =IFERROR(INDEX(C89:C484,MATCH(ROW()-3,E89:E484,0),1),"") | K89: =VLOOKUP(J89,CPDK,2,0) -> #N/A | L89: =VLOOKUP(J89,F89:G484,2,0) -> #N/A
C90: =CONCATENATE($A$81," ",B90) -> [Gia Lai] | E90: =IF(ISNUMBER(SEARCH($I$4,C90)),MAX($E$3:E89)+1,"") | F90: =C90 -> [Gia Lai] | J90: =IFERROR(INDEX(C90:C485,MATCH(ROW()-3,E90:E485,0),1),"") | K90: =VLOOKUP(J90,CPDK,2,0) -> #N/A | L90: =VLOOKUP(J90,F90:G485,2,0) -> #N/A
C91: =CONCATENATE($A$81," ",B91) -> [Gia Lai] | E91: =IF(ISNUMBER(SEARCH($I$4,C91)),MAX($E$3:E90)+1,"") | F91: =C91 -> [Gia Lai] | J91: =IFERROR(INDEX(C91:C486,MATCH(ROW()-3,E91:E486,0),1),"") | K91: =VLOOKUP(J91,CPDK,2,0) -> #N/A | L91: =VLOOKUP(J91,F91:G486,2,0) -> #N/A
C92: =CONCATENATE($A$81," ",B92) -> [Gia Lai] | E92: =IF(ISNUMBER(SEARCH($I$4,C92)),MAX($E$3:E91)+1,"") | F92: =C92 -> [Gia Lai] | J92: =IFERROR(INDEX(C92:C487,MATCH(ROW()-3,E92:E487,0),1),"") | K92: =VLOOKUP(J92,CPDK,2,0) -> #N/A | L92: =VLOOKUP(J92,F92:G487,2,0) -> #N/A
C93: =CONCATENATE($A$81," ",B93) -> [Gia Lai] | E93: =IF(ISNUMBER(SEARCH($I$4,C93)),MAX($E$3:E92)+1,"") | F93: =C93 -> [Gia Lai] | J93: =IFERROR(INDEX(C93:C488,MATCH(ROW()-3,E93:E488,0),1),"") | K93: =VLOOKUP(J93,CPDK,2,0) -> #N/A | L93: =VLOOKUP(J93,F93:G488,2,0) -> #N/A
C94: =CONCATENATE($A$81," ",B94) -> [Gia Lai] | E94: =IF(ISNUMBER(SEARCH($I$4,C94)),MAX($E$3:E93)+1,"") | F94: =C94 -> [Gia Lai] | J94: =IFERROR(INDEX(C94:C489,MATCH(ROW()-3,E94:E489,0),1),"") | K94: =VLOOKUP(J94,CPDK,2,0) -> #N/A | L94: =VLOOKUP(J94,F94:G489,2,0) -> #N/A
C95: =CONCATENATE($A$81," ",B95) -> [Gia Lai] | E95: =IF(ISNUMBER(SEARCH($I$4,C95)),MAX($E$3:E94)+1,"") | F95: =C95 -> [Gia Lai] | J95: =IFERROR(INDEX(C95:C490,MATCH(ROW()-3,E95:E490,0),1),"") | K95: =VLOOKUP(J95,CPDK,2,0) -> #N/A | L95: =VLOOKUP(J95,F95:G490,2,0) -> #N/A
C96: =CONCATENATE($A$81," ",B96) -> [Gia Lai] | E96: =IF(ISNUMBER(SEARCH($I$4,C96)),MAX($E$3:E95)+1,"") | F96: =C96 -> [Gia Lai] | J96: =IFERROR(INDEX(C96:C491,MATCH(ROW()-3,E96:E491,0),1),"") | K96: =VLOOKUP(J96,CPDK,2,0) -> #N/A | L96: =VLOOKUP(J96,F96:G491,2,0) -> #N/A
C97: =CONCATENATE($A$81," ",B97) -> [Gia Lai] | E97: =IF(ISNUMBER(SEARCH($I$4,C97)),MAX($E$3:E96)+1,"") | F97: =C97 -> [Gia Lai] | J97: =IFERROR(INDEX(C97:C492,MATCH(ROW()-3,E97:E492,0),1),"") | K97: =VLOOKUP(J97,CPDK,2,0) -> #N/A | L97: =VLOOKUP(J97,F97:G492,2,0) -> #N/A
A98: [Kon Tum] | B98: VNEID - TOÀN TRÌNH (KHÔNG XE) | C98: =CONCATENATE($A$98," ",B98) -> [Kon Tum] VNEID - TOÀN TRÌNH (KHÔNG XE) | D98: 7000000 | E98: =IF(ISNUMBER(SEARCH($I$4,C98)),MAX($E$3:E97)+1,"") | F98: =C98 -> [Kon Tum] VNEID - TOÀN TRÌNH (KHÔNG XE) | J98: =IFERROR(INDEX(C98:C493,MATCH(ROW()-3,E98:E493,0),1),"") | K98: =VLOOKUP(J98,CPDK,2,0) -> #N/A | L98: =VLOOKUP(J98,F98:G493,2,0) -> #N/A
B99: VNEID - TRUYỀN THỐNG (CÓ XE) | C99: =CONCATENATE($A$98," ",B99) -> [Kon Tum] VNEID - TRUYỀN THỐNG (CÓ XE) | D99: 8000000 | E99: =IF(ISNUMBER(SEARCH($I$4,C99)),MAX($E$3:E98)+1,"") | F99: =C99 -> [Kon Tum] VNEID - TRUYỀN THỐNG (CÓ XE) | J99: =IFERROR(INDEX(C99:C494,MATCH(ROW()-3,E99:E494,0),1),"") | K99: =VLOOKUP(J99,CPDK,2,0) -> #N/A | L99: =VLOOKUP(J99,F99:G494,2,0) -> #N/A
B100: PHÍ CÀ VẸT NHANH | C100: =CONCATENATE($A$98," ",B100) -> [Kon Tum] PHÍ CÀ VẸT NHANH | E100: =IF(ISNUMBER(SEARCH($I$4,C100)),MAX($E$3:E99)+1,"") | F100: =C100 -> [Kon Tum] PHÍ CÀ VẸT NHANH | J100: =IFERROR(INDEX(C100:C495,MATCH(ROW()-3,E100:E495,0),1),"") | K100: =VLOOKUP(J100,CPDK,2,0) -> #N/A | L100: =VLOOKUP(J100,F100:G495,2,0) -> #N/A
C101: =CONCATENATE($A$98," ",B101) -> [Kon Tum] | E101: =IF(ISNUMBER(SEARCH($I$4,C101)),MAX($E$3:E100)+1,"") | F101: =C101 -> [Kon Tum] | J101: =IFERROR(INDEX(C101:C496,MATCH(ROW()-3,E101:E496,0),1),"") | K101: =VLOOKUP(J101,CPDK,2,0) -> #N/A | L101: =VLOOKUP(J101,F101:G496,2,0) -> #N/A
...

Sheet CSG Tạm
A1: CHÍNH SÁCH GIÁ XE T7 | J1: 1 | L1: GIÁ XE HIỆN TẠI | N1: GIÁ XE BẢN CŨ
A2: STT | B2: MODEL | C2: GIÁ HTC | D2: XE 2020 | H2: XE 2021
D3: GIẢM GIÁ | E3: TẶNG PK | F3: THƯỞNG | G3: LƯƠNG NS | H3: GIẢM GIÁ | I3: TẶNG PK | J3: Giá HTC
A4: GRAND I10
A5: 1 | B5: Grand I10 Base | C5: 330000000 | H5: 5000000 | I5: 3 Món + Đụng deal liên hệ TP | J5: =L5 -> 325000000 | L5: =C5-H5 -> 325000000 | N5: =C5-D5 -> 330000000
A6: 2 | B6: Grand I10 MT | C6: 370000000 | H6: 16000000 | J6: =L6 -> 354000000 | L6: =C6-H6 -> 354000000 | N6: =C6-D6 -> 370000000
A7: 3 | B7: Grand I10 AT | C7: 405000000 | H7: 19000000 | J7: =L7 -> 386000000 | L7: =C7-H7 -> 386000000 | N7: =C7-D7 -> 405000000
A8: 4 | B8: Grand I10 SD Base | C8: 350000000 | H8: 6000000 | J8: =L8 -> 344000000 | L8: =C8-H8 -> 344000000 | N8: =C8-D8 -> 350000000
A9: 5 | B9: Grand I10 SD MT | C9: 390000000 | H9: 16000000 | J9: =L9 -> 374000000 | L9: =C9-H9 -> 374000000 | N9: =C9-D9 -> 390000000
A10: 6 | B10: Grand I10 SD AT | C10: 415000000 | H10: 17000000 | J10: =L10 -> 398000000 | L10: =C10-H10 -> 398000000 | N10: =C10-D10 -> 415000000
A11: ACCENT | L11: =C11-H11 -> 0 | N11: =C11-D11 -> 0
A12: 1 | B12: Accent MT Base | C12: 426000000 | H12: 18000000 | I12: 3 Món + Đụng deal liên hệ TP | J12: =L12 -> 408000000 | L12: =C12-H12 -> 408000000 | N12: =C12-D12 -> 426000000
A13: 2 | B13: Accent MT Full | C13: 472000000 | H13: 17000000 | J13: =L13 -> 455000000 | L13: =C13-H13 -> 455000000 | N13: =C13-D13 -> 472000000
A14: 3 | B14: Accent AT | C14: 501000000 | H14: 6000000 | J14: =L14 -> 495000000 | L14: =C14-H14 -> 495000000 | N14: =C14-D14 -> 501000000
A15: 4 | B15: Accent AT ĐB | C15: 542000000 | H15: 7000000 | J15: =L15 -> 535000000 | L15: =C15-H15 -> 535000000 | N15: =C15-D15 -> 542000000
A16: ELANTRA | L16: =C16-H16 -> 0 | N16: =C16-D16 -> 0
A17: 1 | B17: Elantra 1.6 MT | C17: 580000000 | H17: =11000000+15000000 -> 26000000 | I17: 3 Món + Đụng deal liên hệ TP | J17: =L17 -> 554000000 | L17: =C17-H17 -> 554000000 | N17: =C17-D17 -> 580000000
A18: 2 | B18: Elantra 1.6 AT | C18: 655000000 | H18: =12000000+15000000 -> 27000000 | J18: =L18 -> 628000000 | L18: =C18-H18 -> 628000000 | N18: =C18-D18 -> 655000000
A19: 3 | B19: Elantra 2.0 AT | C19: 699000000 | H19: =13000000+15000000 -> 28000000 | J19: =L19 -> 671000000 | L19: =C19-H19 -> 671000000 | N19: =C19-D19 -> 699000000
A20: 4 | B20: Elantra 1.6 Turbo | C20: 769000000 | H20: =14000000+20000000 -> 34000000 | J20: =L20 -> 735000000 | L20: =C20-H20 -> 735000000 | N20: =C20-D20 -> 769000000
A21: KONA | L21: =C21-H21 -> 0 | N21: =C21-D21 -> 0
A22: 1 | B22: Kona 2.0 TC | C22: 636000000 | H22: 61000000 | I22: 3 Món + Đụng deal liên hệ TP | J22: =L22 -> 575000000 | L22: =C22-H22 -> 575000000 | N22: =C22-D22 -> 636000000
A23: 2 | B23: Kona 2.0 ĐB | C23: 699000000 | H23: 62000000 | J23: =L23 -> 637000000 | L23: =C23-H23 -> 637000000 | N23: =C23-D23 -> 699000000
A24: 3 | B24: Kona 1.6 Turbo | C24: 750000000 | H24: 63000000 | J24: =L24 -> 687000000 | L24: =C24-H24 -> 687000000 | N24: =C24-D24 -> 750000000
A25: TUCSON | L25: =C25-H25 -> 0 | N25: =E25-J25 -> 0
A26: 1 | B26: Tucson 2.0 TC | C26: 799000000 | H26: 71000000 | I26: 3 Món + Đụng deal liên hệ TP | J26: =L26 -> 728000000 | L26: =C26-H26 -> 728000000 | N26: =C26-D26 -> 799000000
A27: 2 | B27: Tucson 2.0 ĐB | C27: 878000000 | H27: 74000000 | J27: =L27 -> 804000000 | L27: =C27-H27 -> 804000000 | N27: =C27-D27 -> 878000000
A28: 3 | B28: Tucson 1.6 Turbo | C28: 932000000 | H28: 76000000 | J28: =L28 -> 856000000 | L28: =C28-H28 -> 856000000 | N28: =C28-D28 -> 932000000
A29: 4 | B29: Tucson Dầu | C29: 940000000 | H29: 76000000 | J29: =L29 -> 864000000 | L29: =C29-H29 -> 864000000 | N29: =C29-D29 -> 940000000
A30: SANTAFE | L30: =C30-H30 -> 0 | N30: =E30-J30 -> 0
A31: 1 | B31: Santafe Xăng TC | C31: 1030000000 | H31: 19000000 | I31: 3 Món + Đụng deal liên hệ TP | J31: =L31 -> 1011000000 | L31: =C31-H31 -> 1011000000 | N31: =C31-D31 -> 1030000000
A32: 2 | B32: Santafe Xăng ĐB | C32: 1190000000 | H32: 20000000 | J32: =L32 -> 1170000000 | L32: =C32-H32 -> 1170000000 | N32: =C32-D32 -> 1190000000
A33: 2 | B33: Santafe Xăng CC | C33: 1240000000 | H33: 20000000 | J33: =L33 -> 1220000000 | L33: =C33-H33 -> 1220000000 | N33: =C33-D33 -> 1240000000
A34: 3 | B34: Santafe Dầu TC | C34: 1130000000 | H34: 20000000 | J34: =L34 -> 1110000000 | L34: =C34-H34 -> 1110000000 | N34: =C34-D34 -> 1130000000
A35: 5 | B35: Santafe Dầu ĐB | C35: 1290000000 | H35: 20000000 | J35: =L35 -> 1270000000 | L35: =C35-H35 -> 1270000000 | N35: =C35-D35 -> 1290000000
A36: 4 | B36: Santafe Dầu CC | C36: 1340000000 | H36: 20000000 | J36: =L36 -> 1320000000 | L36: =C36-H36 -> 1320000000 | N36: =C36-D36 -> 1340000000
A37: SOLATI | L37: =C37-H37 -> 0 | N37: =E37-J37 -> 0
A38: 1 | B38: Solati | C38: 1080000000 | D38: 105000000 | E38: 3 Món Phim Hộp | F38: - Không ghế : 940.000.000 - Có ghế : 970.000.000 (Thương lượng) - Ghế U : + 50.000.000 (Trần, Màn hình, Sàn ốp gỗ, Định vị , Camera lùi, Đèn trần) | L38: =C38-H38 -> 1080000000 | N38: =C38-D38 -> 975000000

Sheet BG03Y
A1: LỊCH TRẢ NỢ DỰ KIẾN
A2: KHÁCH HÀNG VAY
A3: Giá xe | D3: ='Thuế chấp'!D3 -> 846040000
A4: Tổng số tiền vay (VND) | D4: ='Thuế chấp'!D4 -> 761436000 | E4: Thời gian ưu đãi (tháng) | G4: 12
A5: Thời gian vay (tháng) | D5: 36 | E5: Lãi dự kiến sau ưu đãi (%/năm) | G5: ='Thuế chấp'!G5 -> 0.0925 | L5: 12
A6: Lãi suất ưu đãi (%/năm) | D6: ='Thuế chấp'!D6 -> 0.069 | E6: Ngày vay dự kiến | G6: ='Thuế chấp'!G6 -> 45958 | L6: 24
E7: Thời gian ân hạn gốc (tháng) | L7: 36
A8: =D5 -> 36 | G8: Tháng | L8: 48
A9: Ngày đóng | B9: Kỳ hạn | C9: Số ngày | D9: Trả gốc | E9: Trả lãi | F9: Total | G9: Dư nợ còn lại | L9: 60
A10: =$G$6 -> 45958 | B10: 0 | G10: =$D4-D10 -> 761436000 | L10: 72
A11: =IF(B10<$D$5,DATE(YEAR(A10),MONTH(A10)+1,DAY(A10)),IF(B10=$D$5,"Tổng","")) -> 45989 | B11: =IF(B10<$D$5,B10+1,"") -> 1 | C11: =IF(B11<>"",A11-A10,"") -> 31 | D11: =IF($B10<$D$5,IF(B10<$G$7,0,$D$4/($D$5-$G$7)),IF($B10=$D$5,$D$4,"")) -> 21151000 | E11: =IF(AND($B11<>"",$B11<=$G$4),$G10*C11*$D$6/360,IF(B11<>"",$G10*C11*$G$5/360,IF(AND(B10<>"",B10=$D$5),SUM($E$10:E10),""))) -> 4524198.9 | F11: =IF(D11<>"",D11+E11,"") -> 25675199 | G11: =IF($B11<>"",G10-D11,"") -> 740285000 | L11: 84
A12: =IF(B11<$D$5,DATE(YEAR(A11),MONTH(A11)+1,DAY(A11)),IF(B11=$D$5,"Tổng","")) -> 46019 | B12: =IF(B11<$D$5,B11+1,"") -> 2 | C12: =IF(B12<>"",A12-A11,"") -> 30 | D12: =IF($B11<$D$5,IF(B11<$G$7,0,$D$4/($D$5-$G$7)),IF($B11=$D$5,$D$4,"")) -> 21151000 | E12: =IF(AND($B12<>"",$B12<=$G$4),$G11*C12*$D$6/360,IF(B12<>"",$G11*C12*$G$5/360,IF(AND(B11<>"",B11=$D$5),SUM($E$10:E11),""))) -> 4256638.8 | F12: =IF(D12<>"",D12+E12,"") -> 25407639 | G12: =IF($B12<>"",G11-D12,"") -> 719134000 | L12: 96
A13: =IF(B12<$D$5,DATE(YEAR(A12),MONTH(A12)+1,DAY(A12)),IF(B12=$D$5,"Tổng","")) -> 46050 | B13: =IF(B12<$D$5,B12+1,"") -> 3 | C13: =IF(B13<>"",A13-A12,"") -> 31 | D13: =IF($B12<$D$5,IF(B12<$G$7,0,$D$4/($D$5-$G$7)),IF($B12=$D$5,$D$4,"")) -> 21151000 | E13: =IF(AND($B13<>"",$B13<=$G$4),$G12*C13*$D$6/360,IF(B13<>"",$G12*C13*$G$5/360,IF(AND(B12<>"",B12=$D$5),SUM($E$10:E12),""))) -> 4272854.5 | F13: =IF(D13<>"",D13+E13,"") -> 25423855 | G13: =IF($B13<>"",G12-D13,"") -> 697983000
A14: =IF(B13<$D$5,DATE(YEAR(A13),MONTH(A13)+1,DAY(A13)),IF(B13=$D$5,"Tổng","")) -> 46081 | B14: =IF(B13<$D$5,B13+1,"") -> 4 | C14: =IF(B14<>"",A14-A13,"") -> 31 | D14: =IF($B13<$D$5,IF(B13<$G$7,0,$D$4/($D$5-$G$7)),IF($B13=$D$5,$D$4,"")) -> 21151000 | E14: =IF(AND($B14<>"",$B14<=$G$4),$G13*C14*$D$6/360,IF(B14<>"",$G13*C14*$G$5/360,IF(AND(B13<>"",B13=$D$5),SUM($E$10:E13),""))) -> 4147182.3 | F14: =IF(D14<>"",D14+E14,"") -> 25298182 | G14: =IF($B14<>"",G13-D14,"") -> 676832000
A15: =IF(B14<$D$5,DATE(YEAR(A14),MONTH(A14)+1,DAY(A14)),IF(B14=$D$5,"Tổng","")) -> 46109 | B15: =IF(B14<$D$5,B14+1,"") -> 5 | C15: =IF(B15<>"",A15-A14,"") -> 28 | D15: =IF($B14<$D$5,IF(B14<$G$7,0,$D$4/($D$5-$G$7)),IF($B14=$D$5,$D$4,"")) -> 21151000 | E15: =IF(AND($B15<>"",$B15<=$G$4),$G14*C15*$D$6/360,IF(B15<>"",$G14*C15*$G$5/360,IF(AND(B14<>"",B14=$D$5),SUM($E$10:E14),""))) -> 3632331.7 | F15: =IF(D15<>"",D15+E15,"") -> 24783332 | G15: =IF($B15<>"",G14-D15,"") -> 655681000
A16: =IF(B15<$D$5,DATE(YEAR(A15),MONTH(A15)+1,DAY(A15)),IF(B15=$D$5,"Tổng","")) -> 46140 | B16: =IF(B15<$D$5,B15+1,"") -> 6 | C16: =IF(B16<>"",A16-A15,"") -> 31 | D16: =IF($B15<$D$5,IF(B15<$G$7,0,$D$4/($D$5-$G$7)),IF($B15=$D$5,$D$4,"")) -> 21151000 | E16: =IF(AND($B16<>"",$B16<=$G$4),$G15*C16*$D$6/360,IF(B16<>"",$G15*C16*$G$5/360,IF(AND(B15<>"",B15=$D$5),SUM($E$10:E15),""))) -> 3895837.9 | F16: =IF(D16<>"",D16+E16,"") -> 25046838 | G16: =IF($B16<>"",G15-D16,"") -> 634530000
A17: =IF(B16<$D$5,DATE(YEAR(A16),MONTH(A16)+1,DAY(A16)),IF(B16=$D$5,"Tổng","")) -> 46170 | B17: =IF(B16<$D$5,B16+1,"") -> 7 | C17: =IF(B17<>"",A17-A16,"") -> 30 | D17: =IF($B16<$D$5,IF(B16<$G$7,0,$D$4/($D$5-$G$7)),IF($B16=$D$5,$D$4,"")) -> 21151000 | E17: =IF(AND($B17<>"",$B17<=$G$4),$G16*C17*$D$6/360,IF(B17<>"",$G16*C17*$G$5/360,IF(AND(B16<>"",B16=$D$5),SUM($E$10:E16),""))) -> 3648547.5 | F17: =IF(D17<>"",D17+E17,"") -> 24799548 | G17: =IF($B17<>"",G16-D17,"") -> 613379000
A18: =IF(B17<$D$5,DATE(YEAR(A17),MONTH(A17)+1,DAY(A17)),IF(B17=$D$5,"Tổng","")) -> 46201 | B18: =IF(B17<$D$5,B17+1,"") -> 8 | C18: =IF(B18<>"",A18-A17,"") -> 31 | D18: =IF($B17<$D$5,IF(B17<$G$7,0,$D$4/($D$5-$G$7)),IF($B17=$D$5,$D$4,"")) -> 21151000 | E18: =IF(AND($B18<>"",$B18<=$G$4),$G17*C18*$D$6/360,IF(B18<>"",$G17*C18*$G$5/360,IF(AND(B17<>"",B17=$D$5),SUM($E$10:E17),""))) -> 3644493.6 | F18: =IF(D18<>"",D18+E18,"") -> 24795494 | G18: =IF($B18<>"",G17-D18,"") -> 592228000
A19: =IF(B18<$D$5,DATE(YEAR(A18),MONTH(A18)+1,DAY(A18)),IF(B18=$D$5,"Tổng","")) -> 46231 | B19: =IF(B18<$D$5,B18+1,"") -> 9 | C19: =IF(B19<>"",A19-A18,"") -> 30 | D19: =IF($B18<$D$5,IF(B18<$G$7,0,$D$4/($D$5-$G$7)),IF($B18=$D$5,$D$4,"")) -> 21151000 | E19: =IF(AND($B19<>"",$B19<=$G$4),$G18*C19*$D$6/360,IF(B19<>"",$G18*C19*$G$5/360,IF(AND(B18<>"",B18=$D$5),SUM($E$10:E18),""))) -> 3405311 | F19: =IF(D19<>"",D19+E19,"") -> 24556311 | G19: =IF($B19<>"",G18-D19,"") -> 571077000
A20: =IF(B19<$D$5,DATE(YEAR(A19),MONTH(A19)+1,DAY(A19)),IF(B19=$D$5,"Tổng","")) -> 46262 | B20: =IF(B19<$D$5,B19+1,"") -> 10 | C20: =IF(B20<>"",A20-A19,"") -> 31 | D20: =IF($B19<$D$5,IF(B19<$G$7,0,$D$4/($D$5-$G$7)),IF($B19=$D$5,$D$4,"")) -> 21151000 | E20: =IF(AND($B20<>"",$B20<=$G$4),$G19*C20*$D$6/360,IF(B20<>"",$G19*C20*$G$5/360,IF(AND(B19<>"",B19=$D$5),SUM($E$10:E19),""))) -> 3393149.2 | F20: =IF(D20<>"",D20+E20,"") -> 24544149 | G20: =IF($B20<>"",G19-D20,"") -> 549926000
A21: =IF(B20<$D$5,DATE(YEAR(A20),MONTH(A20)+1,DAY(A20)),IF(B20=$D$5,"Tổng","")) -> 46293 | B21: =IF(B20<$D$5,B20+1,"") -> 11 | C21: =IF(B21<>"",A21-A20,"") -> 31 | D21: =IF($B20<$D$5,IF(B20<$G$7,0,$D$4/($D$5-$G$7)),IF($B20=$D$5,$D$4,"")) -> 21151000 | E21: =IF(AND($B21<>"",$B21<=$G$4),$G20*C21*$D$6/360,IF(B21<>"",$G20*C21*$G$5/360,IF(AND(B20<>"",B20=$D$5),SUM($E$10:E20),""))) -> 3267477 | F21: =IF(D21<>"",D21+E21,"") -> 24418477 | G21: =IF($B21<>"",G20-D21,"") -> 528775000
A22: =IF(B21<$D$5,DATE(YEAR(A21),MONTH(A21)+1,DAY(A21)),IF(B21=$D$5,"Tổng","")) -> 46323 | B22: =IF(B21<$D$5,B21+1,"") -> 12 | C22: =IF(B22<>"",A22-A21,"") -> 30 | D22: =IF($B21<$D$5,IF(B21<$G$7,0,$D$4/($D$5-$G$7)),IF($B21=$D$5,$D$4,"")) -> 21151000 | E22: =IF(AND($B22<>"",$B22<=$G$4),$G21*C22*$D$6/360,IF(B22<>"",$G21*C22*$G$5/360,IF(AND(B21<>"",B21=$D$5),SUM($E$10:E21),""))) -> 3040456.2 | F22: =IF(D22<>"",D22+E22,"") -> 24191456 | G22: =IF($B22<>"",G21-D22,"") -> 507624000
A23: =IF(B22<$D$5,DATE(YEAR(A22),MONTH(A22)+1,DAY(A22)),IF(B22=$D$5,"Tổng","")) -> 46354 | B23: =IF(B22<$D$5,B22+1,"") -> 13 | C23: =IF(B23<>"",A23-A22,"") -> 31 | D23: =IF($B22<$D$5,IF(B22<$G$7,0,$D$4/($D$5-$G$7)),IF($B22=$D$5,$D$4,"")) -> 21151000 | E23: =IF(AND($B23<>"",$B23<=$G$4),$G22*C23*$D$6/360,IF(B23<>"",$G22*C23*$G$5/360,IF(AND(B22<>"",B22=$D$5),SUM($E$10:E22),""))) -> 4043366.2 | F23: =IF(D23<>"",D23+E23,"") -> 25194366 | G23: =IF($B23<>"",G22-D23,"") -> 486473000
A24: =IF(B23<$D$5,DATE(YEAR(A23),MONTH(A23)+1,DAY(A23)),IF(B23=$D$5,"Tổng","")) -> 46384 | B24: =IF(B23<$D$5,B23+1,"") -> 14 | C24: =IF(B24<>"",A24-A23,"") -> 30 | D24: =IF($B23<$D$5,IF(B23<$G$7,0,$D$4/($D$5-$G$7)),IF($B23=$D$5,$D$4,"")) -> 21151000 | E24: =IF(AND($B24<>"",$B24<=$G$4),$G23*C24*$D$6/360,IF(B24<>"",$G23*C24*$G$5/360,IF(AND(B23<>"",B23=$D$5),SUM($E$10:E23),""))) -> 3749896 | F24: =IF(D24<>"",D24+E24,"") -> 24900896 | G24: =IF($B24<>"",G23-D24,"") -> 465322000
... A195: =IF(B194<$D$5,DATE(YEAR(A194),MONTH(A194)+1,DAY(A194)),IF(B194=$D$5,"Tổng","")) | B195: =IF(B194<$D$5,B194+1,"") | C195: =IF(B195<>"",A195-A194,"") | D195: =IF($B194<$D$5,IF(B194<$G$7,0,$D$4/($D$5-$G$7)),IF($B194=$D$5,$D$4,"")) | E195: =IF(AND($B195<>"",$B195<=$G$4),$G194*C195*$D$6/360,IF(B195<>"",$G194*C195*$G$5/360,IF(AND(B194<>"",B194=$D$5),SUM($E$10:E194),""))) | F195: =IF(D195<>"",D195+E195,"") | G195: =IF($B195<>"",G194-D195,"")
A196: =IF(B195<$D$5,DATE(YEAR(A195),MONTH(A195)+1,DAY(A195)),IF(B195=$D$5,"Tổng","")) | B196: =IF(B195<$D$5,B195+1,"") | C196: =IF(B196<>"",A196-A195,"") | D196: =IF($B195<$D$5,$D$4/$D$5,IF($B195=$D$5,$D$4,"")) | E196: =IF(AND($B196<>"",$B196<=$G$4),$G195*C196*$D$6/360,IF(B196<>"",$G195*C196*$G$5/360,IF(AND(B195<>"",B195=$D$5),SUM($E$10:E195),""))) | F196: =IF(D196<>"",D196+E196,"") | G196: =IF($B196<>"",G195-D196,"")
A197: =IF(B196<$D$5,DATE(YEAR(A196),MONTH(A196)+1,DAY(A196)),IF(B196=$D$5,"Tổng","")) | B197: =IF(B196<$D$5,B196+1,"") | C197: =IF(B197<>"",A197-A196,"") | D197: =IF($B196<$D$5,$D$4/$D$5,IF($B196=$D$5,$D$4,"")) | E197: =IF(AND($B197<>"",$B197<=$G$4),$G196*C197*$D$6/360,IF(B197<>"",$G196*C197*$G$5/360,IF(AND(B196<>"",B196=$D$5),SUM($E$10:E196),""))) | F197: =IF(D197<>"",D197+E197,"") | G197: =IF($B197<>"",G196-D197,"")
